{
    },
    {
      "LeagueName": "Today",
      "LeagueLogo": "",
      "GameTime": "",
      "GameState": "",
      "HomeTeam": "",
      "HomeGoals": "",
      "HomeLogo": "",
      "AwayTeam": "",
      "AwayGoals": "",
      "AwayLogo": "",
      "TVChannels": "LeagueHeader"
    }
  ],
    },
    {
      "LeagueName": "Today",
      "LeagueLogo": "",
      "GameTime": "",
      "GameState": "",
      "HomeTeam": "",
      "HomeGoals": "",
      "HomeLogo": "",
      "AwayTeam": "",
      "AwayGoals": "",
      "AwayLogo": "",
      "TVChannels": "LeagueHeader"
    }
  ],
    },
    {
      "LeagueName": "Today",
      "LeagueLogo": "",
      "GameTime": "",
      "GameState": "",
      "HomeTeam": "",
      "HomeGoals": "",
      "HomeLogo": "",
      "AwayTeam": "",
      "AwayGoals": "",
      "AwayLogo": "",
      "TVChannels": "LeagueHeader"
    }
  ],
    },
    {
      "LeagueName": "Today",
      "LeagueLogo": "",
      "GameTime": "",
      "GameState": "",
      "HomeTeam": "",
      "HomeGoals": "",
      "HomeLogo": "",
      "AwayTeam": "",
      "AwayGoals": "",
      "AwayLogo": "",
      "TVChannels": "LeagueHeader"
    }
  ],
  "day5": [
    {
      "LeagueName": "English Premier League",
      "LeagueLogo": "https://a.espncdn.com/i/leaguelogos/soccer/500/23.png",
      "GameTime": "Monday Oct. 19, 2020",
      "GameState": "",
      "HomeTeam": "",
      "HomeGoals": "",
      "HomeLogo": "",
      "AwayTeam": "",
      "AwayGoals": "",
      "AwayLogo": "",
      "TVChannels": "LeagueHeader"
    },
    {
      "LeagueName": "English Premier League",
      "LeagueLogo": "https://a.espncdn.com/i/leaguelogos/soccer/500/23.png",
      "GameTime": "12:30pm",
      "GameState": "",
      "HomeTeam": "West Bromwich",
      "HomeGoals": "",
      "HomeLogo": "https://a.espncdn.com/i/teamlogos/soccer/500/383.png",
      "AwayTeam": "Burnley",
      "AwayGoals": "",
      "AwayLogo": "https://a.espncdn.com/i/teamlogos/soccer/500/379.png",
      "TVChannels": "NBCSN ,  fuboTV ,  NBCSports.com ,  …"
    },
    {
      "LeagueName": "English Premier League",
      "LeagueLogo": "https://a.espncdn.com/i/leaguelogos/soccer/500/23.png",
      "GameTime": "3:00pm",
      "GameState": "",
      "HomeTeam": "Leeds United",
      "HomeGoals": "",
      "HomeLogo": "https://a.espncdn.com/i/teamlogos/soccer/500/357.png",
      "AwayTeam": "Wolves",
      "AwayGoals": "",
      "AwayLogo": "https://a.espncdn.com/i/teamlogos/soccer/500/380.png",
      "TVChannels": "NBCSN ,  fuboTV ,  NBCSports.com ,  …"
    },
    {
      "LeagueName": "Italian Serie A",
      "LeagueLogo": "https://a.espncdn.com/i/leaguelogos/soccer/500/12.png",
      "GameTime": "Monday Oct. 19, 2020",
      "GameState": "",
      "HomeTeam": "",
      "HomeGoals": "",
      "HomeLogo": "",
      "AwayTeam": "",
      "AwayGoals": "",
      "AwayLogo": "",
      "TVChannels": "LeagueHeader"
    },
    {
      "LeagueName": "Italian Serie A",
      "LeagueLogo": "https://a.espncdn.com/i/leaguelogos/soccer/500/12.png",
      "GameTime": "2:45pm",
      "GameState": "",
      "HomeTeam": "Hellas Verona",
      "HomeGoals": "",
      "HomeLogo": "https://a.espncdn.com/i/teamlogos/soccer/500/119.png",
      "AwayTeam": "Genoa",
      "AwayGoals": "",
      "AwayLogo": "https://a.espncdn.com/i/teamlogos/soccer/500/3263.png",
      "TVChannels": "ESPN App ,  DAZN ,  DAZN ,  Sport TV3 ,  Premier…"
    },
    {
      "LeagueName": "Major League Soccer",
      "LeagueLogo": "https://a.espncdn.com/i/leaguelogos/soccer/500/19.png",
      "GameTime": "Monday Oct. 19, 2020",
      "GameState": "",
      "HomeTeam": "",
      "HomeGoals": "",
      "HomeLogo": "",
      "AwayTeam": "",
      "AwayGoals": "",
      "AwayLogo": "",
      "TVChannels": "LeagueHeader"
    },
    {
      "LeagueName": "Major League Soccer",
      "LeagueLogo": "https://a.espncdn.com/i/leaguelogos/soccer/500/19.png",
      "GameTime": "7:30pm",
      "GameState": "",
      "HomeTeam": "NE Revolution",
      "HomeGoals": "",
      "HomeLogo": "https://a.espncdn.com/i/teamlogos/soccer/500/189.png",
      "AwayTeam": "Philadelphia Union",
      "AwayGoals": "",
      "AwayLogo": "https://a.espncdn.com/i/teamlogos/soccer/500/10739.png",
      "TVChannels": "ESPN+ ,  fuboTV ,  NBCSports…"
    }
  ],
  "day6": [
    {
      "LeagueName": "UEFA Champions League",
      "LeagueLogo": "https://a.espncdn.com/i/leaguelogos/soccer/500/2.png",
      "GameTime": "Tuesday Oct. 20, 2020",
      "GameState": "",
      "HomeTeam": "",
      "HomeGoals": "",
      "HomeLogo": "",
      "AwayTeam": "",
      "AwayGoals": "",
      "AwayLogo": "",
      "TVChannels": "LeagueHeader"
    },
    {
      "LeagueName": "UEFA Champions League",
      "LeagueLogo": "https://a.espncdn.com/i/leaguelogos/soccer/500/2.png",
      "GameTime": "12:55pm",
      "GameState": "",
      "HomeTeam": "Zenit",
      "HomeGoals": "",
      "HomeLogo": "",
      "AwayTeam": "Club Brugge fuboTV ,  Galavision ,  TUDN.com ,  …",
      "AwayGoals": "",
      "AwayLogo": "",
      "TVChannels": "12:55pm   Zenit vs Club Brugge fuboTV ,  Galavision ,  TUDN.com ,  …"
    },
    {
      "LeagueName": "UEFA Champions League",
      "LeagueLogo": "https://a.espncdn.com/i/leaguelogos/soccer/500/2.png",
      "GameTime": "12:55pm",
      "GameState": "",
      "HomeTeam": "Dynamo Kyiv",
      "HomeGoals": "",
      "HomeLogo": "https://cdn.livesoccertv.com/images/teams/ukraine/logos/dynamo-kyiv.png",
      "AwayTeam": "Juventus",
      "AwayGoals": "",
      "AwayLogo": "https://a.espncdn.com/i/teamlogos/soccer/500/111.png",
      "TVChannels": "fuboTV ,  TUDN USA ,  UniMás ,  …"
    },
    {
      "LeagueName": "UEFA Champions League",
      "LeagueLogo": "https://a.espncdn.com/i/leaguelogos/soccer/500/2.png",
      "GameTime": "3:00pm",
      "GameState": "",
      "HomeTeam": "Chelsea",
      "HomeGoals": "",
      "HomeLogo": "https://a.espncdn.com/i/teamlogos/soccer/500/363.png",
      "AwayTeam": "Sevilla FC",
      "AwayGoals": "",
      "AwayLogo": "https://a.espncdn.com/i/teamlogos/soccer/500/243.png",
      "TVChannels": "fuboTV ,  TUDN.com ,  TUDNxtr…"
    },
    {
      "LeagueName": "UEFA Champions League",
      "LeagueLogo": "https://a.espncdn.com/i/leaguelogos/soccer/500/2.png",
      "GameTime": "3:00pm",
      "GameState": "",
      "HomeTeam": "Stade Rennes",
      "HomeGoals": "",
      "HomeLogo": "https://a.espncdn.com/i/teamlogos/soccer/500/169.png",
      "AwayTeam": "Krasnodar fuboTV ,  TUDN.com ,  TUDNxtr…",
      "AwayGoals": "",
      "AwayLogo": "",
      "TVChannels": "vs Krasnodar fuboTV ,  TUDN.com ,  TUDNxtr…"
    },
    {
      "LeagueName": "UEFA Champions League",
      "LeagueLogo": "https://a.espncdn.com/i/leaguelogos/soccer/500/2.png",
      "GameTime": "3:00pm",
      "GameState": "",
      "HomeTeam": "Lazio",
      "HomeGoals": "",
      "HomeLogo": "https://a.espncdn.com/i/teamlogos/soccer/500/112.png",
      "AwayTeam": "Borussia Dortmund",
      "AwayGoals": "",
      "AwayLogo": "https://a.espncdn.com/i/teamlogos/soccer/500/124.png",
      "TVChannels": "fuboTV ,  TUDN.com ,  TUDNxtr…"
    },
    {
      "LeagueName": "UEFA Champions League",
      "LeagueLogo": "https://a.espncdn.com/i/leaguelogos/soccer/500/2.png",
      "GameTime": "3:00pm",
      "GameState": "",
      "HomeTeam": "Barcelona",
      "HomeGoals": "",
      "HomeLogo": "https://a.espncdn.com/i/teamlogos/soccer/500/83.png",
      "AwayTeam": "Ferencváros",
      "AwayGoals": "",
      "AwayLogo": "https://cdn.livesoccertv.com/images/teams/hungary/logos/ferencvaros.png",
      "TVChannels": "fuboTV ,  TUDN USA ,  UniMás ,  …"
    },
    {
      "LeagueName": "UEFA Champions League",
      "LeagueLogo": "https://a.espncdn.com/i/leaguelogos/soccer/500/2.png",
      "GameTime": "3:00pm",
      "GameState": "",
      "HomeTeam": "PSG",
      "HomeGoals": "",
      "HomeLogo": "https://a.espncdn.com/i/teamlogos/soccer/500/160.png",
      "AwayTeam": "Manchester Utd",
      "AwayGoals": "",
      "AwayLogo": "https://a.espncdn.com/i/teamlogos/soccer/500/360.png",
      "TVChannels": "fuboTV ,  Galavision ,  TUDN.com ,  …"
    },
    {
      "LeagueName": "UEFA Champions League",
      "LeagueLogo": "https://a.espncdn.com/i/leaguelogos/soccer/500/2.png",
      "GameTime": "3:00pm",
      "GameState": "",
      "HomeTeam": "RB Leipzig",
      "HomeGoals": "",
      "HomeLogo": "https://a.espncdn.com/i/teamlogos/soccer/500/11420.png",
      "AwayTeam": "İstanbul Başakşehir fuboTV ,  TUDN.com ,  TUDNxtr…",
      "AwayGoals": "",
      "AwayLogo": "",
      "TVChannels": "vs İstanbul Başakşehir fuboTV ,  TUDN.com ,  TUDNxtr…"
    },
    {
      "LeagueName": "Major League Soccer",
      "LeagueLogo": "https://a.espncdn.com/i/leaguelogos/soccer/500/19.png",
      "GameTime": "Tuesday Oct. 20, 2020",
      "GameState": "",
      "HomeTeam": "",
      "HomeGoals": "",
      "HomeLogo": "",
      "AwayTeam": "",
      "AwayGoals": "",
      "AwayLogo": "",
      "TVChannels": "LeagueHeader"
    },
    {
      "LeagueName": "Major League Soccer",
      "LeagueLogo": "https://a.espncdn.com/i/leaguelogos/soccer/500/19.png",
      "GameTime": "8:30pm",
      "GameState": "",
      "HomeTeam": "Nashville SC",
      "HomeGoals": "",
      "HomeLogo": "https://a.espncdn.com/i/teamlogos/soccer/500/18986.png",
      "AwayTeam": "FC Dallas",
      "AwayGoals": "",
      "AwayLogo": "https://a.espncdn.com/i/teamlogos/soccer/500/185.png",
      "TVChannels": "Fox Sports 1 ,  fuboTV ,  FOX Deportes ,  …"
    }
  ],
  "day7": [
    {
      "LeagueName": "UEFA Champions League",
      "LeagueLogo": "https://a.espncdn.com/i/leaguelogos/soccer/500/2.png",
      "GameTime": "Wednesday Oct. 21, 2020",
      "GameState": "",
      "HomeTeam": "",
      "HomeGoals": "",
      "HomeLogo": "",
      "AwayTeam": "",
      "AwayGoals": "",
      "AwayLogo": "",
      "TVChannels": "LeagueHeader"
    },
    {
      "LeagueName": "UEFA Champions League",
      "LeagueLogo": "https://a.espncdn.com/i/leaguelogos/soccer/500/2.png",
      "GameTime": "12:55pm",
      "GameState": "",
      "HomeTeam": "Salzburg",
      "HomeGoals": "",
      "HomeLogo": "",
      "AwayTeam": "Lokomotiv Moskva fuboTV ,  Galavision ,  TUDN.com ,  …",
      "AwayGoals": "",
      "AwayLogo": "",
      "TVChannels": "12:55pm   Salzburg vs Lokomotiv Moskva fuboTV ,  Galavision ,  TUDN.com ,  …"
    },
    {
      "LeagueName": "UEFA Champions League",
      "LeagueLogo": "https://a.espncdn.com/i/leaguelogos/soccer/500/2.png",
      "GameTime": "12:55pm",
      "GameState": "",
      "HomeTeam": "Real Madrid",
      "HomeGoals": "",
      "HomeLogo": "https://a.espncdn.com/i/teamlogos/soccer/500/86.png",
      "AwayTeam": "Shakhtar Donetsk",
      "AwayGoals": "",
      "AwayLogo": "https://a.espncdn.com/combiner/i?img=/i/teamlogos/soccer/500/493.png",
      "TVChannels": "fuboTV ,  TUDN USA ,  UniMás ,  …"
    },
    {
      "LeagueName": "UEFA Champions League",
      "LeagueLogo": "https://a.espncdn.com/i/leaguelogos/soccer/500/2.png",
      "GameTime": "3:00pm",
      "GameState": "",
      "HomeTeam": "Bayern Munich",
      "HomeGoals": "",
      "HomeLogo": "https://a.espncdn.com/i/teamlogos/soccer/500/132.png",
      "AwayTeam": "Atletico Madrid",
      "AwayGoals": "",
      "AwayLogo": "https://a.espncdn.com/i/teamlogos/soccer/500/1068.png",
      "TVChannels": "ern München vs Atlético Madrid fuboTV ,  TUDN USA ,  UniMás ,  …"
    },
    {
      "LeagueName": "UEFA Champions League",
      "LeagueLogo": "https://a.espncdn.com/i/leaguelogos/soccer/500/2.png",
      "GameTime": "3:00pm",
      "GameState": "",
      "HomeTeam": "Inter",
      "HomeGoals": "",
      "HomeLogo": "https://a.espncdn.com/i/teamlogos/soccer/500/110.png",
      "AwayTeam": "Borussia M'gladbach",
      "AwayGoals": "",
      "AwayLogo": "https://a.espncdn.com/i/teamlogos/soccer/500/268.png",
      "TVChannels": "fuboTV ,  TUDN.com ,  TUDNxtr…"
    },
    {
      "LeagueName": "UEFA Champions League",
      "LeagueLogo": "https://a.espncdn.com/i/leaguelogos/soccer/500/2.png",
      "GameTime": "3:00pm",
      "GameState": "",
      "HomeTeam": "Manchester City",
      "HomeGoals": "",
      "HomeLogo": "https://a.espncdn.com/i/teamlogos/soccer/500/382.png",
      "AwayTeam": "Porto fuboTV ,  Galavision ,  TUDN.com ,  …",
      "AwayGoals": "",
      "AwayLogo": "",
      "TVChannels": "vs Porto fuboTV ,  Galavision ,  TUDN.com ,  …"
    },
    {
      "LeagueName": "UEFA Champions League",
      "LeagueLogo": "https://a.espncdn.com/i/leaguelogos/soccer/500/2.png",
      "GameTime": "3:00pm",
      "GameState": "",
      "HomeTeam": "Olympiakos Piraeus",
      "HomeGoals": "",
      "HomeLogo": "",
      "AwayTeam": "Marseille",
      "AwayGoals": "",
      "AwayLogo": "https://a.espncdn.com/i/teamlogos/soccer/500/176.png",
      "TVChannels": "fuboTV ,  TUDN.com ,  TUDNxtr…"
    },
    {
      "LeagueName": "UEFA Champions League",
      "LeagueLogo": "https://a.espncdn.com/i/leaguelogos/soccer/500/2.png",
      "GameTime": "3:00pm",
      "GameState": "",
      "HomeTeam": "Ajax",
      "HomeGoals": "",
      "HomeLogo": "",
      "AwayTeam": "Liverpool",
      "AwayGoals": "",
      "AwayLogo": "https://a.espncdn.com/i/teamlogos/soccer/500/364.png",
      "TVChannels": "fuboTV ,  TUDN.com ,  TUDNxtr…"
    },
    {
      "LeagueName": "UEFA Champions League",
      "LeagueLogo": "https://a.espncdn.com/i/leaguelogos/soccer/500/2.png",
      "GameTime": "3:00pm",
      "GameState": "",
      "HomeTeam": "FC Midtjylland",
      "HomeGoals": "",
      "HomeLogo": "https://a.espncdn.com/i/teamlogos/soccer/500/572.png",
      "AwayTeam": "Atalanta",
      "AwayGoals": "",
      "AwayLogo": "https://a.espncdn.com/i/teamlogos/soccer/500/105.png",
      "TVChannels": "fuboTV ,  TUDN.com ,  TUDNxtr…"
    }
  ]
}
