{
  "today": [
    {
      "LeagueName": "UEFA Champions League",
      "LeagueLogo": "https://a.espncdn.com/i/leaguelogos/soccer/500/2.png",
      "GameTime": "Wednesday Nov. 25, 2020",
      "GameState": "",
      "HomeTeam": "",
      "HomeGoals": "",
      "HomeLogo": "",
      "AwayTeam": "",
      "AwayGoals": "",
      "AwayLogo": "",
      "TVChannels": "LeagueHeader"
    },
    {
      "LeagueName": "UEFA Champions League",
      "LeagueLogo": "https://a.espncdn.com/i/leaguelogos/soccer/500/2.png",
      "GameTime": "12:55pm",
      "GameState": "",
      "HomeTeam": "Borussia M'gladbach",
      "HomeGoals": "",
      "HomeLogo": "https://a.espncdn.com/i/teamlogos/soccer/500/268.png",
      "AwayTeam": "Shakhtar Donetsk",
      "AwayGoals": "",
      "AwayLogo": "https://a.espncdn.com/combiner/i?img=/i/teamlogos/soccer/500/493.png",
      "TVChannels": "fuboTV ,  Galavision ,  TUDN.com ,  …"
    },
    {
      "LeagueName": "UEFA Champions League",
      "LeagueLogo": "https://a.espncdn.com/i/leaguelogos/soccer/500/2.png",
      "GameTime": "12:55pm",
      "GameState": "",
      "HomeTeam": "Olympiakos",
      "HomeGoals": "",
      "HomeLogo": "https://a.espncdn.com/i/teamlogos/soccer/500/435.png",
      "AwayTeam": "Manchester City",
      "AwayGoals": "",
      "AwayLogo": "https://a.espncdn.com/i/teamlogos/soccer/500/382.png",
      "TVChannels": "fuboTV ,  TUDN USA ,  UniMás ,  …"
    },
    {
      "LeagueName": "UEFA Champions League",
      "LeagueLogo": "https://a.espncdn.com/i/leaguelogos/soccer/500/2.png",
      "GameTime": "3:00pm",
      "GameState": "",
      "HomeTeam": "Bayern Munich",
      "HomeGoals": "",
      "HomeLogo": "https://a.espncdn.com/i/teamlogos/soccer/500/132.png",
      "AwayTeam": "Salzburg",
      "AwayGoals": "",
      "AwayLogo": "https://a.espncdn.com/i/teamlogos/soccer/500/2790.png",
      "TVChannels": "fuboTV ,  TUDN.com ,  TUDNxtr…"
    },
    {
      "LeagueName": "UEFA Champions League",
      "LeagueLogo": "https://a.espncdn.com/i/leaguelogos/soccer/500/2.png",
      "GameTime": "3:00pm",
      "GameState": "",
      "HomeTeam": "Atletico Madrid",
      "HomeGoals": "",
      "HomeLogo": "https://a.espncdn.com/i/teamlogos/soccer/500/1068.png",
      "AwayTeam": "Lokomotiv Moskva",
      "AwayGoals": "",
      "AwayLogo": "https://a.espncdn.com/i/teamlogos/soccer/500/442.png",
      "TVChannels": "fuboTV ,  Galavision ,  TUDN.com ,  …"
    },
    {
      "LeagueName": "UEFA Champions League",
      "LeagueLogo": "https://a.espncdn.com/i/leaguelogos/soccer/500/2.png",
      "GameTime": "3:00pm",
      "GameState": "",
      "HomeTeam": "Inter",
      "HomeGoals": "",
      "HomeLogo": "https://a.espncdn.com/i/teamlogos/soccer/500/110.png",
      "AwayTeam": "Real Madrid",
      "AwayGoals": "",
      "AwayLogo": "https://a.espncdn.com/i/teamlogos/soccer/500/86.png",
      "TVChannels": "fuboTV ,  TUDN USA ,  UniMás ,  …"
    },
    {
      "LeagueName": "UEFA Champions League",
      "LeagueLogo": "https://a.espncdn.com/i/leaguelogos/soccer/500/2.png",
      "GameTime": "3:00pm",
      "GameState": "",
      "HomeTeam": "Marseille",
      "HomeGoals": "",
      "HomeLogo": "https://a.espncdn.com/i/teamlogos/soccer/500/176.png",
      "AwayTeam": "Porto",
      "AwayGoals": "",
      "AwayLogo": "https://a.espncdn.com/i/teamlogos/soccer/500/437.png",
      "TVChannels": "fuboTV ,  TUDN.com ,  TUDNxtr…"
    },
    {
      "LeagueName": "UEFA Champions League",
      "LeagueLogo": "https://a.espncdn.com/i/leaguelogos/soccer/500/2.png",
      "GameTime": "3:00pm",
      "GameState": "",
      "HomeTeam": "Liverpool",
      "HomeGoals": "",
      "HomeLogo": "https://a.espncdn.com/i/teamlogos/soccer/500/364.png",
      "AwayTeam": "Atalanta",
      "AwayGoals": "",
      "AwayLogo": "https://a.espncdn.com/i/teamlogos/soccer/500/105.png",
      "TVChannels": "fuboTV ,  TUDN.com ,  TUDNxtr…"
    },
    {
      "LeagueName": "UEFA Champions League",
      "LeagueLogo": "https://a.espncdn.com/i/leaguelogos/soccer/500/2.png",
      "GameTime": "3:00pm",
      "GameState": "",
      "HomeTeam": "Ajax",
      "HomeGoals": "",
      "HomeLogo": "https://a.espncdn.com/i/teamlogos/soccer/500/139.png",
      "AwayTeam": "FC Midtjylland",
      "AwayGoals": "",
      "AwayLogo": "https://a.espncdn.com/i/teamlogos/soccer/500/572.png",
      "TVChannels": "fuboTV ,  TUDN.com ,  TUDNxtr…"
    },
    {
      "LeagueName": "French Ligue 1",
      "LeagueLogo": "https://a.espncdn.com/i/leaguelogos/soccer/500/9.png",
      "GameTime": "Wednesday Nov. 25, 2020",
      "GameState": "",
      "HomeTeam": "",
      "HomeGoals": "",
      "HomeLogo": "",
      "AwayTeam": "",
      "AwayGoals": "",
      "AwayLogo": "",
      "TVChannels": "LeagueHeader"
    },
    {
      "LeagueName": "French Ligue 1",
      "LeagueLogo": "https://a.espncdn.com/i/leaguelogos/soccer/500/9.png",
      "GameTime": "1:00pm",
      "GameState": "",
      "HomeTeam": "Lens",
      "HomeGoals": "",
      "HomeLogo": "https://a.espncdn.com/i/teamlogos/soccer/500/175.png",
      "AwayTeam": "Nantes",
      "AwayGoals": "",
      "AwayLogo": "https://a.espncdn.com/i/teamlogos/soccer/500/165.png",
      "TVChannels": "beIN SPORTS XTRA ,  ESPN Play Norte ,  …"
    }
  ],
  "day2": [
    {
      "LeagueName": "UEFA Europa League",
      "LeagueLogo": "https://a.espncdn.com/i/leaguelogos/soccer/500/2310.png",
      "GameTime": "Thursday Nov. 26, 2020",
      "GameState": "",
      "HomeTeam": "",
      "HomeGoals": "",
      "HomeLogo": "",
      "AwayTeam": "",
      "AwayGoals": "",
      "AwayLogo": "",
      "TVChannels": "LeagueHeader"
    },
    {
      "LeagueName": "UEFA Europa League",
      "LeagueLogo": "https://a.espncdn.com/i/leaguelogos/soccer/500/2310.png",
      "GameTime": "12:55pm",
      "GameState": "",
      "HomeTeam": "CSKA Sofia",
      "HomeGoals": "",
      "HomeLogo": "",
      "AwayTeam": "Young Boys",
      "AwayGoals": "",
      "AwayLogo": "https://a.espncdn.com/i/teamlogos/soccer/500/2722.png.png",
      "TVChannels": "fuboTV ,  TUDN.com ,  TUDNxtr…"
    },
    {
      "LeagueName": "UEFA Europa League",
      "LeagueLogo": "https://a.espncdn.com/i/leaguelogos/soccer/500/2310.png",
      "GameTime": "12:55pm",
      "GameState": "",
      "HomeTeam": "Molde",
      "HomeGoals": "",
      "HomeLogo": "",
      "AwayTeam": "Arsenal",
      "AwayGoals": "",
      "AwayLogo": "https://a.espncdn.com/i/teamlogos/soccer/500/359.png",
      "TVChannels": "fuboTV ,  UniMás ,  TUDN.com ,  …"
    },
    {
      "LeagueName": "UEFA Europa League",
      "LeagueLogo": "https://a.espncdn.com/i/leaguelogos/soccer/500/2310.png",
      "GameTime": "12:55pm",
      "GameState": "",
      "HomeTeam": "Sporting Braga",
      "HomeGoals": "",
      "HomeLogo": "",
      "AwayTeam": "Leicester",
      "AwayGoals": "",
      "AwayLogo": "https://a.espncdn.com/i/teamlogos/soccer/500/375.png",
      "TVChannels": "fuboTV ,  TUDN.com ,  TUDNxtr…"
    },
    {
      "LeagueName": "UEFA Europa League",
      "LeagueLogo": "https://a.espncdn.com/i/leaguelogos/soccer/500/2310.png",
      "GameTime": "12:55pm",
      "GameState": "",
      "HomeTeam": "AEK Athens",
      "HomeGoals": "",
      "HomeLogo": "",
      "AwayTeam": "Zorya fuboTV ,  TUDN.com ,  TUDNxtr…",
      "AwayGoals": "",
      "AwayLogo": "",
      "TVChannels": "12:55pm   AEK Athens vs Zorya fuboTV ,  TUDN.com ,  TUDNxtr…"
    },
    {
      "LeagueName": "UEFA Europa League",
      "LeagueLogo": "https://a.espncdn.com/i/leaguelogos/soccer/500/2310.png",
      "GameTime": "12:55pm",
      "GameState": "",
      "HomeTeam": "Sparta Praha",
      "HomeGoals": "",
      "HomeLogo": "https://a.espncdn.com/i/teamlogos/soccer/500/433.png",
      "AwayTeam": "Celtic",
      "AwayGoals": "",
      "AwayLogo": "https://a.espncdn.com/i/teamlogos/soccer/500/256.png",
      "TVChannels": "fuboTV ,  TUDN.com ,  TUDNxtr…"
    },
    {
      "LeagueName": "UEFA Europa League",
      "LeagueLogo": "https://a.espncdn.com/i/leaguelogos/soccer/500/2310.png",
      "GameTime": "12:55pm",
      "GameState": "",
      "HomeTeam": "Lille",
      "HomeGoals": "",
      "HomeLogo": "https://a.espncdn.com/i/teamlogos/soccer/500/166.png",
      "AwayTeam": "Milan",
      "AwayGoals": "",
      "AwayLogo": "https://a.espncdn.com/i/teamlogos/soccer/500/103.png",
      "TVChannels": "fuboTV ,  TUDN USA ,  TUDN.com ,  …"
    },
    {
      "LeagueName": "UEFA Europa League",
      "LeagueLogo": "https://a.espncdn.com/i/leaguelogos/soccer/500/2310.png",
      "GameTime": "12:55pm",
      "GameState": "",
      "HomeTeam": "Maccabi Tel Aviv",
      "HomeGoals": "",
      "HomeLogo": "https://cdn.livesoccertv.com/images/teams/israel/logos/maccabi-tel-aviv.png",
      "AwayTeam": "Villarreal",
      "AwayGoals": "",
      "AwayLogo": "https://a.espncdn.com/i/teamlogos/soccer/500/102.png",
      "TVChannels": "fuboTV ,  Galavision ,  TUDN.com ,  …"
    },
    {
      "LeagueName": "UEFA Europa League",
      "LeagueLogo": "https://a.espncdn.com/i/leaguelogos/soccer/500/2310.png",
      "GameTime": "12:55pm",
      "GameState": "",
      "HomeTeam": "Qarabağ",
      "HomeGoals": "",
      "HomeLogo": "https://cdn.livesoccertv.com/images/teams/azerbaijan/logos/qaraba.png",
      "AwayTeam": "Sivasspor fuboTV ,  TUDN.com ,  TUDNxtr…",
      "AwayGoals": "",
      "AwayLogo": "",
      "TVChannels": "vs Sivasspor fuboTV ,  TUDN.com ,  TUDNxtr…"
    },
    {
      "LeagueName": "UEFA Europa League",
      "LeagueLogo": "https://a.espncdn.com/i/leaguelogos/soccer/500/2310.png",
      "GameTime": "12:55pm",
      "GameState": "",
      "HomeTeam": "LASK Linz",
      "HomeGoals": "",
      "HomeLogo": "",
      "AwayTeam": "Antwerp fuboTV ,  TUDN.com ,  TUDNxtr…",
      "AwayGoals": "",
      "AwayLogo": "",
      "TVChannels": "12:55pm   LASK Linz vs Antwerp fuboTV ,  TUDN.com ,  TUDNxtr…"
    },
    {
      "LeagueName": "UEFA Europa League",
      "LeagueLogo": "https://a.espncdn.com/i/leaguelogos/soccer/500/2310.png",
      "GameTime": "12:55pm",
      "GameState": "",
      "HomeTeam": "CSKA Moskva",
      "HomeGoals": "",
      "HomeLogo": "https://a.espncdn.com/i/teamlogos/soccer/500/1963.png",
      "AwayTeam": "Feyenoord",
      "AwayGoals": "",
      "AwayLogo": "https://a.espncdn.com/i/teamlogos/soccer/500/142.png",
      "TVChannels": "fuboTV ,  TUDN.com ,  TUDNxtr…"
    },
    {
      "LeagueName": "UEFA Europa League",
      "LeagueLogo": "https://a.espncdn.com/i/leaguelogos/soccer/500/2310.png",
      "GameTime": "12:55pm",
      "GameState": "",
      "HomeTeam": "Wolfsberger",
      "HomeGoals": "",
      "HomeLogo": "https://a.espncdn.com/i/teamlogos/soccer/500/13294.png",
      "AwayTeam": "Dinamo Zagreb fuboTV ,  TUDN.com ,  TUDNxtr…",
      "AwayGoals": "",
      "AwayLogo": "",
      "TVChannels": "AC vs Dinamo Zagreb fuboTV ,  TUDN.com ,  TUDNxtr…"
    },
    {
      "LeagueName": "UEFA Europa League",
      "LeagueLogo": "https://a.espncdn.com/i/leaguelogos/soccer/500/2310.png",
      "GameTime": "12:55pm",
      "GameState": "",
      "HomeTeam": "Gent",
      "HomeGoals": "",
      "HomeLogo": "https://cdn.livesoccertv.com/images/teams/belgium/logos/gent.png",
      "AwayTeam": "Crvena Zvezda",
      "AwayGoals": "",
      "AwayLogo": "https://cdn.livesoccertv.com/images/teams/serbia/logos/crvena-zvezda.png",
      "TVChannels": "fuboTV ,  TUDN.com ,  TUDNxtr…"
    },
    {
      "LeagueName": "UEFA Europa League",
      "LeagueLogo": "https://a.espncdn.com/i/leaguelogos/soccer/500/2310.png",
      "GameTime": "12:55pm",
      "GameState": "",
      "HomeTeam": "Slovan Liberec",
      "HomeGoals": "",
      "HomeLogo": "",
      "AwayTeam": "Hoffenheim",
      "AwayGoals": "",
      "AwayLogo": "https://a.espncdn.com/i/teamlogos/soccer/500/7911.png",
      "TVChannels": "fuboTV ,  TUDN.com ,  TUDNxtr…"
    },
    {
      "LeagueName": "UEFA Europa League",
      "LeagueLogo": "https://a.espncdn.com/i/leaguelogos/soccer/500/2310.png",
      "GameTime": "3:00pm",
      "GameState": "",
      "HomeTeam": "CFR Cluj",
      "HomeGoals": "",
      "HomeLogo": "",
      "AwayTeam": "Roma",
      "AwayGoals": "",
      "AwayLogo": "https://a.espncdn.com/i/teamlogos/soccer/500/104.png",
      "TVChannels": "fuboTV ,  TUDN.com ,  TUDNxtr…"
    },
    {
      "LeagueName": "UEFA Europa League",
      "LeagueLogo": "https://a.espncdn.com/i/leaguelogos/soccer/500/2310.png",
      "GameTime": "3:00pm",
      "GameState": "",
      "HomeTeam": "Dundalk",
      "HomeGoals": "",
      "HomeLogo": "",
      "AwayTeam": "Rapid Wien",
      "AwayGoals": "",
      "AwayLogo": "https://cdn.livesoccertv.com/images/teams/austria/logos/rapid-wien.png",
      "TVChannels": "fuboTV ,  TUDN.com ,  TUDNxtr…"
    },
    {
      "LeagueName": "UEFA Europa League",
      "LeagueLogo": "https://a.espncdn.com/i/leaguelogos/soccer/500/2310.png",
      "GameTime": "3:00pm",
      "GameState": "",
      "HomeTeam": "Bayer Leverkusen",
      "HomeGoals": "",
      "HomeLogo": "https://a.espncdn.com/i/teamlogos/soccer/500/131.png",
      "AwayTeam": "Hapoel Be'er Sheva fuboTV ,  TUDN.com ,  TUDNxtr…",
      "AwayGoals": "",
      "AwayLogo": "",
      "TVChannels": "vs Hapoel Be'er Sheva fuboTV ,  TUDN.com ,  TUDNxtr…"
    },
    {
      "LeagueName": "UEFA Europa League",
      "LeagueLogo": "https://a.espncdn.com/i/leaguelogos/soccer/500/2310.png",
      "GameTime": "3:00pm",
      "GameState": "",
      "HomeTeam": "Nice",
      "HomeGoals": "",
      "HomeLogo": "https://a.espncdn.com/i/teamlogos/soccer/500/2502.png",
      "AwayTeam": "Slavia Praha fuboTV ,  TUDN.com ,  TUDNxtr…",
      "AwayGoals": "",
      "AwayLogo": "",
      "TVChannels": "vs Slavia Praha fuboTV ,  TUDN.com ,  TUDNxtr…"
    },
    {
      "LeagueName": "UEFA Europa League",
      "LeagueLogo": "https://a.espncdn.com/i/leaguelogos/soccer/500/2310.png",
      "GameTime": "3:00pm",
      "GameState": "",
      "HomeTeam": "Standard Liège",
      "HomeGoals": "",
      "HomeLogo": "",
      "AwayTeam": "Lech Poznań fuboTV ,  TUDN.com ,  TUDNxtr…",
      "AwayGoals": "",
      "AwayLogo": "",
      "TVChannels": "3:00pm   Standard Liège vs Lech Poznań fuboTV ,  TUDN.com ,  TUDNxtr…"
    },
    {
      "LeagueName": "UEFA Europa League",
      "LeagueLogo": "https://a.espncdn.com/i/leaguelogos/soccer/500/2310.png",
      "GameTime": "3:00pm",
      "GameState": "",
      "HomeTeam": "Angers",
      "HomeGoals": "",
      "HomeLogo": "https://a.espncdn.com/i/teamlogos/soccer/500/7868.png",
      "AwayTeam": "Benfica",
      "AwayGoals": "",
      "AwayLogo": "https://a.espncdn.com/i/teamlogos/soccer/500/1929.png",
      "TVChannels": "fuboTV ,  TUDN.com ,  TUDNxtr…"
    },
    {
      "LeagueName": "UEFA Europa League",
      "LeagueLogo": "https://a.espncdn.com/i/leaguelogos/soccer/500/2310.png",
      "GameTime": "3:00pm",
      "GameState": "",
      "HomeTeam": "PSV",
      "HomeGoals": "",
      "HomeLogo": "https://a.espncdn.com/i/teamlogos/soccer/500/148.png",
      "AwayTeam": "PAOK",
      "AwayGoals": "",
      "AwayLogo": "https://cdn.livesoccertv.com/images/teams/greece/logos/paok-saloniki.png",
      "TVChannels": "fuboTV ,  TUDN.com ,  TUDNxtr…"
    },
    {
      "LeagueName": "UEFA Europa League",
      "LeagueLogo": "https://a.espncdn.com/i/leaguelogos/soccer/500/2310.png",
      "GameTime": "3:00pm",
      "GameState": "",
      "HomeTeam": "Granada",
      "HomeGoals": "",
      "HomeLogo": "https://a.espncdn.com/i/teamlogos/soccer/500/3747.png",
      "AwayTeam": "Omonia Nicosia fuboTV ,  TUDN.com ,  TUDNxtr…",
      "AwayGoals": "",
      "AwayLogo": "",
      "TVChannels": "vs Omonia Nicosia fuboTV ,  TUDN.com ,  TUDNxtr…"
    },
    {
      "LeagueName": "UEFA Europa League",
      "LeagueLogo": "https://a.espncdn.com/i/leaguelogos/soccer/500/2310.png",
      "GameTime": "3:00pm",
      "GameState": "",
      "HomeTeam": "Napoli",
      "HomeGoals": "",
      "HomeLogo": "https://a.espncdn.com/i/teamlogos/soccer/500/114.png",
      "AwayTeam": "Rijeka fuboTV ,  UniMás ,  TUDN.com ,  …",
      "AwayGoals": "",
      "AwayLogo": "",
      "TVChannels": "vs Rijeka fuboTV ,  UniMás ,  TUDN.com ,  …"
    },
    {
      "LeagueName": "UEFA Europa League",
      "LeagueLogo": "https://a.espncdn.com/i/leaguelogos/soccer/500/2310.png",
      "GameTime": "3:00pm",
      "GameState": "",
      "HomeTeam": "AZ",
      "HomeGoals": "",
      "HomeLogo": "",
      "AwayTeam": "Real Sociedad",
      "AwayGoals": "",
      "AwayLogo": "https://a.espncdn.com/i/teamlogos/soccer/500/89.png",
      "TVChannels": "fuboTV ,  Galavision ,  TUDN.com ,  …"
    },
    {
      "LeagueName": "UEFA Europa League",
      "LeagueLogo": "https://a.espncdn.com/i/leaguelogos/soccer/500/2310.png",
      "GameTime": "3:00pm",
      "GameState": "",
      "HomeTeam": "Tottenham",
      "HomeGoals": "",
      "HomeLogo": "https://a.espncdn.com/i/teamlogos/soccer/500/367.png",
      "AwayTeam": "Ludogorets",
      "AwayGoals": "",
      "AwayLogo": "https://a.espncdn.com/i/teamlogos/soccer/500/13018.png",
      "TVChannels": "fuboTV ,  TUDN USA ,  TUDN.com ,  …"
    }
  ],
  "day3": [
    {
      "LeagueName": "English Premier League",
      "LeagueLogo": "https://a.espncdn.com/i/leaguelogos/soccer/500/23.png",
      "GameTime": "Friday Nov. 27, 2020",
      "GameState": "",
      "HomeTeam": "",
      "HomeGoals": "",
      "HomeLogo": "",
      "AwayTeam": "",
      "AwayGoals": "",
      "AwayLogo": "",
      "TVChannels": "LeagueHeader"
    },
    {
      "LeagueName": "English Premier League",
      "LeagueLogo": "https://a.espncdn.com/i/leaguelogos/soccer/500/23.png",
      "GameTime": "3:00pm",
      "GameState": "",
      "HomeTeam": "Crystal Palace",
      "HomeGoals": "",
      "HomeLogo": "https://a.espncdn.com/i/teamlogos/soccer/500/384.png",
      "AwayTeam": "Newcastle Utd",
      "AwayGoals": "",
      "AwayLogo": "https://a.espncdn.com/i/teamlogos/soccer/500/361.png",
      "TVChannels": "NBCSN ,  fuboTV ,  NBCSports.com ,  …"
    },
    {
      "LeagueName": "Spanish La Liga",
      "LeagueLogo": "https://a.espncdn.com/i/leaguelogos/soccer/500/15.png",
      "GameTime": "Friday Nov. 27, 2020",
      "GameState": "",
      "HomeTeam": "",
      "HomeGoals": "",
      "HomeLogo": "",
      "AwayTeam": "",
      "AwayGoals": "",
      "AwayLogo": "",
      "TVChannels": "LeagueHeader"
    },
    {
      "LeagueName": "Spanish La Liga",
      "LeagueLogo": "https://a.espncdn.com/i/leaguelogos/soccer/500/15.png",
      "GameTime": "3:00pm",
      "GameState": "",
      "HomeTeam": "Real Valladolid",
      "HomeGoals": "",
      "HomeLogo": "https://a.espncdn.com/i/teamlogos/soccer/500/95.png",
      "AwayTeam": "Levante",
      "AwayGoals": "",
      "AwayLogo": "https://a.espncdn.com/i/teamlogos/soccer/500/1538.png",
      "TVChannels": "fuboTV ,  Fanatiz USA ,  beIN SP…"
    },
    {
      "LeagueName": "German Bundesliga",
      "LeagueLogo": "https://a.espncdn.com/i/leaguelogos/soccer/500/10.png",
      "GameTime": "Friday Nov. 27, 2020",
      "GameState": "",
      "HomeTeam": "",
      "HomeGoals": "",
      "HomeLogo": "",
      "AwayTeam": "",
      "AwayGoals": "",
      "AwayLogo": "",
      "TVChannels": "LeagueHeader"
    },
    {
      "LeagueName": "German Bundesliga",
      "LeagueLogo": "https://a.espncdn.com/i/leaguelogos/soccer/500/10.png",
      "GameTime": "2:30pm",
      "GameState": "",
      "HomeTeam": "Wolfsburg",
      "HomeGoals": "",
      "HomeLogo": "https://a.espncdn.com/i/teamlogos/soccer/500/138.png",
      "AwayTeam": "Werder Bremen",
      "AwayGoals": "",
      "AwayLogo": "https://a.espncdn.com/i/teamlogos/soccer/500/137.png",
      "TVChannels": "ESPN+ ,  ESPN App ,  Sportsnet East ,  Spo…"
    },
    {
      "LeagueName": "French Ligue 1",
      "LeagueLogo": "https://a.espncdn.com/i/leaguelogos/soccer/500/9.png",
      "GameTime": "Friday Nov. 27, 2020",
      "GameState": "",
      "HomeTeam": "",
      "HomeGoals": "",
      "HomeLogo": "",
      "AwayTeam": "",
      "AwayGoals": "",
      "AwayLogo": "",
      "TVChannels": "LeagueHeader"
    },
    {
      "LeagueName": "French Ligue 1",
      "LeagueLogo": "https://a.espncdn.com/i/leaguelogos/soccer/500/9.png",
      "GameTime": "3:00pm",
      "GameState": "",
      "HomeTeam": "Strasbourg",
      "HomeGoals": "",
      "HomeLogo": "https://a.espncdn.com/i/teamlogos/soccer/500/180.png",
      "AwayTeam": "Stade Rennes",
      "AwayGoals": "",
      "AwayLogo": "https://a.espncdn.com/i/teamlogos/soccer/500/169.png",
      "TVChannels": "ESPN Norte ,  ESPN Play Norte ,  DAZN ,  Are…"
    },
    {
      "LeagueName": "English FA Cup",
      "LeagueLogo": "https://a.espncdn.com/i/leaguelogos/soccer/500/40.png",
      "GameTime": "Friday Nov. 27, 2020",
      "GameState": "",
      "HomeTeam": "",
      "HomeGoals": "",
      "HomeLogo": "",
      "AwayTeam": "",
      "AwayGoals": "",
      "AwayLogo": "",
      "TVChannels": "LeagueHeader"
    },
    {
      "LeagueName": "English FA Cup",
      "LeagueLogo": "https://a.espncdn.com/i/leaguelogos/soccer/500/40.png",
      "GameTime": "2:55pm",
      "GameState": "",
      "HomeTeam": "Tranmere Rovers",
      "HomeGoals": "",
      "HomeLogo": "https://a.espncdn.com/combiner/i?img=/i/teamlogos/soccer/500/345.png",
      "AwayTeam": "Brackley Town ESPN+ ,  ESPN App ,  Sportsnet World No…",
      "AwayGoals": "",
      "AwayLogo": "",
      "TVChannels": "vs Brackley Town ESPN+ ,  ESPN App ,  Sportsnet World No…"
    }
  ],
  "day4": [
    {
      "LeagueName": "English Premier League",
      "LeagueLogo": "https://a.espncdn.com/i/leaguelogos/soccer/500/23.png",
      "GameTime": "Saturday Nov. 28, 2020",
      "GameState": "",
      "HomeTeam": "",
      "HomeGoals": "",
      "HomeLogo": "",
      "AwayTeam": "",
      "AwayGoals": "",
      "AwayLogo": "",
      "TVChannels": "LeagueHeader"
    },
    {
      "LeagueName": "English Premier League",
      "LeagueLogo": "https://a.espncdn.com/i/leaguelogos/soccer/500/23.png",
      "GameTime": "7:30am",
      "GameState": "",
      "HomeTeam": "Brighton",
      "HomeGoals": "",
      "HomeLogo": "https://a.espncdn.com/i/teamlogos/soccer/500/331.png",
      "AwayTeam": "Liverpool",
      "AwayGoals": "",
      "AwayLogo": "https://a.espncdn.com/i/teamlogos/soccer/500/364.png",
      "TVChannels": "DAZN ,  Sky HD ,  Blue To Go Video Everywher…"
    },
    {
      "LeagueName": "English Premier League",
      "LeagueLogo": "https://a.espncdn.com/i/leaguelogos/soccer/500/23.png",
      "GameTime": "10:00am",
      "GameState": "",
      "HomeTeam": "Manchester City",
      "HomeGoals": "",
      "HomeLogo": "https://a.espncdn.com/i/teamlogos/soccer/500/382.png",
      "AwayTeam": "Burnley",
      "AwayGoals": "",
      "AwayLogo": "https://a.espncdn.com/i/teamlogos/soccer/500/379.png",
      "TVChannels": "NBCSN ,  fuboTV ,  NBCSports.com ,  …"
    },
    {
      "LeagueName": "English Premier League",
      "LeagueLogo": "https://a.espncdn.com/i/leaguelogos/soccer/500/23.png",
      "GameTime": "12:30pm",
      "GameState": "",
      "HomeTeam": "Everton",
      "HomeGoals": "",
      "HomeLogo": "https://a.espncdn.com/i/teamlogos/soccer/500/368.png",
      "AwayTeam": "Leeds United",
      "AwayGoals": "",
      "AwayLogo": "https://a.espncdn.com/i/teamlogos/soccer/500/357.png",
      "TVChannels": "fuboTV ,  Telemundo ,  Telemundo Dep…"
    },
    {
      "LeagueName": "English Premier League",
      "LeagueLogo": "https://a.espncdn.com/i/leaguelogos/soccer/500/23.png",
      "GameTime": "3:00pm",
      "GameState": "",
      "HomeTeam": "West Bromwich",
      "HomeGoals": "",
      "HomeLogo": "https://a.espncdn.com/i/teamlogos/soccer/500/383.png",
      "AwayTeam": "Sheffield Utd",
      "AwayGoals": "",
      "AwayLogo": "https://a.espncdn.com/i/teamlogos/soccer/500/398.png",
      "TVChannels": "NBCSN ,  fuboTV ,  NBCSports.com ,  …"
    },
    {
      "LeagueName": "Spanish La Liga",
      "LeagueLogo": "https://a.espncdn.com/i/leaguelogos/soccer/500/15.png",
      "GameTime": "Saturday Nov. 28, 2020",
      "GameState": "",
      "HomeTeam": "",
      "HomeGoals": "",
      "HomeLogo": "",
      "AwayTeam": "",
      "AwayGoals": "",
      "AwayLogo": "",
      "TVChannels": "LeagueHeader"
    },
    {
      "LeagueName": "Spanish La Liga",
      "LeagueLogo": "https://a.espncdn.com/i/leaguelogos/soccer/500/15.png",
      "GameTime": "8:00am",
      "GameState": "",
      "HomeTeam": "Elche",
      "HomeGoals": "",
      "HomeLogo": "https://a.espncdn.com/i/teamlogos/soccer/500/3751.png",
      "AwayTeam": "Cádiz",
      "AwayGoals": "",
      "AwayLogo": "https://a.espncdn.com/i/teamlogos/soccer/500/3842.png",
      "TVChannels": "fuboTV ,  Fanatiz USA ,  beIN…"
    },
    {
      "LeagueName": "Spanish La Liga",
      "LeagueLogo": "https://a.espncdn.com/i/leaguelogos/soccer/500/15.png",
      "GameTime": "10:15am",
      "GameState": "",
      "HomeTeam": "Valencia",
      "HomeGoals": "",
      "HomeLogo": "https://a.espncdn.com/i/teamlogos/soccer/500/94.png",
      "AwayTeam": "Atletico Madrid",
      "AwayGoals": "",
      "AwayLogo": "https://a.espncdn.com/i/teamlogos/soccer/500/1068.png",
      "TVChannels": "encia vs Atlético Madrid beIN SPORTS ,  fuboTV ,  Fanatiz…"
    },
    {
      "LeagueName": "Spanish La Liga",
      "LeagueLogo": "https://a.espncdn.com/i/leaguelogos/soccer/500/15.png",
      "GameTime": "12:30pm",
      "GameState": "",
      "HomeTeam": "Huesca",
      "HomeGoals": "",
      "HomeLogo": "https://a.espncdn.com/i/teamlogos/soccer/500/5413.png",
      "AwayTeam": "Sevilla FC",
      "AwayGoals": "",
      "AwayLogo": "https://a.espncdn.com/i/teamlogos/soccer/500/243.png",
      "TVChannels": "beIN SPORTS ,  fuboTV ,  Fanatiz…"
    },
    {
      "LeagueName": "Spanish La Liga",
      "LeagueLogo": "https://a.espncdn.com/i/leaguelogos/soccer/500/15.png",
      "GameTime": "3:00pm",
      "GameState": "",
      "HomeTeam": "Real Madrid",
      "HomeGoals": "",
      "HomeLogo": "https://a.espncdn.com/i/teamlogos/soccer/500/86.png",
      "AwayTeam": "Alavés",
      "AwayGoals": "",
      "AwayLogo": "https://a.espncdn.com/i/teamlogos/soccer/500/96.png",
      "TVChannels": "beIN SPORTS ,  fuboTV ,  Fanatiz…"
    },
    {
      "LeagueName": "Italian Serie A",
      "LeagueLogo": "https://a.espncdn.com/i/leaguelogos/soccer/500/12.png",
      "GameTime": "Saturday Nov. 28, 2020",
      "GameState": "",
      "HomeTeam": "",
      "HomeGoals": "",
      "HomeLogo": "",
      "AwayTeam": "",
      "AwayGoals": "",
      "AwayLogo": "",
      "TVChannels": "LeagueHeader"
    },
    {
      "LeagueName": "Italian Serie A",
      "LeagueLogo": "https://a.espncdn.com/i/leaguelogos/soccer/500/12.png",
      "GameTime": "9:00am",
      "GameState": "",
      "HomeTeam": "Sassuolo",
      "HomeGoals": "",
      "HomeLogo": "https://a.espncdn.com/i/teamlogos/soccer/500/3997.png",
      "AwayTeam": "Inter",
      "AwayGoals": "",
      "AwayLogo": "https://a.espncdn.com/i/teamlogos/soccer/500/110.png",
      "TVChannels": "ESPN+ ,  ESPN App ,  DAZN ,  TLN ,  ESPN Ca…"
    },
    {
      "LeagueName": "Italian Serie A",
      "LeagueLogo": "https://a.espncdn.com/i/leaguelogos/soccer/500/12.png",
      "GameTime": "12:00pm",
      "GameState": "",
      "HomeTeam": "Benevento",
      "HomeGoals": "",
      "HomeLogo": "https://a.espncdn.com/i/teamlogos/soccer/500/4059.png",
      "AwayTeam": "Juventus",
      "AwayGoals": "",
      "AwayLogo": "https://a.espncdn.com/i/teamlogos/soccer/500/111.png",
      "TVChannels": "ESPN+ ,  ESPN App ,  DAZN ,  TLN ,  ESPN Ca…"
    },
    {
      "LeagueName": "Italian Serie A",
      "LeagueLogo": "https://a.espncdn.com/i/leaguelogos/soccer/500/12.png",
      "GameTime": "2:45pm",
      "GameState": "",
      "HomeTeam": "Atalanta",
      "HomeGoals": "",
      "HomeLogo": "https://a.espncdn.com/i/teamlogos/soccer/500/105.png",
      "AwayTeam": "Hellas Verona",
      "AwayGoals": "",
      "AwayLogo": "https://a.espncdn.com/i/teamlogos/soccer/500/119.png",
      "TVChannels": "ESPN+ ,  ESPN App ,  DAZN ,  TLN ,  ESPNPl…"
    },
    {
      "LeagueName": "German Bundesliga",
      "LeagueLogo": "https://a.espncdn.com/i/leaguelogos/soccer/500/10.png",
      "GameTime": "Saturday Nov. 28, 2020",
      "GameState": "",
      "HomeTeam": "",
      "HomeGoals": "",
      "HomeLogo": "",
      "AwayTeam": "",
      "AwayGoals": "",
      "AwayLogo": "",
      "TVChannels": "LeagueHeader"
    },
    {
      "LeagueName": "German Bundesliga",
      "LeagueLogo": "https://a.espncdn.com/i/leaguelogos/soccer/500/10.png",
      "GameTime": "9:30am",
      "GameState": "",
      "HomeTeam": "Borussia Dortmund",
      "HomeGoals": "",
      "HomeLogo": "https://a.espncdn.com/i/teamlogos/soccer/500/124.png",
      "AwayTeam": "Köln",
      "AwayGoals": "",
      "AwayLogo": "https://a.espncdn.com/i/teamlogos/soccer/500/122.png",
      "TVChannels": "ESPN+ ,  ESPN App ,  Sportsnet World ,  Sp…"
    },
    {
      "LeagueName": "German Bundesliga",
      "LeagueLogo": "https://a.espncdn.com/i/leaguelogos/soccer/500/10.png",
      "GameTime": "9:30am",
      "GameState": "",
      "HomeTeam": "RB Leipzig",
      "HomeGoals": "",
      "HomeLogo": "https://a.espncdn.com/i/teamlogos/soccer/500/11420.png",
      "AwayTeam": "Arminia Bielefeld",
      "AwayGoals": "",
      "AwayLogo": "https://a.espncdn.com/i/teamlogos/soccer/500/2506.png",
      "TVChannels": "ESPN+ ,  ESPN App ,  Sportsnet World No…"
    },
    {
      "LeagueName": "German Bundesliga",
      "LeagueLogo": "https://a.espncdn.com/i/leaguelogos/soccer/500/10.png",
      "GameTime": "9:30am",
      "GameState": "",
      "HomeTeam": "Union Berlin",
      "HomeGoals": "",
      "HomeLogo": "https://a.espncdn.com/i/teamlogos/soccer/500/598.png",
      "AwayTeam": "Eintracht",
      "AwayGoals": "",
      "AwayLogo": "https://a.espncdn.com/i/teamlogos/soccer/500/125.png",
      "TVChannels": "ESPN+ ,  ESPN App ,  Sportsnet World No…"
    },
    {
      "LeagueName": "German Bundesliga",
      "LeagueLogo": "https://a.espncdn.com/i/leaguelogos/soccer/500/10.png",
      "GameTime": "9:30am",
      "GameState": "",
      "HomeTeam": "Augsburg",
      "HomeGoals": "",
      "HomeLogo": "https://a.espncdn.com/i/teamlogos/soccer/500/3841.png",
      "AwayTeam": "Freiburg",
      "AwayGoals": "",
      "AwayLogo": "https://a.espncdn.com/i/teamlogos/soccer/500/126.png",
      "TVChannels": "ESPN+ ,  ESPN App ,  Sportsnet World No…"
    },
    {
      "LeagueName": "German Bundesliga",
      "LeagueLogo": "https://a.espncdn.com/i/leaguelogos/soccer/500/10.png",
      "GameTime": "9:30am",
      "GameState": "",
      "HomeTeam": "Stuttgart",
      "HomeGoals": "",
      "HomeLogo": "https://a.espncdn.com/i/teamlogos/soccer/500/134.png",
      "AwayTeam": "Bayern Munich",
      "AwayGoals": "",
      "AwayLogo": "https://a.espncdn.com/i/teamlogos/soccer/500/132.png",
      "TVChannels": "tuttgart vs Bayern München ESPN+ ,  ESPN App ,  Sportsnet East ,  Spo…"
    },
    {
      "LeagueName": "German Bundesliga",
      "LeagueLogo": "https://a.espncdn.com/i/leaguelogos/soccer/500/10.png",
      "GameTime": "12:30pm",
      "GameState": "",
      "HomeTeam": "Borussia M'gladbach",
      "HomeGoals": "",
      "HomeLogo": "https://a.espncdn.com/i/teamlogos/soccer/500/268.png",
      "AwayTeam": "Schalke 04",
      "AwayGoals": "",
      "AwayLogo": "https://a.espncdn.com/i/teamlogos/soccer/500/133.png",
      "TVChannels": "ESPN+ ,  ESPN App ,  Sportsnet East ,  Spo…"
    },
    {
      "LeagueName": "French Ligue 1",
      "LeagueLogo": "https://a.espncdn.com/i/leaguelogos/soccer/500/9.png",
      "GameTime": "Saturday Nov. 28, 2020",
      "GameState": "",
      "HomeTeam": "",
      "HomeGoals": "",
      "HomeLogo": "",
      "AwayTeam": "",
      "AwayGoals": "",
      "AwayLogo": "",
      "TVChannels": "LeagueHeader"
    },
    {
      "LeagueName": "French Ligue 1",
      "LeagueLogo": "https://a.espncdn.com/i/leaguelogos/soccer/500/9.png",
      "GameTime": "11:00am",
      "GameState": "",
      "HomeTeam": "Marseille",
      "HomeGoals": "",
      "HomeLogo": "https://a.espncdn.com/i/teamlogos/soccer/500/176.png",
      "AwayTeam": "Nantes",
      "AwayGoals": "",
      "AwayLogo": "https://a.espncdn.com/i/teamlogos/soccer/500/165.png",
      "TVChannels": "ESPN2 Norte ,  ESPN Play Norte ,  DAZN ,  A…"
    },
    {
      "LeagueName": "French Ligue 1",
      "LeagueLogo": "https://a.espncdn.com/i/leaguelogos/soccer/500/9.png",
      "GameTime": "3:00pm",
      "GameState": "",
      "HomeTeam": "PSG",
      "HomeGoals": "",
      "HomeLogo": "https://a.espncdn.com/i/teamlogos/soccer/500/160.png",
      "AwayTeam": "Bordeaux",
      "AwayGoals": "",
      "AwayLogo": "https://a.espncdn.com/i/teamlogos/soccer/500/159.png",
      "TVChannels": "fuboTV ,  Fanatiz USA ,  beIN…"
    },
    {
      "LeagueName": "English FA Cup",
      "LeagueLogo": "https://a.espncdn.com/i/leaguelogos/soccer/500/40.png",
      "GameTime": "Saturday Nov. 28, 2020",
      "GameState": "",
      "HomeTeam": "",
      "HomeGoals": "",
      "HomeLogo": "",
      "AwayTeam": "",
      "AwayGoals": "",
      "AwayLogo": "",
      "TVChannels": "LeagueHeader"
    },
    {
      "LeagueName": "English FA Cup",
      "LeagueLogo": "https://a.espncdn.com/i/leaguelogos/soccer/500/40.png",
      "GameTime": "7:30am",
      "GameState": "",
      "HomeTeam": "Morecambe",
      "HomeGoals": "",
      "HomeLogo": "https://a.espncdn.com/combiner/i?img=/i/teamlogos/soccer/500/278.png",
      "AwayTeam": "Solihull Moors",
      "AwayGoals": "",
      "AwayLogo": "https://a.espncdn.com/combiner/i?img=/i/teamlogos/soccer/500/13061.png",
      "TVChannels": "ESPN+ ,  ESPN App ,  Sportsnet One ,  Spor…"
    },
    {
      "LeagueName": "English FA Cup",
      "LeagueLogo": "https://a.espncdn.com/i/leaguelogos/soccer/500/40.png",
      "GameTime": "8:00am",
      "GameState": "",
      "HomeTeam": "Newport County",
      "HomeGoals": "",
      "HomeLogo": "https://a.espncdn.com/combiner/i?img=/i/teamlogos/soccer/500/635.png",
      "AwayTeam": "Salford City",
      "AwayGoals": "",
      "AwayLogo": "https://a.espncdn.com/combiner/i?img=/i/teamlogos/soccer/500/4703.png",
      "TVChannels": ""
    },
    {
      "LeagueName": "English FA Cup",
      "LeagueLogo": "https://a.espncdn.com/i/leaguelogos/soccer/500/40.png",
      "GameTime": "8:00am",
      "GameState": "",
      "HomeTeam": "Gillingham",
      "HomeGoals": "",
      "HomeLogo": "https://a.espncdn.com/combiner/i?img=/i/teamlogos/soccer/500/389.png",
      "AwayTeam": "Exeter City",
      "AwayGoals": "",
      "AwayLogo": "https://a.espncdn.com/combiner/i?img=/i/teamlogos/soccer/500/324.png",
      "TVChannels": ""
    },
    {
      "LeagueName": "English FA Cup",
      "LeagueLogo": "https://a.espncdn.com/i/leaguelogos/soccer/500/40.png",
      "GameTime": "10:00am",
      "GameState": "",
      "HomeTeam": "Harrogate Town",
      "HomeGoals": "",
      "HomeLogo": "https://a.espncdn.com/combiner/i?img=/i/teamlogos/soccer/500/19262.png",
      "AwayTeam": "Blackpool",
      "AwayGoals": "",
      "AwayLogo": "https://a.espncdn.com/combiner/i?img=/i/teamlogos/soccer/500/346.png",
      "TVChannels": ""
    },
    {
      "LeagueName": "English FA Cup",
      "LeagueLogo": "https://a.espncdn.com/i/leaguelogos/soccer/500/40.png",
      "GameTime": "10:00am",
      "GameState": "",
      "HomeTeam": "Plymouth Argyle",
      "HomeGoals": "",
      "HomeLogo": "https://a.espncdn.com/combiner/i?img=/i/teamlogos/soccer/500/307.png",
      "AwayTeam": "Lincoln City",
      "AwayGoals": "",
      "AwayLogo": "https://a.espncdn.com/combiner/i?img=/i/teamlogos/soccer/500/314.png",
      "TVChannels": ""
    },
    {
      "LeagueName": "English FA Cup",
      "LeagueLogo": "https://a.espncdn.com/i/leaguelogos/soccer/500/40.png",
      "GameTime": "10:00am",
      "GameState": "",
      "HomeTeam": "Portsmouth",
      "HomeGoals": "",
      "HomeLogo": "https://a.espncdn.com/combiner/i?img=/i/teamlogos/soccer/500/385.png",
      "AwayTeam": "King's Lynn Town ESPN+ ,  ESPN App ,  Sportsnet One ,  Spor…",
      "AwayGoals": "",
      "AwayLogo": "",
      "TVChannels": "vs King's Lynn Town ESPN+ ,  ESPN App ,  Sportsnet One ,  Spor…"
    },
    {
      "LeagueName": "English FA Cup",
      "LeagueLogo": "https://a.espncdn.com/i/leaguelogos/soccer/500/40.png",
      "GameTime": "10:00am",
      "GameState": "",
      "HomeTeam": "Cheltenham Town",
      "HomeGoals": "",
      "HomeLogo": "https://a.espncdn.com/combiner/i?img=/i/teamlogos/soccer/500/320.png",
      "AwayTeam": "Crewe Alexandra",
      "AwayGoals": "",
      "AwayLogo": "https://a.espncdn.com/combiner/i?img=/i/teamlogos/soccer/500/396.png",
      "TVChannels": "BBC Sport Web ,  BBC iPlayer"
    },
    {
      "LeagueName": "English FA Cup",
      "LeagueLogo": "https://a.espncdn.com/i/leaguelogos/soccer/500/40.png",
      "GameTime": "10:00am",
      "GameState": "",
      "HomeTeam": "Bradford City",
      "HomeGoals": "",
      "HomeLogo": "https://a.espncdn.com/combiner/i?img=/i/teamlogos/soccer/500/387.png",
      "AwayTeam": "Oldham Athletic",
      "AwayGoals": "",
      "AwayLogo": "https://a.espncdn.com/combiner/i?img=/i/teamlogos/soccer/500/332.png",
      "TVChannels": "BBC Sport Web ,  BBC iPlayer"
    },
    {
      "LeagueName": "English FA Cup",
      "LeagueLogo": "https://a.espncdn.com/i/leaguelogos/soccer/500/40.png",
      "GameTime": "12:30pm",
      "GameState": "",
      "HomeTeam": "Peterborough United",
      "HomeGoals": "",
      "HomeLogo": "https://a.espncdn.com/combiner/i?img=/i/teamlogos/soccer/500/342.png",
      "AwayTeam": "Chorley",
      "AwayGoals": "",
      "AwayLogo": "https://a.espncdn.com/combiner/i?img=/i/teamlogos/soccer/500/3829.png",
      "TVChannels": "ESPN+ ,  ESPN App ,  Sportsnet One ,  Spor…"
    }
  ],
  "day5": [
    {
      "LeagueName": "English Premier League",
      "LeagueLogo": "https://a.espncdn.com/i/leaguelogos/soccer/500/23.png",
      "GameTime": "Sunday Nov. 29, 2020",
      "GameState": "",
      "HomeTeam": "",
      "HomeGoals": "",
      "HomeLogo": "",
      "AwayTeam": "",
      "AwayGoals": "",
      "AwayLogo": "",
      "TVChannels": "LeagueHeader"
    },
    {
      "LeagueName": "English Premier League",
      "LeagueLogo": "https://a.espncdn.com/i/leaguelogos/soccer/500/23.png",
      "GameTime": "9:00am",
      "GameState": "",
      "HomeTeam": "Southampton",
      "HomeGoals": "",
      "HomeLogo": "https://a.espncdn.com/i/teamlogos/soccer/500/376.png",
      "AwayTeam": "Manchester Utd",
      "AwayGoals": "",
      "AwayLogo": "https://a.espncdn.com/i/teamlogos/soccer/500/360.png",
      "TVChannels": "NBCSN ,  fuboTV ,  NBCSports.com ,  Te…"
    },
    {
      "LeagueName": "English Premier League",
      "LeagueLogo": "https://a.espncdn.com/i/leaguelogos/soccer/500/23.png",
      "GameTime": "11:30am",
      "GameState": "",
      "HomeTeam": "Chelsea",
      "HomeGoals": "",
      "HomeLogo": "https://a.espncdn.com/i/teamlogos/soccer/500/363.png",
      "AwayTeam": "Tottenham",
      "AwayGoals": "",
      "AwayLogo": "https://a.espncdn.com/i/teamlogos/soccer/500/367.png",
      "TVChannels": "NBCSN ,  fuboTV ,  NBCSports.com ,  Te…"
    },
    {
      "LeagueName": "English Premier League",
      "LeagueLogo": "https://a.espncdn.com/i/leaguelogos/soccer/500/23.png",
      "GameTime": "2:15pm",
      "GameState": "",
      "HomeTeam": "Arsenal",
      "HomeGoals": "",
      "HomeLogo": "https://a.espncdn.com/i/teamlogos/soccer/500/359.png",
      "AwayTeam": "Wolves",
      "AwayGoals": "",
      "AwayLogo": "https://a.espncdn.com/i/teamlogos/soccer/500/380.png",
      "TVChannels": "NBCSN ,  fuboTV ,  NBCSports.com ,  …"
    },
    {
      "LeagueName": "Spanish La Liga",
      "LeagueLogo": "https://a.espncdn.com/i/leaguelogos/soccer/500/15.png",
      "GameTime": "Sunday Nov. 29, 2020",
      "GameState": "",
      "HomeTeam": "",
      "HomeGoals": "",
      "HomeLogo": "",
      "AwayTeam": "",
      "AwayGoals": "",
      "AwayLogo": "",
      "TVChannels": "LeagueHeader"
    },
    {
      "LeagueName": "Spanish La Liga",
      "LeagueLogo": "https://a.espncdn.com/i/leaguelogos/soccer/500/15.png",
      "GameTime": "8:00am",
      "GameState": "",
      "HomeTeam": "Barcelona",
      "HomeGoals": "",
      "HomeLogo": "https://a.espncdn.com/i/teamlogos/soccer/500/83.png",
      "AwayTeam": "Osasuna",
      "AwayGoals": "",
      "AwayLogo": "https://a.espncdn.com/i/teamlogos/soccer/500/97.png",
      "TVChannels": "beIN SPORTS ,  fuboTV ,  Fanatiz…"
    },
    {
      "LeagueName": "Spanish La Liga",
      "LeagueLogo": "https://a.espncdn.com/i/leaguelogos/soccer/500/15.png",
      "GameTime": "10:15am",
      "GameState": "",
      "HomeTeam": "Getafe",
      "HomeGoals": "",
      "HomeLogo": "https://a.espncdn.com/i/teamlogos/soccer/500/2922.png",
      "AwayTeam": "Athletic Club",
      "AwayGoals": "",
      "AwayLogo": "https://a.espncdn.com/i/teamlogos/soccer/500/93.png",
      "TVChannels": "fuboTV ,  Fanatiz USA ,  beIN SP…"
    },
    {
      "LeagueName": "Spanish La Liga",
      "LeagueLogo": "https://a.espncdn.com/i/leaguelogos/soccer/500/15.png",
      "GameTime": "12:30pm",
      "GameState": "",
      "HomeTeam": "Celta de Vigo",
      "HomeGoals": "",
      "HomeLogo": "https://a.espncdn.com/i/teamlogos/soccer/500/85.png",
      "AwayTeam": "Granada",
      "AwayGoals": "",
      "AwayLogo": "https://a.espncdn.com/i/teamlogos/soccer/500/3747.png",
      "TVChannels": "beIN SPORTS ,  fuboTV ,  Fanatiz…"
    },
    {
      "LeagueName": "Spanish La Liga",
      "LeagueLogo": "https://a.espncdn.com/i/leaguelogos/soccer/500/15.png",
      "GameTime": "3:00pm",
      "GameState": "",
      "HomeTeam": "Real Sociedad",
      "HomeGoals": "",
      "HomeLogo": "https://a.espncdn.com/i/teamlogos/soccer/500/89.png",
      "AwayTeam": "Villarreal",
      "AwayGoals": "",
      "AwayLogo": "https://a.espncdn.com/i/teamlogos/soccer/500/102.png",
      "TVChannels": "beIN SPORTS ,  fuboTV ,  Fanatiz…"
    },
    {
      "LeagueName": "Italian Serie A",
      "LeagueLogo": "https://a.espncdn.com/i/leaguelogos/soccer/500/12.png",
      "GameTime": "Sunday Nov. 29, 2020",
      "GameState": "",
      "HomeTeam": "",
      "HomeGoals": "",
      "HomeLogo": "",
      "AwayTeam": "",
      "AwayGoals": "",
      "AwayLogo": "",
      "TVChannels": "LeagueHeader"
    },
    {
      "LeagueName": "Italian Serie A",
      "LeagueLogo": "https://a.espncdn.com/i/leaguelogos/soccer/500/12.png",
      "GameTime": "6:30am",
      "GameState": "",
      "HomeTeam": "Lazio",
      "HomeGoals": "",
      "HomeLogo": "https://a.espncdn.com/i/teamlogos/soccer/500/112.png",
      "AwayTeam": "Udinese",
      "AwayGoals": "",
      "AwayLogo": "https://a.espncdn.com/i/teamlogos/soccer/500/118.png",
      "TVChannels": "ESPN Deportes ,  ESPN Deportes+ ,  fubo…"
    },
    {
      "LeagueName": "Italian Serie A",
      "LeagueLogo": "https://a.espncdn.com/i/leaguelogos/soccer/500/12.png",
      "GameTime": "9:00am",
      "GameState": "",
      "HomeTeam": "Bologna",
      "HomeGoals": "",
      "HomeLogo": "https://a.espncdn.com/i/teamlogos/soccer/500/107.png",
      "AwayTeam": "Crotone",
      "AwayGoals": "",
      "AwayLogo": "https://a.espncdn.com/i/teamlogos/soccer/500/3173.png",
      "TVChannels": "ESPN+ ,  ESPN App ,  DAZN ,  ESPN Play…"
    },
    {
      "LeagueName": "Italian Serie A",
      "LeagueLogo": "https://a.espncdn.com/i/leaguelogos/soccer/500/12.png",
      "GameTime": "9:00am",
      "GameState": "",
      "HomeTeam": "Milan",
      "HomeGoals": "",
      "HomeLogo": "https://a.espncdn.com/i/teamlogos/soccer/500/103.png",
      "AwayTeam": "Fiorentina",
      "AwayGoals": "",
      "AwayLogo": "https://a.espncdn.com/i/teamlogos/soccer/500/109.png",
      "TVChannels": "ESPN+ ,  ESPN App ,  DAZN ,  TLN ,  ESPN Ca…"
    },
    {
      "LeagueName": "Italian Serie A",
      "LeagueLogo": "https://a.espncdn.com/i/leaguelogos/soccer/500/12.png",
      "GameTime": "12:00pm",
      "GameState": "",
      "HomeTeam": "Cagliari",
      "HomeGoals": "",
      "HomeLogo": "https://a.espncdn.com/i/teamlogos/soccer/500/2925.png",
      "AwayTeam": "Spezia",
      "AwayGoals": "",
      "AwayLogo": "https://a.espncdn.com/i/teamlogos/soccer/500/4056.png",
      "TVChannels": "ESPN+ ,  ESPN App ,  DAZN ,  TLN ,  ESPN P…"
    },
    {
      "LeagueName": "Italian Serie A",
      "LeagueLogo": "https://a.espncdn.com/i/leaguelogos/soccer/500/12.png",
      "GameTime": "2:45pm",
      "GameState": "",
      "HomeTeam": "Napoli",
      "HomeGoals": "",
      "HomeLogo": "https://a.espncdn.com/i/teamlogos/soccer/500/114.png",
      "AwayTeam": "Roma",
      "AwayGoals": "",
      "AwayLogo": "https://a.espncdn.com/i/teamlogos/soccer/500/104.png",
      "TVChannels": "ESPN+ ,  ESPN App ,  DAZN ,  TLN ,  ESPN No…"
    },
    {
      "LeagueName": "German Bundesliga",
      "LeagueLogo": "https://a.espncdn.com/i/leaguelogos/soccer/500/10.png",
      "GameTime": "Sunday Nov. 29, 2020",
      "GameState": "",
      "HomeTeam": "",
      "HomeGoals": "",
      "HomeLogo": "",
      "AwayTeam": "",
      "AwayGoals": "",
      "AwayLogo": "",
      "TVChannels": "LeagueHeader"
    },
    {
      "LeagueName": "German Bundesliga",
      "LeagueLogo": "https://a.espncdn.com/i/leaguelogos/soccer/500/10.png",
      "GameTime": "9:30am",
      "GameState": "",
      "HomeTeam": "Bayer Leverkusen",
      "HomeGoals": "",
      "HomeLogo": "https://a.espncdn.com/i/teamlogos/soccer/500/131.png",
      "AwayTeam": "Hertha BSC",
      "AwayGoals": "",
      "AwayLogo": "https://a.espncdn.com/i/teamlogos/soccer/500/129.png",
      "TVChannels": "ESPN+ ,  ESPN App ,  Sportsnet East ,  Spo…"
    },
    {
      "LeagueName": "German Bundesliga",
      "LeagueLogo": "https://a.espncdn.com/i/leaguelogos/soccer/500/10.png",
      "GameTime": "12:00pm",
      "GameState": "",
      "HomeTeam": "Mainz 05",
      "HomeGoals": "",
      "HomeLogo": "https://a.espncdn.com/i/teamlogos/soccer/500/2950.png",
      "AwayTeam": "Hoffenheim",
      "AwayGoals": "",
      "AwayLogo": "https://a.espncdn.com/i/teamlogos/soccer/500/7911.png",
      "TVChannels": "ESPN+ ,  ESPN App ,  Sportsnet East ,  Spo…"
    },
    {
      "LeagueName": "French Ligue 1",
      "LeagueLogo": "https://a.espncdn.com/i/leaguelogos/soccer/500/9.png",
      "GameTime": "Sunday Nov. 29, 2020",
      "GameState": "",
      "HomeTeam": "",
      "HomeGoals": "",
      "HomeLogo": "",
      "AwayTeam": "",
      "AwayGoals": "",
      "AwayLogo": "",
      "TVChannels": "LeagueHeader"
    },
    {
      "LeagueName": "French Ligue 1",
      "LeagueLogo": "https://a.espncdn.com/i/leaguelogos/soccer/500/9.png",
      "GameTime": "7:00am",
      "GameState": "",
      "HomeTeam": "Lyon",
      "HomeGoals": "",
      "HomeLogo": "https://a.espncdn.com/i/teamlogos/soccer/500/167.png",
      "AwayTeam": "Stade de Reims",
      "AwayGoals": "",
      "AwayLogo": "https://a.espncdn.com/i/teamlogos/soccer/500/3243.png",
      "TVChannels": "ESPN Play Norte ,  ESPNPlay Caribbean ,  …"
    },
    {
      "LeagueName": "French Ligue 1",
      "LeagueLogo": "https://a.espncdn.com/i/leaguelogos/soccer/500/9.png",
      "GameTime": "9:00am",
      "GameState": "",
      "HomeTeam": "Lens",
      "HomeGoals": "",
      "HomeLogo": "https://a.espncdn.com/i/teamlogos/soccer/500/175.png",
      "AwayTeam": "Angers",
      "AwayGoals": "",
      "AwayLogo": "https://a.espncdn.com/i/teamlogos/soccer/500/7868.png",
      "TVChannels": "SCO Viaplay Denmark ,  Viaplay Sweden ,  Viaplay N…"
    },
    {
      "LeagueName": "French Ligue 1",
      "LeagueLogo": "https://a.espncdn.com/i/leaguelogos/soccer/500/9.png",
      "GameTime": "9:00am",
      "GameState": "",
      "HomeTeam": "Lorient",
      "HomeGoals": "",
      "HomeLogo": "https://a.espncdn.com/i/teamlogos/soccer/500/273.png",
      "AwayTeam": "Montpellier",
      "AwayGoals": "",
      "AwayLogo": "https://a.espncdn.com/i/teamlogos/soccer/500/274.png",
      "TVChannels": "fuboTV ,  Fanatiz USA ,  beIN…"
    },
    {
      "LeagueName": "French Ligue 1",
      "LeagueLogo": "https://a.espncdn.com/i/leaguelogos/soccer/500/9.png",
      "GameTime": "9:00am",
      "GameState": "",
      "HomeTeam": "Metz",
      "HomeGoals": "",
      "HomeLogo": "https://a.espncdn.com/i/teamlogos/soccer/500/177.png",
      "AwayTeam": "Brest",
      "AwayGoals": "",
      "AwayLogo": "https://a.espncdn.com/i/teamlogos/soccer/500/6997.png",
      "TVChannels": "Viaplay Denmark ,  Viaplay Sweden ,  Viaplay N…"
    },
    {
      "LeagueName": "French Ligue 1",
      "LeagueLogo": "https://a.espncdn.com/i/leaguelogos/soccer/500/9.png",
      "GameTime": "9:00am",
      "GameState": "",
      "HomeTeam": "Monaco",
      "HomeGoals": "",
      "HomeLogo": "https://a.espncdn.com/i/teamlogos/soccer/500/174.png",
      "AwayTeam": "Nimes",
      "AwayGoals": "",
      "AwayLogo": "https://a.espncdn.com/i/teamlogos/soccer/500/7730.png",
      "TVChannels": "fuboTV ,  Fanatiz USA ,  beIN…"
    },
    {
      "LeagueName": "French Ligue 1",
      "LeagueLogo": "https://a.espncdn.com/i/leaguelogos/soccer/500/9.png",
      "GameTime": "11:00am",
      "GameState": "",
      "HomeTeam": "Nice",
      "HomeGoals": "",
      "HomeLogo": "https://a.espncdn.com/i/teamlogos/soccer/500/2502.png",
      "AwayTeam": "Dijon",
      "AwayGoals": "",
      "AwayLogo": "https://a.espncdn.com/i/teamlogos/soccer/500/3170.png",
      "TVChannels": "ESPN Caribbean ,  ESPN Norte ,  ESPN Play…"
    },
    {
      "LeagueName": "French Ligue 1",
      "LeagueLogo": "https://a.espncdn.com/i/leaguelogos/soccer/500/9.png",
      "GameTime": "3:00pm",
      "GameState": "",
      "HomeTeam": "Saint-Étienne",
      "HomeGoals": "",
      "HomeLogo": "https://a.espncdn.com/i/teamlogos/soccer/500/178.png",
      "AwayTeam": "Lille",
      "AwayGoals": "",
      "AwayLogo": "https://a.espncdn.com/i/teamlogos/soccer/500/166.png",
      "TVChannels": "ESPN Play Norte ,  OneSoccer ,  DAZN ,  Arena…"
    },
    {
      "LeagueName": "German Bundesliga",
      "LeagueLogo": "https://a.espncdn.com/i/leaguelogos/soccer/500/10.png",
      "GameTime": "Sunday Nov. 29, 2020",
      "GameState": "",
      "HomeTeam": "",
      "HomeGoals": "",
      "HomeLogo": "",
      "AwayTeam": "",
      "AwayGoals": "",
      "AwayLogo": "",
      "TVChannels": "LeagueHeader"
    },
    {
      "LeagueName": "German Bundesliga",
      "LeagueLogo": "https://a.espncdn.com/i/leaguelogos/soccer/500/10.png",
      "GameTime": "8:30am",
      "GameState": "",
      "HomeTeam": "Wolfsberger",
      "HomeGoals": "",
      "HomeLogo": "https://a.espncdn.com/i/teamlogos/soccer/500/13294.png",
      "AwayTeam": "Ried fuboTV ,  Eleven Sports Network USA ,  …",
      "AwayGoals": "",
      "AwayLogo": "",
      "TVChannels": "AC vs Ried fuboTV ,  Eleven Sports Network USA ,  …"
    },
    {
      "LeagueName": "German Bundesliga",
      "LeagueLogo": "https://a.espncdn.com/i/leaguelogos/soccer/500/10.png",
      "GameTime": "8:30am",
      "GameState": "",
      "HomeTeam": "LASK Linz",
      "HomeGoals": "",
      "HomeLogo": "",
      "AwayTeam": "Austria",
      "AwayGoals": "",
      "AwayLogo": "https://a.espncdn.com/combiner/i?img=/i/teamlogos/soccer/500/474.png",
      "TVChannels": "1 ,  Sky Go ,  Sky Ticket ,  O…"
    },
    {
      "LeagueName": "German Bundesliga",
      "LeagueLogo": "https://a.espncdn.com/i/leaguelogos/soccer/500/10.png",
      "GameTime": "11:00am",
      "GameState": "",
      "HomeTeam": "Rapid Wien",
      "HomeGoals": "",
      "HomeLogo": "https://cdn.livesoccertv.com/images/teams/austria/logos/rapid-wien.png",
      "AwayTeam": "Austria",
      "AwayGoals": "",
      "AwayLogo": "https://a.espncdn.com/combiner/i?img=/i/teamlogos/soccer/500/474.png",
      "TVChannels": "Wien Sky Sport Austria 1 ,  Sky Go ,  Sky Ticket ,  O…"
    },
    {
      "LeagueName": "English FA Cup",
      "LeagueLogo": "https://a.espncdn.com/i/leaguelogos/soccer/500/40.png",
      "GameTime": "Sunday Nov. 29, 2020",
      "GameState": "",
      "HomeTeam": "",
      "HomeGoals": "",
      "HomeLogo": "",
      "AwayTeam": "",
      "AwayGoals": "",
      "AwayLogo": "",
      "TVChannels": "LeagueHeader"
    },
    {
      "LeagueName": "English FA Cup",
      "LeagueLogo": "https://a.espncdn.com/i/leaguelogos/soccer/500/40.png",
      "GameTime": "8:30am",
      "GameState": "",
      "HomeTeam": "Stevenage",
      "HomeGoals": "",
      "HomeLogo": "https://a.espncdn.com/combiner/i?img=/i/teamlogos/soccer/500/285.png",
      "AwayTeam": "Hull City",
      "AwayGoals": "",
      "AwayLogo": "https://a.espncdn.com/combiner/i?img=/i/teamlogos/soccer/500/306.png",
      "TVChannels": "BBC Sport Web ,  BBC iPlayer"
    },
    {
      "LeagueName": "English FA Cup",
      "LeagueLogo": "https://a.espncdn.com/i/leaguelogos/soccer/500/40.png",
      "GameTime": "8:30am",
      "GameState": "",
      "HomeTeam": "Stockport County",
      "HomeGoals": "",
      "HomeLogo": "",
      "AwayTeam": "Yeovil Town",
      "AwayGoals": "",
      "AwayLogo": "https://a.espncdn.com/combiner/i?img=/i/teamlogos/soccer/500/284.png",
      "TVChannels": "BBC Sport Web ,  BBC iPlayer"
    },
    {
      "LeagueName": "English FA Cup",
      "LeagueLogo": "https://a.espncdn.com/i/leaguelogos/soccer/500/40.png",
      "GameTime": "8:30am",
      "GameState": "",
      "HomeTeam": "Shrewsbury Town",
      "HomeGoals": "",
      "HomeLogo": "https://a.espncdn.com/combiner/i?img=/i/teamlogos/soccer/500/302.png",
      "AwayTeam": "Oxford City",
      "AwayGoals": "",
      "AwayLogo": "https://a.espncdn.com/combiner/i?img=/i/teamlogos/soccer/500/4489.png",
      "TVChannels": "ESPN+ ,  ESPN App ,  Sportsnet One ,  Spor…"
    },
    {
      "LeagueName": "English FA Cup",
      "LeagueLogo": "https://a.espncdn.com/i/leaguelogos/soccer/500/40.png",
      "GameTime": "8:30am",
      "GameState": "",
      "HomeTeam": "Mansfield Town",
      "HomeGoals": "",
      "HomeLogo": "https://a.espncdn.com/combiner/i?img=/i/teamlogos/soccer/500/304.png",
      "AwayTeam": "Dagenham & Redbridge BBC Sport Web ,  BBC iPlayer",
      "AwayGoals": "",
      "AwayLogo": "",
      "TVChannels": "vs Dagenham & Redbridge BBC Sport Web ,  BBC iPlayer"
    },
    {
      "LeagueName": "English FA Cup",
      "LeagueLogo": "https://a.espncdn.com/i/leaguelogos/soccer/500/40.png",
      "GameTime": "8:30am",
      "GameState": "",
      "HomeTeam": "Carlisle United",
      "HomeGoals": "",
      "HomeLogo": "https://a.espncdn.com/combiner/i?img=/i/teamlogos/soccer/500/322.png",
      "AwayTeam": "Doncaster Rovers",
      "AwayGoals": "",
      "AwayLogo": "https://a.espncdn.com/combiner/i?img=/i/teamlogos/soccer/500/279.png",
      "TVChannels": "BBC Sport Web ,  BBC iPlayer"
    },
    {
      "LeagueName": "English FA Cup",
      "LeagueLogo": "https://a.espncdn.com/i/leaguelogos/soccer/500/40.png",
      "GameTime": "8:30am",
      "GameState": "",
      "HomeTeam": "Barnet",
      "HomeGoals": "",
      "HomeLogo": "https://a.espncdn.com/combiner/i?img=/i/teamlogos/soccer/500/280.png",
      "AwayTeam": "Milton Keynes Dons",
      "AwayGoals": "",
      "AwayLogo": "https://a.espncdn.com/combiner/i?img=/i/teamlogos/soccer/500/390.png",
      "TVChannels": "BBC Sport Web ,  BBC iPlayer"
    },
    {
      "LeagueName": "English FA Cup",
      "LeagueLogo": "https://a.espncdn.com/i/leaguelogos/soccer/500/40.png",
      "GameTime": "8:30am",
      "GameState": "",
      "HomeTeam": "Bristol Rovers",
      "HomeGoals": "",
      "HomeLogo": "https://a.espncdn.com/combiner/i?img=/i/teamlogos/soccer/500/308.png",
      "AwayTeam": "Darlington",
      "AwayGoals": "",
      "AwayLogo": "https://a.espncdn.com/combiner/i?img=/i/teamlogos/soccer/500/305.png",
      "TVChannels": "ESPN+ ,  ESPN App ,  Sportsnet World No…"
    },
    {
      "LeagueName": "English FA Cup",
      "LeagueLogo": "https://a.espncdn.com/i/leaguelogos/soccer/500/40.png",
      "GameTime": "8:30am",
      "GameState": "",
      "HomeTeam": "Afc Wimbledon",
      "HomeGoals": "",
      "HomeLogo": "https://a.espncdn.com/combiner/i?img=/i/teamlogos/soccer/500/3802.png",
      "AwayTeam": "Crawley Town",
      "AwayGoals": "",
      "AwayLogo": "https://a.espncdn.com/combiner/i?img=/i/teamlogos/soccer/500/2594.png",
      "TVChannels": "BBC Sport Web ,  BBC iPlayer"
    },
    {
      "LeagueName": "English FA Cup",
      "LeagueLogo": "https://a.espncdn.com/i/leaguelogos/soccer/500/40.png",
      "GameTime": "9:45am",
      "GameState": "",
      "HomeTeam": "Marine",
      "HomeGoals": "",
      "HomeLogo": "",
      "AwayTeam": "Havant & Waterlooville ESPN+ ,  ESPN App ,  Sportsnet World No…",
      "AwayGoals": "",
      "AwayLogo": "",
      "TVChannels": "9:45am   Marine vs Havant & Waterlooville ESPN+ ,  ESPN App ,  Sportsnet World No…"
    }
  ],
  "day6": [
    {
      "LeagueName": "English Premier League",
      "LeagueLogo": "https://a.espncdn.com/i/leaguelogos/soccer/500/23.png",
      "GameTime": "Monday Nov. 30, 2020",
      "GameState": "",
      "HomeTeam": "",
      "HomeGoals": "",
      "HomeLogo": "",
      "AwayTeam": "",
      "AwayGoals": "",
      "AwayLogo": "",
      "TVChannels": "LeagueHeader"
    },
    {
      "LeagueName": "English Premier League",
      "LeagueLogo": "https://a.espncdn.com/i/leaguelogos/soccer/500/23.png",
      "GameTime": "12:30pm",
      "GameState": "",
      "HomeTeam": "Leicester",
      "HomeGoals": "",
      "HomeLogo": "https://a.espncdn.com/i/teamlogos/soccer/500/375.png",
      "AwayTeam": "Fulham",
      "AwayGoals": "",
      "AwayLogo": "https://a.espncdn.com/i/teamlogos/soccer/500/370.png",
      "TVChannels": "NBCSN ,  fuboTV ,  NBCSports.com ,  …"
    },
    {
      "LeagueName": "English Premier League",
      "LeagueLogo": "https://a.espncdn.com/i/leaguelogos/soccer/500/23.png",
      "GameTime": "3:00pm",
      "GameState": "",
      "HomeTeam": "West Ham",
      "HomeGoals": "",
      "HomeLogo": "https://a.espncdn.com/i/teamlogos/soccer/500/371.png",
      "AwayTeam": "Aston Villa",
      "AwayGoals": "",
      "AwayLogo": "https://a.espncdn.com/i/teamlogos/soccer/500/362.png",
      "TVChannels": "NBCSN ,  fuboTV ,  NBCSports.com ,  …"
    },
    {
      "LeagueName": "Spanish La Liga",
      "LeagueLogo": "https://a.espncdn.com/i/leaguelogos/soccer/500/15.png",
      "GameTime": "Monday Nov. 30, 2020",
      "GameState": "",
      "HomeTeam": "",
      "HomeGoals": "",
      "HomeLogo": "",
      "AwayTeam": "",
      "AwayGoals": "",
      "AwayLogo": "",
      "TVChannels": "LeagueHeader"
    },
    {
      "LeagueName": "Spanish La Liga",
      "LeagueLogo": "https://a.espncdn.com/i/leaguelogos/soccer/500/15.png",
      "GameTime": "3:00pm",
      "GameState": "",
      "HomeTeam": "Real Betis",
      "HomeGoals": "",
      "HomeLogo": "https://a.espncdn.com/i/teamlogos/soccer/500/244.png",
      "AwayTeam": "Eibar",
      "AwayGoals": "",
      "AwayLogo": "https://a.espncdn.com/i/teamlogos/soccer/500/3752.png",
      "TVChannels": "fuboTV ,  Fanatiz USA ,  beIN…"
    },
    {
      "LeagueName": "Italian Serie A",
      "LeagueLogo": "https://a.espncdn.com/i/leaguelogos/soccer/500/12.png",
      "GameTime": "Monday Nov. 30, 2020",
      "GameState": "",
      "HomeTeam": "",
      "HomeGoals": "",
      "HomeLogo": "",
      "AwayTeam": "",
      "AwayGoals": "",
      "AwayLogo": "",
      "TVChannels": "LeagueHeader"
    },
    {
      "LeagueName": "Italian Serie A",
      "LeagueLogo": "https://a.espncdn.com/i/leaguelogos/soccer/500/12.png",
      "GameTime": "12:30pm",
      "GameState": "",
      "HomeTeam": "Torino",
      "HomeGoals": "",
      "HomeLogo": "https://a.espncdn.com/i/teamlogos/soccer/500/239.png",
      "AwayTeam": "Sampdoria",
      "AwayGoals": "",
      "AwayLogo": "https://a.espncdn.com/i/teamlogos/soccer/500/2734.png",
      "TVChannels": "ESPN+ ,  ESPN App ,  DAZN ,  ESPN Caribb…"
    },
    {
      "LeagueName": "Italian Serie A",
      "LeagueLogo": "https://a.espncdn.com/i/leaguelogos/soccer/500/12.png",
      "GameTime": "2:45pm",
      "GameState": "",
      "HomeTeam": "Genoa",
      "HomeGoals": "",
      "HomeLogo": "https://a.espncdn.com/i/teamlogos/soccer/500/3263.png",
      "AwayTeam": "Parma",
      "AwayGoals": "",
      "AwayLogo": "https://a.espncdn.com/i/teamlogos/soccer/500/115.png",
      "TVChannels": "ESPN+ ,  ESPN App ,  DAZN ,  ESPN Caribb…"
    },
    {
      "LeagueName": "English FA Cup",
      "LeagueLogo": "https://a.espncdn.com/i/leaguelogos/soccer/500/40.png",
      "GameTime": "Monday Nov. 30, 2020",
      "GameState": "",
      "HomeTeam": "",
      "HomeGoals": "",
      "HomeLogo": "",
      "AwayTeam": "",
      "AwayGoals": "",
      "AwayLogo": "",
      "TVChannels": "LeagueHeader"
    },
    {
      "LeagueName": "English FA Cup",
      "LeagueLogo": "https://a.espncdn.com/i/leaguelogos/soccer/500/40.png",
      "GameTime": "2:45pm",
      "GameState": "",
      "HomeTeam": "Canvey Island",
      "HomeGoals": "",
      "HomeLogo": "",
      "AwayTeam": "Boreham Wood ESPN+ ,  ESPN App ,  Sportsnet East ,  Spo…",
      "AwayGoals": "",
      "AwayLogo": "",
      "TVChannels": "2:45pm   Canvey Island vs Boreham Wood ESPN+ ,  ESPN App ,  Sportsnet East ,  Spo…"
    },
    {
      "LeagueName": "English FA Cup",
      "LeagueLogo": "https://a.espncdn.com/i/leaguelogos/soccer/500/40.png",
      "GameTime": "2:30pm",
      "GameState": "",
      "HomeTeam": "Bochum",
      "HomeGoals": "",
      "HomeLogo": "https://a.espncdn.com/i/teamlogos/soccer/500/121.png",
      "AwayTeam": "Fortuna Düsseldorf",
      "AwayGoals": "",
      "AwayLogo": "https://a.espncdn.com/i/teamlogos/soccer/500/9707.png",
      "TVChannels": "ESPN+ ,  ESPN App ,  Sport 1 Hungary ,  Sk…"
    }
  ],
  "day7": [
    {
      "LeagueName": "UEFA Champions League",
      "LeagueLogo": "https://a.espncdn.com/i/leaguelogos/soccer/500/2.png",
      "GameTime": "Tuesday Dec. 1, 2020",
      "GameState": "",
      "HomeTeam": "",
      "HomeGoals": "",
      "HomeLogo": "",
      "AwayTeam": "",
      "AwayGoals": "",
      "AwayLogo": "",
      "TVChannels": "LeagueHeader"
    },
    {
      "LeagueName": "UEFA Champions League",
      "LeagueLogo": "https://a.espncdn.com/i/leaguelogos/soccer/500/2.png",
      "GameTime": "12:55pm",
      "GameState": "",
      "HomeTeam": "Lokomotiv Moskva",
      "HomeGoals": "",
      "HomeLogo": "https://a.espncdn.com/i/teamlogos/soccer/500/442.png",
      "AwayTeam": "Salzburg",
      "AwayGoals": "",
      "AwayLogo": "https://a.espncdn.com/i/teamlogos/soccer/500/2790.png",
      "TVChannels": "fuboTV ,  TUDN.com ,  TUDNxtr…"
    },
    {
      "LeagueName": "UEFA Champions League",
      "LeagueLogo": "https://a.espncdn.com/i/leaguelogos/soccer/500/2.png",
      "GameTime": "12:55pm",
      "GameState": "",
      "HomeTeam": "Shakhtar Donetsk",
      "HomeGoals": "",
      "HomeLogo": "https://a.espncdn.com/combiner/i?img=/i/teamlogos/soccer/500/493.png",
      "AwayTeam": "Real Madrid",
      "AwayGoals": "",
      "AwayLogo": "https://a.espncdn.com/i/teamlogos/soccer/500/86.png",
      "TVChannels": "fuboTV ,  TUDN USA ,  TUDN.com ,  …"
    },
    {
      "LeagueName": "UEFA Champions League",
      "LeagueLogo": "https://a.espncdn.com/i/leaguelogos/soccer/500/2.png",
      "GameTime": "3:00pm",
      "GameState": "",
      "HomeTeam": "Atletico Madrid",
      "HomeGoals": "",
      "HomeLogo": "https://a.espncdn.com/i/teamlogos/soccer/500/1068.png",
      "AwayTeam": "Bayern Munich",
      "AwayGoals": "",
      "AwayLogo": "https://a.espncdn.com/i/teamlogos/soccer/500/132.png",
      "TVChannels": "tlético Madrid vs Bayern München fuboTV ,  TUDN USA ,  TUDN.com ,  …"
    },
    {
      "LeagueName": "UEFA Champions League",
      "LeagueLogo": "https://a.espncdn.com/i/leaguelogos/soccer/500/2.png",
      "GameTime": "3:00pm",
      "GameState": "",
      "HomeTeam": "Borussia M'gladbach",
      "HomeGoals": "",
      "HomeLogo": "https://a.espncdn.com/i/teamlogos/soccer/500/268.png",
      "AwayTeam": "Inter",
      "AwayGoals": "",
      "AwayLogo": "https://a.espncdn.com/i/teamlogos/soccer/500/110.png",
      "TVChannels": "fuboTV ,  TUDN.com ,  TUDNxtr…"
    },
    {
      "LeagueName": "UEFA Champions League",
      "LeagueLogo": "https://a.espncdn.com/i/leaguelogos/soccer/500/2.png",
      "GameTime": "3:00pm",
      "GameState": "",
      "HomeTeam": "Porto",
      "HomeGoals": "",
      "HomeLogo": "https://a.espncdn.com/i/teamlogos/soccer/500/437.png",
      "AwayTeam": "Manchester City",
      "AwayGoals": "",
      "AwayLogo": "https://a.espncdn.com/i/teamlogos/soccer/500/382.png",
      "TVChannels": "fuboTV ,  TUDN.com ,  TUDNxtr…"
    },
    {
      "LeagueName": "UEFA Champions League",
      "LeagueLogo": "https://a.espncdn.com/i/leaguelogos/soccer/500/2.png",
      "GameTime": "3:00pm",
      "GameState": "",
      "HomeTeam": "Marseille",
      "HomeGoals": "",
      "HomeLogo": "https://a.espncdn.com/i/teamlogos/soccer/500/176.png",
      "AwayTeam": "Olympiakos",
      "AwayGoals": "",
      "AwayLogo": "https://a.espncdn.com/i/teamlogos/soccer/500/435.png",
      "TVChannels": "Piraeus fuboTV ,  TUDN.com ,  TUDNxtr…"
    },
    {
      "LeagueName": "UEFA Champions League",
      "LeagueLogo": "https://a.espncdn.com/i/leaguelogos/soccer/500/2.png",
      "GameTime": "3:00pm",
      "GameState": "",
      "HomeTeam": "Liverpool",
      "HomeGoals": "",
      "HomeLogo": "https://a.espncdn.com/i/teamlogos/soccer/500/364.png",
      "AwayTeam": "Ajax",
      "AwayGoals": "",
      "AwayLogo": "https://a.espncdn.com/i/teamlogos/soccer/500/139.png",
      "TVChannels": "fuboTV ,  TUDN.com ,  TUDNxtr…"
    },
    {
      "LeagueName": "UEFA Champions League",
      "LeagueLogo": "https://a.espncdn.com/i/leaguelogos/soccer/500/2.png",
      "GameTime": "3:00pm",
      "GameState": "",
      "HomeTeam": "Atalanta",
      "HomeGoals": "",
      "HomeLogo": "https://a.espncdn.com/i/teamlogos/soccer/500/105.png",
      "AwayTeam": "FC Midtjylland",
      "AwayGoals": "",
      "AwayLogo": "https://a.espncdn.com/i/teamlogos/soccer/500/572.png",
      "TVChannels": "fuboTV ,  TUDN.com ,  TUDNxtr…"
    }
  ]
}
