{
  "today": [
    {
      "LeagueName": "UEFA Champions League",
      "LeagueLogo": "https://a.espncdn.com/i/leaguelogos/soccer/500/2.png",
      "GameTime": "",
      "GameState": "",
      "HomeTeam": "",
      "HomeGoals": "",
      "HomeLogo": "",
      "AwayTeam": "",
      "AwayGoals": "",
      "AwayLogo": "",
      "TVChannels": "LeagueHeader"
    },
    {
      "LeagueName": "UEFA Champions League",
      "LeagueLogo": "https://a.espncdn.com/i/leaguelogos/soccer/500/2.png",
      "GameTime": "11:00am",
      "GameState": "AET",
      "HomeTeam": "Arar",
      "HomeGoals": "a",
      "HomeLogo": "",
      "AwayTeam": "menia  0 - 1  Omonia Nicosia *Qualifying Round 2020/2021 Sport 1 Hungary ,  Sport 2 CZ/SK ,  Sportbox…",
      "AwayGoals": "r",
      "AwayLogo": "",
      "TVChannels": "11:00am AET   Ararat-Armenia  0 - 1  Omonia Nicosia *Qualifying Round 2020/2021 Sport 1 Hungary ,  Sport 2 CZ/SK ,  Sportbox…"
    },
    {
      "LeagueName": "UEFA Champions League",
      "LeagueLogo": "https://a.espncdn.com/i/leaguelogos/soccer/500/2.png",
      "GameTime": "12:30pm",
      "GameState": "FT ",
      "HomeTeam": "Flora",
      "HomeGoals": "1",
      "HomeLogo": "",
      "AwayTeam": "P  Sūduva *Qualifying Round 2020/2021 ETV 2",
      "AwayGoals": "1",
      "AwayLogo": "",
      "TVChannels": "12:30pm FT   Flora  1 - 1 P  Sūduva *Qualifying Round 2020/2021 ETV 2"
    },
    {
      "LeagueName": "UEFA Champions League",
      "LeagueLogo": "https://a.espncdn.com/i/leaguelogos/soccer/500/2.png",
      "GameTime": "1:00pm",
      "GameState": "FT ",
      "HomeTeam": "Maccabi Tel Aviv",
      "HomeGoals": "2",
      "HomeLogo": "",
      "AwayTeam": "Riga *Qualifying Round 2020/2021 Sport 1",
      "AwayGoals": "0",
      "AwayLogo": "",
      "TVChannels": "1:00pm FT   Maccabi Tel Aviv  2 - 0  Riga *Qualifying Round 2020/2021 Sport 1"
    },
    {
      "LeagueName": "UEFA Champions League",
      "LeagueLogo": "https://a.espncdn.com/i/leaguelogos/soccer/500/2.png",
      "GameTime": "2:00pm",
      "GameState": "78 ",
      "HomeTeam": "Budućnost",
      "HomeGoals": "1",
      "HomeLogo": "",
      "AwayTeam": "Ludogorets *Qualifying Round 2020/2021 Arena Sport BIH ,  Diema Sport ,  Play Diema…",
      "AwayGoals": "2",
      "AwayLogo": "",
      "TVChannels": "2:00pm 78 '   Budućnost  1 - 2  Ludogorets *Qualifying Round 2020/2021 Arena Sport BIH ,  Diema Sport ,  Play Diema…"
    },
    {
      "LeagueName": "UEFA Champions League",
      "LeagueLogo": "https://a.espncdn.com/i/leaguelogos/soccer/500/2.png",
      "GameTime": "KÍ vs",
      "GameState": "Slo",
      "HomeTeam": "an Bratislava *Qualifying Round 2020/202",
      "HomeGoals": "1",
      "HomeLogo": "",
      "AwayTeam": "KÍ vs Slovan Bratislava *Qualifying Round 2020/2021",
      "AwayGoals": " ",
      "AwayLogo": "",
      "TVChannels": "KÍ vs Slovan Bratislava *Qualifying Round 2020/2021"
    },
    {
      "LeagueName": "UEFA Champions League",
      "LeagueLogo": "https://a.espncdn.com/i/leaguelogos/soccer/500/2.png",
      "GameTime": "2:00pm",
      "GameState": "",
      "HomeTeam": "Connah's Quay",
      "HomeGoals": "",
      "HomeLogo": "",
      "AwayTeam": "Sarajebo *Qualifying Round 2020/2021 BBC Wales",
      "AwayGoals": "",
      "AwayLogo": "",
      "TVChannels": "2:00pm   Connah's Quay vs Sarajebo *Qualifying Round 2020/2021 BBC Wales"
    },
    {
      "LeagueName": "UEFA Champions League",
      "LeagueLogo": "https://a.espncdn.com/i/leaguelogos/soccer/500/2.png",
      "GameTime": "3:00pm",
      "GameState": "35 ",
      "HomeTeam": "Olympique Lyonnais",
      "HomeGoals": "0",
      "HomeLogo": "cdn.livesoccertv.com/images/teams/france/logos/olympique-lyon.png",
      "AwayTeam": "Bayern München",
      "AwayGoals": "2",
      "AwayLogo": "cdn.livesoccertv.com/images/teams/germany/logos/bayern-munchen.png",
      "TVChannels": ""
    }
  ],
  "day2": [
    {
      "LeagueName": "UEFA Europa League",
      "LeagueLogo": "https://a.espncdn.com/i/leaguelogos/soccer/500/2310.png",
      "GameTime": "",
      "GameState": "",
      "HomeTeam": "",
      "HomeGoals": "",
      "HomeLogo": "",
      "AwayTeam": "",
      "AwayGoals": "",
      "AwayLogo": "",
      "TVChannels": "LeagueHeader"
    },
    {
      "LeagueName": "UEFA Europa League",
      "LeagueLogo": "https://a.espncdn.com/i/leaguelogos/soccer/500/2310.png",
      "GameTime": "2:00pm",
      "GameState": "",
      "HomeTeam": "Glentoran",
      "HomeGoals": "",
      "HomeLogo": "",
      "AwayTeam": "HB *Preliminary Round 2020/2021 BBC Sport Web",
      "AwayGoals": "",
      "AwayLogo": "",
      "TVChannels": "2:00pm   Glentoran vs HB *Preliminary Round 2020/2021 BBC Sport Web"
    },
    {
      "LeagueName": "UEFA Europa League",
      "LeagueLogo": "https://a.espncdn.com/i/leaguelogos/soccer/500/2310.png",
      "GameTime": "2:30pm",
      "GameState": "",
      "HomeTeam": "Coleraine",
      "HomeGoals": "",
      "HomeLogo": "",
      "AwayTeam": "La Fiorita *Preliminary Round 2020/2021 BBC Sport Web",
      "AwayGoals": "",
      "AwayLogo": "",
      "TVChannels": "2:30pm   Coleraine vs La Fiorita *Preliminary Round 2020/2021 BBC Sport Web"
    },
    {
      "LeagueName": "UEFA Europa League",
      "LeagueLogo": "https://a.espncdn.com/i/leaguelogos/soccer/500/2310.png",
      "GameTime": "7:00pm",
      "GameState": "",
      "HomeTeam": "New York RB",
      "HomeGoals": "",
      "HomeLogo": "",
      "AwayTeam": "New York City ESPN+ ,  fuboTV ,  ESPN App ,  …",
      "AwayGoals": "",
      "AwayLogo": "",
      "TVChannels": "7:00pm   New York RB vs New York City ESPN+ ,  fuboTV ,  ESPN App ,  …"
    },
    {
      "LeagueName": "UEFA Europa League",
      "LeagueLogo": "https://a.espncdn.com/i/leaguelogos/soccer/500/2310.png",
      "GameTime": "7:30pm",
      "GameState": "",
      "HomeTeam": "Columbus Crew",
      "HomeGoals": "",
      "HomeLogo": "",
      "AwayTeam": "Chicago Fire ESPN+ ,  fuboTV ,  ESPN App ,  …",
      "AwayGoals": "",
      "AwayLogo": "",
      "TVChannels": "7:30pm   Columbus Crew vs Chicago Fire ESPN+ ,  fuboTV ,  ESPN App ,  …"
    },
    {
      "LeagueName": "UEFA Europa League",
      "LeagueLogo": "https://a.espncdn.com/i/leaguelogos/soccer/500/2310.png",
      "GameTime": "7:30pm",
      "GameState": "",
      "HomeTeam": "New England",
      "HomeGoals": "",
      "HomeLogo": "",
      "AwayTeam": "Philadelphia Union ESPN+ ,  fuboTV ,  NBCSports…",
      "AwayGoals": "",
      "AwayLogo": "",
      "TVChannels": "7:30pm   New England vs Philadelphia Union ESPN+ ,  fuboTV ,  NBCSports…"
    },
    {
      "LeagueName": "UEFA Europa League",
      "LeagueLogo": "https://a.espncdn.com/i/leaguelogos/soccer/500/2310.png",
      "GameTime": "6:15pm",
      "GameState": "",
      "HomeTeam": "Sport Recife",
      "HomeGoals": "",
      "HomeLogo": "",
      "AwayTeam": "Santos Fanatiz Brasileirão ,  Arena Sport 3 ,  Premi…",
      "AwayGoals": "",
      "AwayLogo": "",
      "TVChannels": "6:15pm   Sport Recife vs Santos Fanatiz Brasileirão ,  Arena Sport 3 ,  Premi…"
    },
    {
      "LeagueName": "UEFA Europa League",
      "LeagueLogo": "https://a.espncdn.com/i/leaguelogos/soccer/500/2310.png",
      "GameTime": "7:00pm",
      "GameState": "",
      "HomeTeam": "São Paulo",
      "HomeGoals": "",
      "HomeLogo": "",
      "AwayTeam": "Bahia PFC Internacional ,  Fanatiz Brasileirão ,  …",
      "AwayGoals": "",
      "AwayLogo": "",
      "TVChannels": "7:00pm   São Paulo vs Bahia PFC Internacional ,  Fanatiz Brasileirão ,  …"
    },
    {
      "LeagueName": "UEFA Europa League",
      "LeagueLogo": "https://a.espncdn.com/i/leaguelogos/soccer/500/2310.png",
      "GameTime": "7:00pm",
      "GameState": "",
      "HomeTeam": "Ceará",
      "HomeGoals": "",
      "HomeLogo": "",
      "AwayTeam": "Vasco da Gama Fanatiz Brasileirão ,  Premiere FC Brasil ,  …",
      "AwayGoals": "",
      "AwayLogo": "",
      "TVChannels": "7:00pm   Ceará vs Vasco da Gama Fanatiz Brasileirão ,  Premiere FC Brasil ,  …"
    },
    {
      "LeagueName": "UEFA Europa League",
      "LeagueLogo": "https://a.espncdn.com/i/leaguelogos/soccer/500/2310.png",
      "GameTime": "4:00pm",
      "GameState": "",
      "HomeTeam": "São Caetano",
      "HomeGoals": "",
      "HomeLogo": "",
      "AwayTeam": "São Bernardo PFC Internacional",
      "AwayGoals": "",
      "AwayLogo": "",
      "TVChannels": "4:00pm   São Caetano vs São Bernardo PFC Internacional"
    },
    {
      "LeagueName": "UEFA Europa League",
      "LeagueLogo": "https://a.espncdn.com/i/leaguelogos/soccer/500/2310.png",
      "GameTime": "8:00pm",
      "GameState": "",
      "HomeTeam": "Edmonton",
      "HomeGoals": "",
      "HomeLogo": "",
      "AwayTeam": "Cavalry Fox Sports 2 ,  fuboTV ,  Foxspo…",
      "AwayGoals": "",
      "AwayLogo": "",
      "TVChannels": "8:00pm   Edmonton vs Cavalry Fox Sports 2 ,  fuboTV ,  Foxspo…"
    },
    {
      "LeagueName": "UEFA Europa League",
      "LeagueLogo": "https://a.espncdn.com/i/leaguelogos/soccer/500/2310.png",
      "GameTime": "6:00am",
      "GameState": "",
      "HomeTeam": "Guangzhou Evergrande",
      "HomeGoals": "",
      "HomeLogo": "",
      "AwayTeam": "Jiangsu Suning ESPN+ ,  ESPN App ,  DAZN ,  sportdigital ,  …",
      "AwayGoals": "",
      "AwayLogo": "",
      "TVChannels": "6:00am   Guangzhou Evergrande vs Jiangsu Suning ESPN+ ,  ESPN App ,  DAZN ,  sportdigital ,  …"
    },
    {
      "LeagueName": "UEFA Europa League",
      "LeagueLogo": "https://a.espncdn.com/i/leaguelogos/soccer/500/2310.png",
      "GameTime": "8:00am",
      "GameState": "",
      "HomeTeam": "Shenzhen Ruby",
      "HomeGoals": "",
      "HomeLogo": "",
      "AwayTeam": "Dalian Aerbin OVO Play",
      "AwayGoals": "",
      "AwayLogo": "",
      "TVChannels": "8:00am   Shenzhen Ruby vs Dalian Aerbin OVO Play"
    },
    {
      "LeagueName": "UEFA Europa League",
      "LeagueLogo": "https://a.espncdn.com/i/leaguelogos/soccer/500/2310.png",
      "GameTime": "10:00pm",
      "GameState": "",
      "HomeTeam": "Cancún",
      "HomeGoals": "",
      "HomeLogo": "",
      "AwayTeam": "Tampico Madero TUDN USA ,  TUDN ,  TUDN En Vivo",
      "AwayGoals": "",
      "AwayLogo": "",
      "TVChannels": "10:00pm   Cancún vs Tampico Madero TUDN USA ,  TUDN ,  TUDN En Vivo"
    },
    {
      "LeagueName": "UEFA Europa League",
      "LeagueLogo": "https://a.espncdn.com/i/leaguelogos/soccer/500/2310.png",
      "GameTime": "5:00pm",
      "GameState": "",
      "HomeTeam": "Cruz Azul",
      "HomeGoals": "",
      "HomeLogo": "",
      "AwayTeam": "Atlas fuboTV ,  TUDN USA ,  TUDN.com ,  T…",
      "AwayGoals": "",
      "AwayLogo": "",
      "TVChannels": "5:00pm   Cruz Azul vs Atlas fuboTV ,  TUDN USA ,  TUDN.com ,  T…"
    },
    {
      "LeagueName": "UEFA Europa League",
      "LeagueLogo": "https://a.espncdn.com/i/leaguelogos/soccer/500/2310.png",
      "GameTime": "4:00pm",
      "GameState": "",
      "HomeTeam": "Elche",
      "HomeGoals": "",
      "HomeLogo": "",
      "AwayTeam": "Girona *Promotion Play-Off beIN SPORTS ,  fuboTV ,  Fanatiz…",
      "AwayGoals": "",
      "AwayLogo": "",
      "TVChannels": "4:00pm   Elche vs Girona *Promotion Play-Off beIN SPORTS ,  fuboTV ,  Fanatiz…"
    },
    {
      "LeagueName": "UEFA Europa League",
      "LeagueLogo": "https://a.espncdn.com/i/leaguelogos/soccer/500/2310.png",
      "GameTime": "11:00am",
      "GameState": "",
      "HomeTeam": "Cerro",
      "HomeGoals": "",
      "HomeLogo": "",
      "AwayTeam": "Fénix GOLTV Play ,  GolTV Latinoamerica ,  VTV U…",
      "AwayGoals": "",
      "AwayLogo": "",
      "TVChannels": "11:00am   Cerro vs Fénix GOLTV Play ,  GolTV Latinoamerica ,  VTV U…"
    },
    {
      "LeagueName": "UEFA Europa League",
      "LeagueLogo": "https://a.espncdn.com/i/leaguelogos/soccer/500/2310.png",
      "GameTime": "2:00pm",
      "GameState": "",
      "HomeTeam": "Cerro Largo",
      "HomeGoals": "",
      "HomeLogo": "",
      "AwayTeam": "Liverpool",
      "AwayGoals": "",
      "AwayLogo": "cdn.livesoccertv.com/images/teams/england/logos/liverpool.png",
      "TVChannels": ""
    },
    {
      "LeagueName": "UEFA Europa League",
      "LeagueLogo": "https://a.espncdn.com/i/leaguelogos/soccer/500/2310.png",
      "GameTime": "4:30pm",
      "GameState": "",
      "HomeTeam": "Nacional",
      "HomeGoals": "",
      "HomeLogo": "",
      "AwayTeam": "Torque fuboTV ,  Fanatiz USA ,  GOLTV ,  Go…   Bahrain - Premier League   Brazil - Serie C   Brazil - Serie B   Iceland - Úrvalsdeild   Iran - Persian Gulf Pro League   Italy - Serie B   Jordan - Jordan League   Lithuania - A Lyga   Qatar - Qatar Stars League   Saudi Arabia - Pro League   Scotland - Scottish Premiership   South Africa - ABSA Premiership   Sudan - Sudan Premier League   Ukraine - Persha Liga   Uzbekistan - Uzbekistan Super League   World - Club Friendly   Zambia - Zambian Super League",
      "AwayGoals": "",
      "AwayLogo": "",
      "TVChannels": "4:30pm   Nacional vs Torque fuboTV ,  Fanatiz USA ,  GOLTV ,  Go…   Bahrain - Premier League   Brazil - Serie C   Brazil - Serie B   Iceland - Úrvalsdeild   Iran - Persian Gulf Pro League   Italy - Serie B   Jordan - Jordan League   Lithuania - A Lyga   Qatar - Qatar Stars League   Saudi Arabia - Pro League   Scotland - Scottish Premiership   South Africa - ABSA Premiership   Sudan - Sudan Premier League   Ukraine - Persha Liga   Uzbekistan - Uzbekistan Super League   World - Club Friendly   Zambia - Zambian Super League"
    }
  ],
  "day3": [
    {
      "LeagueName": "UEFA Europa League",
      "LeagueLogo": "https://a.espncdn.com/i/leaguelogos/soccer/500/2310.png",
      "GameTime": "",
      "GameState": "",
      "HomeTeam": "",
      "HomeGoals": "",
      "HomeLogo": "",
      "AwayTeam": "",
      "AwayGoals": "",
      "AwayLogo": "",
      "TVChannels": "LeagueHeader"
    },
    {
      "LeagueName": "UEFA Europa League",
      "LeagueLogo": "https://a.espncdn.com/i/leaguelogos/soccer/500/2310.png",
      "GameTime": "3:00pm",
      "GameState": "",
      "HomeTeam": "Sevilla",
      "HomeGoals": "",
      "HomeLogo": "cdn.livesoccertv.com/images/teams/spain/logos/sevilla.png",
      "AwayTeam": "Internazionale",
      "AwayGoals": "",
      "AwayLogo": "cdn.livesoccertv.com/images/teams/italy/logos/inter-milan.png",
      "TVChannels": ""
    },
    {
      "LeagueName": "UEFA Europa League",
      "LeagueLogo": "https://a.espncdn.com/i/leaguelogos/soccer/500/2310.png",
      "GameTime": "1:00pm",
      "GameState": "",
      "HomeTeam": "Bordeaux",
      "HomeGoals": "",
      "HomeLogo": "cdn.livesoccertv.com/images/teams/france/logos/bordeaux.png",
      "AwayTeam": "Nantes",
      "AwayGoals": "",
      "AwayLogo": "cdn.livesoccertv.com/images/teams/france/logos/nantes.png",
      "TVChannels": ""
    },
    {
      "LeagueName": "UEFA Europa League",
      "LeagueLogo": "https://a.espncdn.com/i/leaguelogos/soccer/500/2310.png",
      "GameTime": "Olymp",
      "GameState": "que",
      "HomeTeam": "Marseille vs Sai",
      "HomeGoals": "n",
      "HomeLogo": "",
      "AwayTeam": "ienne",
      "AwayGoals": "t",
      "AwayLogo": "",
      "TVChannels": "Olympique Marseille vs Saint-Étienne"
    }
  ],
  "day4": [
    {
      "LeagueName": "French Ligue 1",
      "LeagueLogo": "https://a.espncdn.com/i/leaguelogos/soccer/500/9.png",
      "GameTime": "",
      "GameState": "",
      "HomeTeam": "",
      "HomeGoals": "",
      "HomeLogo": "",
      "AwayTeam": "",
      "AwayGoals": "",
      "AwayLogo": "",
      "TVChannels": "LeagueHeader"
    },
    {
      "LeagueName": "French Ligue 1",
      "LeagueLogo": "https://a.espncdn.com/i/leaguelogos/soccer/500/9.png",
      "GameTime": "3:00pm",
      "GameState": "",
      "HomeTeam": "Lille",
      "HomeGoals": "",
      "HomeLogo": "cdn.livesoccertv.com/images/teams/france/logos/lille.png",
      "AwayTeam": "Rennes",
      "AwayGoals": "",
      "AwayLogo": "cdn.livesoccertv.com/images/teams/france/logos/stade-rennes.png",
      "TVChannels": ""
    },
    {
      "LeagueName": "French Ligue 1",
      "LeagueLogo": "https://a.espncdn.com/i/leaguelogos/soccer/500/9.png",
      "GameTime": "6:00pm",
      "GameState": "",
      "HomeTeam": "Atlas",
      "HomeGoals": "",
      "HomeLogo": "",
      "AwayTeam": "Querétaro fuboTV ,  TUDN USA ,  TUDN.com ,  Afi…",
      "AwayGoals": "",
      "AwayLogo": "",
      "TVChannels": "6:00pm   Atlas vs Querétaro fuboTV ,  TUDN USA ,  TUDN.com ,  Afi…"
    },
    {
      "LeagueName": "French Ligue 1",
      "LeagueLogo": "https://a.espncdn.com/i/leaguelogos/soccer/500/9.png",
      "GameTime": "8:00pm",
      "GameState": "",
      "HomeTeam": "Tigres UANL",
      "HomeGoals": "",
      "HomeLogo": "",
      "AwayTeam": "Pumas UNAM ESPN Deportes ,  ESPN Deportes+ ,  fubo…",
      "AwayGoals": "",
      "AwayLogo": "",
      "TVChannels": "8:00pm   Tigres UANL vs Pumas UNAM ESPN Deportes ,  ESPN Deportes+ ,  fubo…"
    },
    {
      "LeagueName": "French Ligue 1",
      "LeagueLogo": "https://a.espncdn.com/i/leaguelogos/soccer/500/9.png",
      "GameTime": "10:00pm",
      "GameState": "",
      "HomeTeam": "América",
      "HomeGoals": "",
      "HomeLogo": "",
      "AwayTeam": "Monterrey ESPN Deportes ,  ESPN Deportes+ ,  fubo…",
      "AwayGoals": "",
      "AwayLogo": "",
      "TVChannels": "10:00pm   América vs Monterrey ESPN Deportes ,  ESPN Deportes+ ,  fubo…"
    },
    {
      "LeagueName": "French Ligue 1",
      "LeagueLogo": "https://a.espncdn.com/i/leaguelogos/soccer/500/9.png",
      "GameTime": "6:00pm",
      "GameState": "",
      "HomeTeam": "Los Angeles FC",
      "HomeGoals": "",
      "HomeLogo": "",
      "AwayTeam": "LA Galaxy fuboTV ,  FOX Deportes ,  MLSsoccer…",
      "AwayGoals": "",
      "AwayLogo": "",
      "TVChannels": "6:00pm   Los Angeles FC vs LA Galaxy fuboTV ,  FOX Deportes ,  MLSsoccer…"
    },
    {
      "LeagueName": "French Ligue 1",
      "LeagueLogo": "https://a.espncdn.com/i/leaguelogos/soccer/500/9.png",
      "GameTime": "7:00pm",
      "GameState": "",
      "HomeTeam": "Atlanta United",
      "HomeGoals": "",
      "HomeLogo": "",
      "AwayTeam": "Nashville SC ESPN+ ,  fuboTV ,  ESPN App ,  …",
      "AwayGoals": "",
      "AwayLogo": "",
      "TVChannels": "7:00pm   Atlanta United vs Nashville SC ESPN+ ,  fuboTV ,  ESPN App ,  …"
    },
    {
      "LeagueName": "French Ligue 1",
      "LeagueLogo": "https://a.espncdn.com/i/leaguelogos/soccer/500/9.png",
      "GameTime": "8:00pm",
      "GameState": "",
      "HomeTeam": "Inter Miami",
      "HomeGoals": "",
      "HomeLogo": "",
      "AwayTeam": "Orlando City SC ESPN+ ,  fuboTV ,  ESPN App ,  U…",
      "AwayGoals": "",
      "AwayLogo": "",
      "TVChannels": "8:00pm   Inter Miami vs Orlando City SC ESPN+ ,  fuboTV ,  ESPN App ,  U…"
    },
    {
      "LeagueName": "French Ligue 1",
      "LeagueLogo": "https://a.espncdn.com/i/leaguelogos/soccer/500/9.png",
      "GameTime": "9:00pm",
      "GameState": "",
      "HomeTeam": "Colorado Rapids",
      "HomeGoals": "",
      "HomeLogo": "",
      "AwayTeam": "Real Salt Lake ESPN+ ,  ESPN App ,  MLSsoccer.com ,  …",
      "AwayGoals": "",
      "AwayLogo": "",
      "TVChannels": "9:00pm   Colorado Rapids vs Real Salt Lake ESPN+ ,  ESPN App ,  MLSsoccer.com ,  …"
    },
    {
      "LeagueName": "French Ligue 1",
      "LeagueLogo": "https://a.espncdn.com/i/leaguelogos/soccer/500/9.png",
      "GameTime": "3:00pm",
      "GameState": "",
      "HomeTeam": "Atlético PR",
      "HomeGoals": "",
      "HomeLogo": "",
      "AwayTeam": "Fluminense Fanatiz Brasileirão ,  Arena Sport 3 Serbi…",
      "AwayGoals": "",
      "AwayLogo": "",
      "TVChannels": "3:00pm   Atlético PR vs Fluminense Fanatiz Brasileirão ,  Arena Sport 3 Serbi…"
    },
    {
      "LeagueName": "French Ligue 1",
      "LeagueLogo": "https://a.espncdn.com/i/leaguelogos/soccer/500/9.png",
      "GameTime": "6:00pm",
      "GameState": "",
      "HomeTeam": "Internacional",
      "HomeGoals": "",
      "HomeLogo": "",
      "AwayTeam": "Atlético Mineiro Fanatiz Brasileirão ,  Arena Sport 3 ,  Premi…",
      "AwayGoals": "",
      "AwayLogo": "",
      "TVChannels": "6:00pm   Internacional vs Atlético Mineiro Fanatiz Brasileirão ,  Arena Sport 3 ,  Premi…"
    },
    {
      "LeagueName": "French Ligue 1",
      "LeagueLogo": "https://a.espncdn.com/i/leaguelogos/soccer/500/9.png",
      "GameTime": "8:00pm",
      "GameState": "",
      "HomeTeam": "Goiás",
      "HomeGoals": "",
      "HomeLogo": "",
      "AwayTeam": "Atlético GO PFC Internacional ,  Fanatiz Brasileirão ,  …",
      "AwayGoals": "",
      "AwayLogo": "",
      "TVChannels": "8:00pm   Goiás vs Atlético GO PFC Internacional ,  Fanatiz Brasileirão ,  …"
    },
    {
      "LeagueName": "French Ligue 1",
      "LeagueLogo": "https://a.espncdn.com/i/leaguelogos/soccer/500/9.png",
      "GameTime": "10:00am",
      "GameState": "",
      "HomeTeam": "Avaí",
      "HomeGoals": "",
      "HomeLogo": "",
      "AwayTeam": "Cuiabá PFC Internacional ,  Fanatiz Brasileirão ,  S…",
      "AwayGoals": "",
      "AwayLogo": "",
      "TVChannels": "10:00am   Avaí vs Cuiabá PFC Internacional ,  Fanatiz Brasileirão ,  S…"
    },
    {
      "LeagueName": "French Ligue 1",
      "LeagueLogo": "https://a.espncdn.com/i/leaguelogos/soccer/500/9.png",
      "GameTime": "3:30pm",
      "GameState": "",
      "HomeTeam": "Botafogo SP",
      "HomeGoals": "",
      "HomeLogo": "",
      "AwayTeam": "Figueirense Fanatiz Brasileirão ,  Premiere FC Brasil",
      "AwayGoals": "",
      "AwayLogo": "",
      "TVChannels": "3:30pm   Botafogo SP vs Figueirense Fanatiz Brasileirão ,  Premiere FC Brasil"
    },
    {
      "LeagueName": "French Ligue 1",
      "LeagueLogo": "https://a.espncdn.com/i/leaguelogos/soccer/500/9.png",
      "GameTime": "3:30pm",
      "GameState": "",
      "HomeTeam": "Náutico",
      "HomeGoals": "",
      "HomeLogo": "",
      "AwayTeam": "Juventude PFC Internacional ,  Fanatiz Brasileirão ,  …",
      "AwayGoals": "",
      "AwayLogo": "",
      "TVChannels": "3:30pm   Náutico vs Juventude PFC Internacional ,  Fanatiz Brasileirão ,  …"
    },
    {
      "LeagueName": "French Ligue 1",
      "LeagueLogo": "https://a.espncdn.com/i/leaguelogos/soccer/500/9.png",
      "GameTime": "6:00pm",
      "GameState": "",
      "HomeTeam": "CRB",
      "HomeGoals": "",
      "HomeLogo": "",
      "AwayTeam": "Vitória Fanatiz Brasileirão ,  SporTV ,  Premiere FC…",
      "AwayGoals": "",
      "AwayLogo": "",
      "TVChannels": "6:00pm   CRB vs Vitória Fanatiz Brasileirão ,  SporTV ,  Premiere FC…"
    },
    {
      "LeagueName": "French Ligue 1",
      "LeagueLogo": "https://a.espncdn.com/i/leaguelogos/soccer/500/9.png",
      "GameTime": "8:00pm",
      "GameState": "",
      "HomeTeam": "Brasil de Pelotas",
      "HomeGoals": "",
      "HomeLogo": "",
      "AwayTeam": "Sampaio Corrêa Fanatiz Brasileirão ,  Premiere FC Brasil",
      "AwayGoals": "",
      "AwayLogo": "",
      "TVChannels": "8:00pm   Brasil de Pelotas vs Sampaio Corrêa Fanatiz Brasileirão ,  Premiere FC Brasil"
    },
    {
      "LeagueName": "French Ligue 1",
      "LeagueLogo": "https://a.espncdn.com/i/leaguelogos/soccer/500/9.png",
      "GameTime": "1:00pm",
      "GameState": "",
      "HomeTeam": "York9",
      "HomeGoals": "",
      "HomeLogo": "",
      "AwayTeam": "Valour Fox Sports 2 ,  fuboTV ,  Foxspo…",
      "AwayGoals": "",
      "AwayLogo": "",
      "TVChannels": "1:00pm   York9 vs Valour Fox Sports 2 ,  fuboTV ,  Foxspo…"
    },
    {
      "LeagueName": "French Ligue 1",
      "LeagueLogo": "https://a.espncdn.com/i/leaguelogos/soccer/500/9.png",
      "GameTime": "4:00pm",
      "GameState": "",
      "HomeTeam": "Forge",
      "HomeGoals": "",
      "HomeLogo": "",
      "AwayTeam": "Pacific Fox Soccer Plus ,  fuboTV ,  OneSoccer",
      "AwayGoals": "",
      "AwayLogo": "",
      "TVChannels": "4:00pm   Forge vs Pacific Fox Soccer Plus ,  fuboTV ,  OneSoccer"
    },
    {
      "LeagueName": "French Ligue 1",
      "LeagueLogo": "https://a.espncdn.com/i/leaguelogos/soccer/500/9.png",
      "GameTime": "6:00am",
      "GameState": "",
      "HomeTeam": "Tianjin Teda",
      "HomeGoals": "",
      "HomeLogo": "",
      "AwayTeam": "Qingdao Huanghai OVO Play",
      "AwayGoals": "",
      "AwayLogo": "",
      "TVChannels": "6:00am   Tianjin Teda vs Qingdao Huanghai OVO Play"
    },
    {
      "LeagueName": "French Ligue 1",
      "LeagueLogo": "https://a.espncdn.com/i/leaguelogos/soccer/500/9.png",
      "GameTime": "8:00am",
      "GameState": "",
      "HomeTeam": "Beijing Guoan",
      "HomeGoals": "",
      "HomeLogo": "",
      "AwayTeam": "Shanghai SIPG ESPN+ ,  ESPN App ,  DAZN ,  sportdigital ,  …",
      "AwayGoals": "",
      "AwayLogo": "",
      "TVChannels": "8:00am   Beijing Guoan vs Shanghai SIPG ESPN+ ,  ESPN App ,  DAZN ,  sportdigital ,  …"
    },
    {
      "LeagueName": "French Ligue 1",
      "LeagueLogo": "https://a.espncdn.com/i/leaguelogos/soccer/500/9.png",
      "GameTime": "5:00am",
      "GameState": "",
      "HomeTeam": "Sementina",
      "HomeGoals": "",
      "HomeLogo": "",
      "AwayTeam": "Lugano",
      "AwayGoals": "",
      "AwayLogo": "",
      "TVChannels": "5:00am   Sementina vs Lugano"
    },
    {
      "LeagueName": "French Ligue 1",
      "LeagueLogo": "https://a.espncdn.com/i/leaguelogos/soccer/500/9.png",
      "GameTime": "5:50am",
      "GameState": "",
      "HomeTeam": "BK Frem",
      "HomeGoals": "",
      "HomeLogo": "",
      "AwayTeam": "Hillerod",
      "AwayGoals": "",
      "AwayLogo": "",
      "TVChannels": "5:50am   BK Frem vs Hillerod"
    },
    {
      "LeagueName": "French Ligue 1",
      "LeagueLogo": "https://a.espncdn.com/i/leaguelogos/soccer/500/9.png",
      "GameTime": "6:00am",
      "GameState": "",
      "HomeTeam": "Bronshoj",
      "HomeGoals": "",
      "HomeLogo": "",
      "AwayTeam": "Tarnby",
      "AwayGoals": "",
      "AwayLogo": "",
      "TVChannels": "6:00am   Bronshoj vs Tarnby"
    },
    {
      "LeagueName": "French Ligue 1",
      "LeagueLogo": "https://a.espncdn.com/i/leaguelogos/soccer/500/9.png",
      "GameTime": "6:00am",
      "GameState": "",
      "HomeTeam": "Górnik Łęczna",
      "HomeGoals": "",
      "HomeLogo": "",
      "AwayTeam": "Znicz Pruszków",
      "AwayGoals": "",
      "AwayLogo": "",
      "TVChannels": "6:00am   Górnik Łęczna vs Znicz Pruszków"
    },
    {
      "LeagueName": "French Ligue 1",
      "LeagueLogo": "https://a.espncdn.com/i/leaguelogos/soccer/500/9.png",
      "GameTime": "7:00am",
      "GameState": "",
      "HomeTeam": "FC Gutersloh",
      "HomeGoals": "",
      "HomeLogo": "",
      "AwayTeam": "Espelkamp",
      "AwayGoals": "",
      "AwayLogo": "",
      "TVChannels": "7:00am   FC Gutersloh vs Espelkamp"
    },
    {
      "LeagueName": "French Ligue 1",
      "LeagueLogo": "https://a.espncdn.com/i/leaguelogos/soccer/500/9.png",
      "GameTime": "7:00am",
      "GameState": "",
      "HomeTeam": "Lyngby",
      "HomeGoals": "",
      "HomeLogo": "",
      "AwayTeam": "Hvidovre",
      "AwayGoals": "",
      "AwayLogo": "",
      "TVChannels": "7:00am   Lyngby vs Hvidovre"
    },
    {
      "LeagueName": "French Ligue 1",
      "LeagueLogo": "https://a.espncdn.com/i/leaguelogos/soccer/500/9.png",
      "GameTime": "7:00am",
      "GameState": "",
      "HomeTeam": "Sparta Rotterdam",
      "HomeGoals": "",
      "HomeLogo": "",
      "AwayTeam": "NAC Breda",
      "AwayGoals": "",
      "AwayLogo": "",
      "TVChannels": "7:00am   Sparta Rotterdam vs NAC Breda"
    },
    {
      "LeagueName": "French Ligue 1",
      "LeagueLogo": "https://a.espncdn.com/i/leaguelogos/soccer/500/9.png",
      "GameTime": "7:00am",
      "GameState": "",
      "HomeTeam": "Vendsyssel",
      "HomeGoals": "",
      "HomeLogo": "",
      "AwayTeam": "Jammerbugt",
      "AwayGoals": "",
      "AwayLogo": "",
      "TVChannels": "7:00am   Vendsyssel vs Jammerbugt"
    },
    {
      "LeagueName": "French Ligue 1",
      "LeagueLogo": "https://a.espncdn.com/i/leaguelogos/soccer/500/9.png",
      "GameTime": "8:00am",
      "GameState": "",
      "HomeTeam": "AaB",
      "HomeGoals": "",
      "HomeLogo": "",
      "AwayTeam": "Silkeborg",
      "AwayGoals": "",
      "AwayLogo": "",
      "TVChannels": "8:00am   AaB vs Silkeborg"
    },
    {
      "LeagueName": "French Ligue 1",
      "LeagueLogo": "https://a.espncdn.com/i/leaguelogos/soccer/500/9.png",
      "GameTime": "8:00am",
      "GameState": "",
      "HomeTeam": "Almere City",
      "HomeGoals": "",
      "HomeLogo": "",
      "AwayTeam": "Groningen",
      "AwayGoals": "",
      "AwayLogo": "",
      "TVChannels": "8:00am   Almere City vs Groningen"
    },
    {
      "LeagueName": "French Ligue 1",
      "LeagueLogo": "https://a.espncdn.com/i/leaguelogos/soccer/500/9.png",
      "GameTime": "8:00am",
      "GameState": "",
      "HomeTeam": "Fleetwood Town",
      "HomeGoals": "",
      "HomeLogo": "",
      "AwayTeam": "Blackburn Rovers",
      "AwayGoals": "",
      "AwayLogo": "",
      "TVChannels": "8:00am   Fleetwood Town vs Blackburn Rovers"
    },
    {
      "LeagueName": "French Ligue 1",
      "LeagueLogo": "https://a.espncdn.com/i/leaguelogos/soccer/500/9.png",
      "GameTime": "8:00am",
      "GameState": "",
      "HomeTeam": "Mainz 05",
      "HomeGoals": "",
      "HomeLogo": "cdn.livesoccertv.com/images/teams/germany/logos/1-fsv-mainz-05.gif",
      "AwayTeam": "Sandhausen",
      "AwayGoals": "",
      "AwayLogo": "",
      "TVChannels": ""
    },
    {
      "LeagueName": "French Ligue 1",
      "LeagueLogo": "https://a.espncdn.com/i/leaguelogos/soccer/500/9.png",
      "GameTime": "8:00am",
      "GameState": "",
      "HomeTeam": "NEC",
      "HomeGoals": "",
      "HomeLogo": "",
      "AwayTeam": "RKC Waalwijk",
      "AwayGoals": "",
      "AwayLogo": "",
      "TVChannels": "8:00am   NEC vs RKC Waalwijk"
    },
    {
      "LeagueName": "French Ligue 1",
      "LeagueLogo": "https://a.espncdn.com/i/leaguelogos/soccer/500/9.png",
      "GameTime": "8:00am",
      "GameState": "",
      "HomeTeam": "Waldgirmes",
      "HomeGoals": "",
      "HomeLogo": "",
      "AwayTeam": "Eintracht Stadtallendorf",
      "AwayGoals": "",
      "AwayLogo": "",
      "TVChannels": "8:00am   Waldgirmes vs Eintracht Stadtallendorf"
    },
    {
      "LeagueName": "French Ligue 1",
      "LeagueLogo": "https://a.espncdn.com/i/leaguelogos/soccer/500/9.png",
      "GameTime": "8:00am",
      "GameState": "",
      "HomeTeam": "Queens Park Rangers",
      "HomeGoals": "",
      "HomeLogo": "",
      "AwayTeam": "AFC Wimbledon",
      "AwayGoals": "",
      "AwayLogo": "",
      "TVChannels": "8:00am   Queens Park Rangers vs AFC Wimbledon"
    },
    {
      "LeagueName": "French Ligue 1",
      "LeagueLogo": "https://a.espncdn.com/i/leaguelogos/soccer/500/9.png",
      "GameTime": "8:30am",
      "GameState": "",
      "HomeTeam": "Cambuur",
      "HomeGoals": "",
      "HomeLogo": "",
      "AwayTeam": "Dordrecht",
      "AwayGoals": "",
      "AwayLogo": "",
      "TVChannels": "8:30am   Cambuur vs Dordrecht"
    },
    {
      "LeagueName": "French Ligue 1",
      "LeagueLogo": "https://a.espncdn.com/i/leaguelogos/soccer/500/9.png",
      "GameTime": "8:30am",
      "GameState": "",
      "HomeTeam": "Freiburg",
      "HomeGoals": "",
      "HomeLogo": "cdn.livesoccertv.com/images/teams/germany/logos/sc-freiburg.png",
      "AwayTeam": "Dornbirn",
      "AwayGoals": "",
      "AwayLogo": "",
      "TVChannels": ""
    },
    {
      "LeagueName": "French Ligue 1",
      "LeagueLogo": "https://a.espncdn.com/i/leaguelogos/soccer/500/9.png",
      "GameTime": "8:30am",
      "GameState": "",
      "HomeTeam": "De Graafschap",
      "HomeGoals": "",
      "HomeLogo": "",
      "AwayTeam": "Heracles",
      "AwayGoals": "",
      "AwayLogo": "",
      "TVChannels": "8:30am   De Graafschap vs Heracles"
    },
    {
      "LeagueName": "French Ligue 1",
      "LeagueLogo": "https://a.espncdn.com/i/leaguelogos/soccer/500/9.png",
      "GameTime": "8:30am",
      "GameState": "",
      "HomeTeam": "Rijnsburgse Boys",
      "HomeGoals": "",
      "HomeLogo": "",
      "AwayTeam": "USV Hercules",
      "AwayGoals": "",
      "AwayLogo": "",
      "TVChannels": "8:30am   Rijnsburgse Boys vs USV Hercules"
    },
    {
      "LeagueName": "French Ligue 1",
      "LeagueLogo": "https://a.espncdn.com/i/leaguelogos/soccer/500/9.png",
      "GameTime": "9:00am",
      "GameState": "",
      "HomeTeam": "IJsselmeervogels",
      "HomeGoals": "",
      "HomeLogo": "",
      "AwayTeam": "Telstar",
      "AwayGoals": "",
      "AwayLogo": "",
      "TVChannels": "9:00am   IJsselmeervogels vs Telstar"
    },
    {
      "LeagueName": "French Ligue 1",
      "LeagueLogo": "https://a.espncdn.com/i/leaguelogos/soccer/500/9.png",
      "GameTime": "9:00am",
      "GameState": "",
      "HomeTeam": "Sportfreunde Lotte",
      "HomeGoals": "",
      "HomeLogo": "",
      "AwayTeam": "Werder Bremen",
      "AwayGoals": "",
      "AwayLogo": "cdn.livesoccertv.com/images/teams/germany/logos/werder-bremen.png",
      "TVChannels": ""
    },
    {
      "LeagueName": "French Ligue 1",
      "LeagueLogo": "https://a.espncdn.com/i/leaguelogos/soccer/500/9.png",
      "GameTime": "9:00am",
      "GameState": "",
      "HomeTeam": "1860 München",
      "HomeGoals": "",
      "HomeLogo": "",
      "AwayTeam": "Jahn Regensburg",
      "AwayGoals": "",
      "AwayLogo": "",
      "TVChannels": "9:00am   1860 München vs Jahn Regensburg"
    },
    {
      "LeagueName": "French Ligue 1",
      "LeagueLogo": "https://a.espncdn.com/i/leaguelogos/soccer/500/9.png",
      "GameTime": "9:00am",
      "GameState": "",
      "HomeTeam": "Paderborn",
      "HomeGoals": "",
      "HomeLogo": "",
      "AwayTeam": "Borussia M'gladbach",
      "AwayGoals": "",
      "AwayLogo": "cdn.livesoccertv.com/images/teams/germany/logos/borussia-mgladbach.png",
      "TVChannels": ""
    },
    {
      "LeagueName": "French Ligue 1",
      "LeagueLogo": "https://a.espncdn.com/i/leaguelogos/soccer/500/9.png",
      "GameTime": "9:00am",
      "GameState": "",
      "HomeTeam": "Sparta Nijkerk",
      "HomeGoals": "",
      "HomeLogo": "",
      "AwayTeam": "GVVV",
      "AwayGoals": "",
      "AwayLogo": "",
      "TVChannels": "9:00am   Sparta Nijkerk vs GVVV"
    },
    {
      "LeagueName": "French Ligue 1",
      "LeagueLogo": "https://a.espncdn.com/i/leaguelogos/soccer/500/9.png",
      "GameTime": "9:15am",
      "GameState": "",
      "HomeTeam": "AZ II",
      "HomeGoals": "",
      "HomeLogo": "",
      "AwayTeam": "AFC",
      "AwayGoals": "",
      "AwayLogo": "",
      "TVChannels": "9:15am   AZ II vs AFC"
    },
    {
      "LeagueName": "French Ligue 1",
      "LeagueLogo": "https://a.espncdn.com/i/leaguelogos/soccer/500/9.png",
      "GameTime": "9:30am",
      "GameState": "",
      "HomeTeam": "MSV Duisburg",
      "HomeGoals": "",
      "HomeLogo": "",
      "AwayTeam": "Borussia Dortmund",
      "AwayGoals": "",
      "AwayLogo": "cdn.livesoccertv.com/images/teams/germany/logos/borussia-dortmund.png",
      "TVChannels": ""
    },
    {
      "LeagueName": "French Ligue 1",
      "LeagueLogo": "https://a.espncdn.com/i/leaguelogos/soccer/500/9.png",
      "GameTime": "9:30am",
      "GameState": "",
      "HomeTeam": "Wolfsburg",
      "HomeGoals": "",
      "HomeLogo": "cdn.livesoccertv.com/images/teams/germany/logos/vfl-wolfsburg.gif",
      "AwayTeam": "Holstein Kiel",
      "AwayGoals": "",
      "AwayLogo": "",
      "TVChannels": ""
    },
    {
      "LeagueName": "French Ligue 1",
      "LeagueLogo": "https://a.espncdn.com/i/leaguelogos/soccer/500/9.png",
      "GameTime": "10:00am",
      "GameState": "",
      "HomeTeam": "Blackpool",
      "HomeGoals": "",
      "HomeLogo": "",
      "AwayTeam": "Everton",
      "AwayGoals": "",
      "AwayLogo": "cdn.livesoccertv.com/images/teams/england/logos/everton.png",
      "TVChannels": ""
    },
    {
      "LeagueName": "French Ligue 1",
      "LeagueLogo": "https://a.espncdn.com/i/leaguelogos/soccer/500/9.png",
      "GameTime": "10:00am",
      "GameState": "",
      "HomeTeam": "Salzburg",
      "HomeGoals": "",
      "HomeLogo": "",
      "AwayTeam": "Ajax ESPN Deportes ,  ESPN Deportes+ ,  ESP…",
      "AwayGoals": "",
      "AwayLogo": "",
      "TVChannels": "10:00am   Salzburg vs Ajax ESPN Deportes ,  ESPN Deportes+ ,  ESP…"
    },
    {
      "LeagueName": "French Ligue 1",
      "LeagueLogo": "https://a.espncdn.com/i/leaguelogos/soccer/500/9.png",
      "GameTime": "10:00am",
      "GameState": "",
      "HomeTeam": "Tottenham Hotspur",
      "HomeGoals": "",
      "HomeLogo": "cdn.livesoccertv.com/images/teams/england/logos/tottenham-hotspur.png",
      "AwayTeam": "Ipswich Town Sport 1 ,  Arena Sport 2 Serbia ,  Sport 1…",
      "AwayGoals": "",
      "AwayLogo": "",
      "TVChannels": ""
    },
    {
      "LeagueName": "French Ligue 1",
      "LeagueLogo": "https://a.espncdn.com/i/leaguelogos/soccer/500/9.png",
      "GameTime": "10:00am",
      "GameState": "",
      "HomeTeam": "United of Manchester",
      "HomeGoals": "",
      "HomeLogo": "",
      "AwayTeam": "Barrow",
      "AwayGoals": "",
      "AwayLogo": "",
      "TVChannels": "10:00am   United of Manchester vs Barrow"
    },
    {
      "LeagueName": "French Ligue 1",
      "LeagueLogo": "https://a.espncdn.com/i/leaguelogos/soccer/500/9.png",
      "GameTime": "10:00am",
      "GameState": "",
      "HomeTeam": "Melksham",
      "HomeGoals": "",
      "HomeLogo": "",
      "AwayTeam": "Chippenham",
      "AwayGoals": "",
      "AwayLogo": "",
      "TVChannels": "10:00am   Melksham vs Chippenham"
    },
    {
      "LeagueName": "French Ligue 1",
      "LeagueLogo": "https://a.espncdn.com/i/leaguelogos/soccer/500/9.png",
      "GameTime": "10:45am",
      "GameState": "",
      "HomeTeam": "Feyenoord",
      "HomeGoals": "",
      "HomeLogo": "",
      "AwayTeam": "Borussia Dortmund",
      "AwayGoals": "",
      "AwayLogo": "cdn.livesoccertv.com/images/teams/germany/logos/borussia-dortmund.png",
      "TVChannels": ""
    },
    {
      "LeagueName": "French Ligue 1",
      "LeagueLogo": "https://a.espncdn.com/i/leaguelogos/soccer/500/9.png",
      "GameTime": "11:00am",
      "GameState": "",
      "HomeTeam": "LASK Linz",
      "HomeGoals": "",
      "HomeLogo": "",
      "AwayTeam": "Karlsruher SC",
      "AwayGoals": "",
      "AwayLogo": "",
      "TVChannels": "11:00am   LASK Linz vs Karlsruher SC"
    },
    {
      "LeagueName": "French Ligue 1",
      "LeagueLogo": "https://a.espncdn.com/i/leaguelogos/soccer/500/9.png",
      "GameTime": "11:00am",
      "GameState": "",
      "HomeTeam": "Sturm Graz",
      "HomeGoals": "",
      "HomeLogo": "",
      "AwayTeam": "Lafnitz",
      "AwayGoals": "",
      "AwayLogo": "",
      "TVChannels": "11:00am   Sturm Graz vs Lafnitz"
    },
    {
      "LeagueName": "French Ligue 1",
      "LeagueLogo": "https://a.espncdn.com/i/leaguelogos/soccer/500/9.png",
      "GameTime": "12:00pm",
      "GameState": "",
      "HomeTeam": "Twente",
      "HomeGoals": "",
      "HomeLogo": "",
      "AwayTeam": "Go Ahead Eagles",
      "AwayGoals": "",
      "AwayLogo": "",
      "TVChannels": "12:00pm   Twente vs Go Ahead Eagles"
    },
    {
      "LeagueName": "French Ligue 1",
      "LeagueLogo": "https://a.espncdn.com/i/leaguelogos/soccer/500/9.png",
      "GameTime": "12:00pm",
      "GameState": "",
      "HomeTeam": "PSV",
      "HomeGoals": "",
      "HomeLogo": "",
      "AwayTeam": "Eintracht Frankfurt",
      "AwayGoals": "",
      "AwayLogo": "cdn.livesoccertv.com/images/teams/germany/logos/eintracht-frankfurt.png",
      "TVChannels": ""
    },
    {
      "LeagueName": "French Ligue 1",
      "LeagueLogo": "https://a.espncdn.com/i/leaguelogos/soccer/500/9.png",
      "GameTime": "12:00pm",
      "GameState": "",
      "HomeTeam": "Kapfenberger SV",
      "HomeGoals": "",
      "HomeLogo": "",
      "AwayTeam": "Blau-Weiß Linz",
      "AwayGoals": "",
      "AwayLogo": "",
      "TVChannels": "12:00pm   Kapfenberger SV vs Blau-Weiß Linz"
    },
    {
      "LeagueName": "French Ligue 1",
      "LeagueLogo": "https://a.espncdn.com/i/leaguelogos/soccer/500/9.png",
      "GameTime": "1:00pm",
      "GameState": "",
      "HomeTeam": "Valencia",
      "HomeGoals": "",
      "HomeLogo": "cdn.livesoccertv.com/images/teams/spain/logos/valencia.png",
      "AwayTeam": "Castellón Gol",
      "AwayGoals": "",
      "AwayLogo": "",
      "TVChannels": ""
    },
    {
      "LeagueName": "French Ligue 1",
      "LeagueLogo": "https://a.espncdn.com/i/leaguelogos/soccer/500/9.png",
      "GameTime": "1:30pm",
      "GameState": "",
      "HomeTeam": "Espanyol",
      "HomeGoals": "",
      "HomeLogo": "cdn.livesoccertv.com/images/teams/spain/logos/espanyol.png",
      "AwayTeam": "Huesca Esport3",
      "AwayGoals": "",
      "AwayLogo": "",
      "TVChannels": ""
    },
    {
      "LeagueName": "French Ligue 1",
      "LeagueLogo": "https://a.espncdn.com/i/leaguelogos/soccer/500/9.png",
      "GameTime": "4:30am",
      "GameState": "",
      "HomeTeam": "Incheon United",
      "HomeGoals": "",
      "HomeLogo": "",
      "AwayTeam": "Suwon Bluewings PPTV Sport China ,  JTBC Golf&Sports ,  Sk…",
      "AwayGoals": "",
      "AwayLogo": "",
      "TVChannels": "4:30am   Incheon United vs Suwon Bluewings PPTV Sport China ,  JTBC Golf&Sports ,  Sk…"
    },
    {
      "LeagueName": "French Ligue 1",
      "LeagueLogo": "https://a.espncdn.com/i/leaguelogos/soccer/500/9.png",
      "GameTime": "6:00am",
      "GameState": "",
      "HomeTeam": "Gwangju",
      "HomeGoals": "",
      "HomeLogo": "",
      "AwayTeam": "Seoul fuboTV ,  Eleven Sports Network USA ,  …",
      "AwayGoals": "",
      "AwayLogo": "",
      "TVChannels": "6:00am   Gwangju vs Seoul fuboTV ,  Eleven Sports Network USA ,  …"
    },
    {
      "LeagueName": "French Ligue 1",
      "LeagueLogo": "https://a.espncdn.com/i/leaguelogos/soccer/500/9.png",
      "GameTime": "6:00am",
      "GameState": "",
      "HomeTeam": "Busan I'Park",
      "HomeGoals": "",
      "HomeLogo": "",
      "AwayTeam": "Pohang Steelers Arena Sport 2 Serbia ,  MaxTV Go ,  PPTV S…",
      "AwayGoals": "",
      "AwayLogo": "",
      "TVChannels": "6:00am   Busan I'Park vs Pohang Steelers Arena Sport 2 Serbia ,  MaxTV Go ,  PPTV S…"
    },
    {
      "LeagueName": "French Ligue 1",
      "LeagueLogo": "https://a.espncdn.com/i/leaguelogos/soccer/500/9.png",
      "GameTime": "7:00am",
      "GameState": "",
      "HomeTeam": "Gangwon",
      "HomeGoals": "",
      "HomeLogo": "",
      "AwayTeam": "Daegu PPTV Sport China ,  JTBC Golf&Sports ,  Sk…",
      "AwayGoals": "",
      "AwayLogo": "",
      "TVChannels": "7:00am   Gangwon vs Daegu PPTV Sport China ,  JTBC Golf&Sports ,  Sk…"
    },
    {
      "LeagueName": "French Ligue 1",
      "LeagueLogo": "https://a.espncdn.com/i/leaguelogos/soccer/500/9.png",
      "GameTime": "11:00am",
      "GameState": "",
      "HomeTeam": "Mazatlán",
      "HomeGoals": "",
      "HomeLogo": "",
      "AwayTeam": "Tigres UANL",
      "AwayGoals": "",
      "AwayLogo": "",
      "TVChannels": "11:00am   Mazatlán vs Tigres UANL"
    },
    {
      "LeagueName": "French Ligue 1",
      "LeagueLogo": "https://a.espncdn.com/i/leaguelogos/soccer/500/9.png",
      "GameTime": "1:00pm",
      "GameState": "",
      "HomeTeam": "Pumas UNAM",
      "HomeGoals": "",
      "HomeLogo": "",
      "AwayTeam": "Toluca fuboTV ,  TUDN USA ,  TUDN.com ,  T…",
      "AwayGoals": "",
      "AwayLogo": "",
      "TVChannels": "1:00pm   Pumas UNAM vs Toluca fuboTV ,  TUDN USA ,  TUDN.com ,  T…"
    },
    {
      "LeagueName": "French Ligue 1",
      "LeagueLogo": "https://a.espncdn.com/i/leaguelogos/soccer/500/9.png",
      "GameTime": "7:00pm",
      "GameState": "",
      "HomeTeam": "Pittsburgh Riverhounds",
      "HomeGoals": "",
      "HomeLogo": "",
      "AwayTeam": "Saint Louis ESPN+ ,  ESPN App",
      "AwayGoals": "",
      "AwayLogo": "",
      "TVChannels": "7:00pm   Pittsburgh Riverhounds vs Saint Louis ESPN+ ,  ESPN App"
    },
    {
      "LeagueName": "French Ligue 1",
      "LeagueLogo": "https://a.espncdn.com/i/leaguelogos/soccer/500/9.png",
      "GameTime": "7:30pm",
      "GameState": "",
      "HomeTeam": "Birmingham Legion",
      "HomeGoals": "",
      "HomeLogo": "",
      "AwayTeam": "Memphis 901 ESPN+ ,  ESPN App",
      "AwayGoals": "",
      "AwayLogo": "",
      "TVChannels": "7:30pm   Birmingham Legion vs Memphis 901 ESPN+ ,  ESPN App"
    },
    {
      "LeagueName": "French Ligue 1",
      "LeagueLogo": "https://a.espncdn.com/i/leaguelogos/soccer/500/9.png",
      "GameTime": "7:30pm",
      "GameState": "",
      "HomeTeam": "Tampa Bay Rowdies",
      "HomeGoals": "",
      "HomeLogo": "",
      "AwayTeam": "Atlanta United II ESPN+ ,  ESPN App",
      "AwayGoals": "",
      "AwayLogo": "",
      "TVChannels": "7:30pm   Tampa Bay Rowdies vs Atlanta United II ESPN+ ,  ESPN App"
    },
    {
      "LeagueName": "French Ligue 1",
      "LeagueLogo": "https://a.espncdn.com/i/leaguelogos/soccer/500/9.png",
      "GameTime": "8:00pm",
      "GameState": "",
      "HomeTeam": "Sporting Kansas City II",
      "HomeGoals": "",
      "HomeLogo": "",
      "AwayTeam": "OKC Energy ESPN+ ,  ESPN App",
      "AwayGoals": "",
      "AwayLogo": "",
      "TVChannels": "8:00pm   Sporting Kansas City II vs OKC Energy ESPN+ ,  ESPN App"
    },
    {
      "LeagueName": "French Ligue 1",
      "LeagueLogo": "https://a.espncdn.com/i/leaguelogos/soccer/500/9.png",
      "GameTime": "8:00pm",
      "GameState": "",
      "HomeTeam": "Colorado Springs",
      "HomeGoals": "",
      "HomeLogo": "",
      "AwayTeam": "El Paso Locomotive ESPN+ ,  ESPN App",
      "AwayGoals": "",
      "AwayLogo": "",
      "TVChannels": "8:00pm   Colorado Springs vs El Paso Locomotive ESPN+ ,  ESPN App"
    },
    {
      "LeagueName": "French Ligue 1",
      "LeagueLogo": "https://a.espncdn.com/i/leaguelogos/soccer/500/9.png",
      "GameTime": "9:00pm",
      "GameState": "",
      "HomeTeam": "San Antonio",
      "HomeGoals": "",
      "HomeLogo": "",
      "AwayTeam": "FC Tulsa ESPN+ ,  ESPN App",
      "AwayGoals": "",
      "AwayLogo": "",
      "TVChannels": "9:00pm   San Antonio vs FC Tulsa ESPN+ ,  ESPN App"
    },
    {
      "LeagueName": "French Ligue 1",
      "LeagueLogo": "https://a.espncdn.com/i/leaguelogos/soccer/500/9.png",
      "GameTime": "9:00pm",
      "GameState": "",
      "HomeTeam": "Rio Grande Valley",
      "HomeGoals": "",
      "HomeLogo": "",
      "AwayTeam": "Austin Bold ESPN+ ,  ESPN App",
      "AwayGoals": "",
      "AwayLogo": "",
      "TVChannels": "9:00pm   Rio Grande Valley vs Austin Bold ESPN+ ,  ESPN App"
    },
    {
      "LeagueName": "French Ligue 1",
      "LeagueLogo": "https://a.espncdn.com/i/leaguelogos/soccer/500/9.png",
      "GameTime": "10:00pm",
      "GameState": "",
      "HomeTeam": "LA Galaxy II",
      "HomeGoals": "",
      "HomeLogo": "",
      "AwayTeam": "Orange County SC ESPN+ ,  ESPN App",
      "AwayGoals": "",
      "AwayLogo": "",
      "TVChannels": "10:00pm   LA Galaxy II vs Orange County SC ESPN+ ,  ESPN App"
    },
    {
      "LeagueName": "French Ligue 1",
      "LeagueLogo": "https://a.espncdn.com/i/leaguelogos/soccer/500/9.png",
      "GameTime": "10:00pm",
      "GameState": "",
      "HomeTeam": "Real Monarchs",
      "HomeGoals": "",
      "HomeLogo": "",
      "AwayTeam": "New Mexico United ESPN+ ,  ESPN App",
      "AwayGoals": "",
      "AwayLogo": "",
      "TVChannels": "10:00pm   Real Monarchs vs New Mexico United ESPN+ ,  ESPN App"
    },
    {
      "LeagueName": "French Ligue 1",
      "LeagueLogo": "https://a.espncdn.com/i/leaguelogos/soccer/500/9.png",
      "GameTime": "10:00pm",
      "GameState": "",
      "HomeTeam": "San Diego Loyal",
      "HomeGoals": "",
      "HomeLogo": "",
      "AwayTeam": "Reno 1868 ESPN App",
      "AwayGoals": "",
      "AwayLogo": "",
      "TVChannels": "10:00pm   San Diego Loyal vs Reno 1868 ESPN App"
    },
    {
      "LeagueName": "French Ligue 1",
      "LeagueLogo": "https://a.espncdn.com/i/leaguelogos/soccer/500/9.png",
      "GameTime": "10:30pm",
      "GameState": "",
      "HomeTeam": "Las Vegas Lights",
      "HomeGoals": "",
      "HomeLogo": "",
      "AwayTeam": "Phoenix Rising ESPN+ ,  ESPN App ,  SiriusXM FC",
      "AwayGoals": "",
      "AwayLogo": "",
      "TVChannels": "10:30pm   Las Vegas Lights vs Phoenix Rising ESPN+ ,  ESPN App ,  SiriusXM FC"
    },
    {
      "LeagueName": "French Ligue 1",
      "LeagueLogo": "https://a.espncdn.com/i/leaguelogos/soccer/500/9.png",
      "GameTime": "11:00pm",
      "GameState": "",
      "HomeTeam": "Sacramento Republic",
      "HomeGoals": "",
      "HomeLogo": "",
      "AwayTeam": "Portland Timbers II ESPN+ ,  ESPN App",
      "AwayGoals": "",
      "AwayLogo": "",
      "TVChannels": "11:00pm   Sacramento Republic vs Portland Timbers II ESPN+ ,  ESPN App"
    },
    {
      "LeagueName": "French Ligue 1",
      "LeagueLogo": "https://a.espncdn.com/i/leaguelogos/soccer/500/9.png",
      "GameTime": "1:00pm",
      "GameState": "",
      "HomeTeam": "Chattanooga Red Wolves",
      "HomeGoals": "",
      "HomeLogo": "",
      "AwayTeam": "Tormenta ESPN App",
      "AwayGoals": "",
      "AwayLogo": "",
      "TVChannels": "1:00pm   Chattanooga Red Wolves vs Tormenta ESPN App"
    },
    {
      "LeagueName": "French Ligue 1",
      "LeagueLogo": "https://a.espncdn.com/i/leaguelogos/soccer/500/9.png",
      "GameTime": "7:00pm",
      "GameState": "",
      "HomeTeam": "Greenville Triumph",
      "HomeGoals": "",
      "HomeLogo": "",
      "AwayTeam": "Roma",
      "AwayGoals": "",
      "AwayLogo": "cdn.livesoccertv.com/images/teams/italy/logos/as-roma.png",
      "TVChannels": "orZone   Australia - NPL WA   Austria - Regionalliga   Azerbaijan - Premier Liqa   Belarus - Premier League   Belgium - First Division A   Belgium - Belgian Cup   Belgium - First Division B   Bosnia and Herzegovina - Premijer Liga   Brazil - Serie C   Brazil - Serie D   Bulgaria - Parva Liga   Canada - Canadian Soccer League   Costa Rica - Primera Division   Croatia - 1. HNL   Croatia - Druga HNL   Cyprus - First Division   Czech Republic - Czech First League   Czech Republic - 2. Liga   Czech Republic - 3. Liga   Denmark - Elitedivisionen   Ecuador - Primera A   Egypt - Premier League   Estonia - Meistriliiga   Europe - UEFA Womens Champions League   Europe - UEFA Youth League   Finland - Veikkausliiga   Finland - Ykkönen   Finland - Kakkonen   France - Ligue 2   France - National 2   Germany - Regionalliga   Germany - Oberliga   Guatemala - Liga Nacional   Hungary - NB1   Iceland - Úrvalsdeild   Indonesia - Liga 1   Indonesia - Liga 2   Ireland Republic - Premier Division   Ireland Republic - First Division   Italy - Serie A (women)   Japan - J1 League   Japan - J2 League   Japan - J3 League   Kazakhstan - Kazakhstan Premier League   Korea Republic - K League 2   Latvia - Virsliga   Luxembourg - National Division   Malaysia - Super League   Moldova - Divizia Nationala   Morocco - Botola Pro   Nicaragua - Primera División   North Macedonia - Prva Liga   North Macedonia - Vtora Liga   Norway - Eliteserien   Norway - 2. Divisjon   Paraguay - Primera Division   Poland - Ekstraklasa   Poland - Puchar Polski   Romania - Liga I   Russia - Premier League   Russia - FNL   Scotland - Scottish Premiership   Serbia - Super Liga   Serbia - Prva Liga   Singapore - Singapore Premier League   Slovakia - Fortuna Liga   Slovakia - 2. Futbalová Liga   Slovakia - 3. Futbalová Liga   Slovenia - Prva Liga   Slovenia - Druga Liga   South Africa - ABSA Premiership   Sweden - Allsvenskan   Sweden - Superettan   Sweden - Division 1   Switzerland - 1. Liga Classic   Switzerland - 1. Liga Promotion   Thailand - Thai League 1   Thailand - Thai League 2   Tunisia - Ligue Professionnelle 1   Turkey - 2. Lig   Ukraine - Premier League   United States - NISA   Uruguay - Primera Division   Uzbekistan - Uzbekistan Super League   Zambia - Zambian Super League"
    }
  ],
  "day5": [
    {
      "LeagueName": "UEFA Champions League",
      "LeagueLogo": "https://a.espncdn.com/i/leaguelogos/soccer/500/2.png",
      "GameTime": "",
      "GameState": "",
      "HomeTeam": "",
      "HomeGoals": "",
      "HomeLogo": "",
      "AwayTeam": "",
      "AwayGoals": "",
      "AwayLogo": "",
      "TVChannels": "LeagueHeader"
    },
    {
      "LeagueName": "UEFA Champions League",
      "LeagueLogo": "https://a.espncdn.com/i/leaguelogos/soccer/500/2.png",
      "GameTime": "3:00pm",
      "GameState": "",
      "HomeTeam": "PSG",
      "HomeGoals": "",
      "HomeLogo": "cdn.livesoccertv.com/images/teams/france/logos/psg.png",
      "AwayTeam": "TBD *Final CBS Sports Network ,  fuboTV ,  T…",
      "AwayGoals": "",
      "AwayLogo": "",
      "TVChannels": ""
    },
    {
      "LeagueName": "French Ligue 1",
      "LeagueLogo": "https://a.espncdn.com/i/leaguelogos/soccer/500/9.png",
      "GameTime": "",
      "GameState": "",
      "HomeTeam": "",
      "HomeGoals": "",
      "HomeLogo": "",
      "AwayTeam": "",
      "AwayGoals": "",
      "AwayLogo": "",
      "TVChannels": "LeagueHeader"
    },
    {
      "LeagueName": "French Ligue 1",
      "LeagueLogo": "https://a.espncdn.com/i/leaguelogos/soccer/500/9.png",
      "GameTime": "7:00am",
      "GameState": "",
      "HomeTeam": "Monaco",
      "HomeGoals": "",
      "HomeLogo": "cdn.livesoccertv.com/images/teams/france/logos/monaco.png",
      "AwayTeam": "Roma",
      "AwayGoals": "",
      "AwayLogo": "cdn.livesoccertv.com/images/teams/italy/logos/as-roma.png",
      "TVChannels": ""
    },
    {
      "LeagueName": "French Ligue 1",
      "LeagueLogo": "https://a.espncdn.com/i/leaguelogos/soccer/500/9.png",
      "GameTime": "9:00am",
      "GameState": "",
      "HomeTeam": "Montpellier",
      "HomeGoals": "",
      "HomeLogo": "cdn.livesoccertv.com/images/teams/france/logos/montpellier.png",
      "AwayTeam": "Roma",
      "AwayGoals": "",
      "AwayLogo": "cdn.livesoccertv.com/images/teams/italy/logos/as-roma.png",
      "TVChannels": ""
    },
    {
      "LeagueName": "French Ligue 1",
      "LeagueLogo": "https://a.espncdn.com/i/leaguelogos/soccer/500/9.png",
      "GameTime": "9:00am",
      "GameState": "",
      "HomeTeam": "Dijon",
      "HomeGoals": "",
      "HomeLogo": "cdn.livesoccertv.com/images/teams/france/logos/dijon.png",
      "AwayTeam": "Angers SCO",
      "AwayGoals": "",
      "AwayLogo": "cdn.livesoccertv.com/images/teams/france/logos/angers.png",
      "TVChannels": ""
    },
    {
      "LeagueName": "French Ligue 1",
      "LeagueLogo": "https://a.espncdn.com/i/leaguelogos/soccer/500/9.png",
      "GameTime": "9:00am",
      "GameState": "",
      "HomeTeam": "Nîmes",
      "HomeGoals": "",
      "HomeLogo": "cdn.livesoccertv.com/images/teams/france/logos/nimes.png",
      "AwayTeam": "Brest",
      "AwayGoals": "",
      "AwayLogo": "cdn.livesoccertv.com/images/teams/france/logos/brest.png",
      "TVChannels": ""
    },
    {
      "LeagueName": "French Ligue 1",
      "LeagueLogo": "https://a.espncdn.com/i/leaguelogos/soccer/500/9.png",
      "GameTime": "9:00am",
      "GameState": "",
      "HomeTeam": "Lorient",
      "HomeGoals": "",
      "HomeLogo": "cdn.livesoccertv.com/images/teams/france/logos/lorient.png",
      "AwayTeam": "Strasbourg",
      "AwayGoals": "",
      "AwayLogo": "cdn.livesoccertv.com/images/teams/france/logos/strasbourg.png",
      "TVChannels": ""
    },
    {
      "LeagueName": "French Ligue 1",
      "LeagueLogo": "https://a.espncdn.com/i/leaguelogos/soccer/500/9.png",
      "GameTime": "11:00am",
      "GameState": "",
      "HomeTeam": "Nice",
      "HomeGoals": "",
      "HomeLogo": "cdn.livesoccertv.com/images/teams/france/logos/nice.png",
      "AwayTeam": "Lens",
      "AwayGoals": "",
      "AwayLogo": "cdn.livesoccertv.com/images/teams/france/logos/lens.png",
      "TVChannels": ""
    },
    {
      "LeagueName": "French Ligue 1",
      "LeagueLogo": "https://a.espncdn.com/i/leaguelogos/soccer/500/9.png",
      "GameTime": "6:30pm",
      "GameState": "",
      "HomeTeam": "Toluca",
      "HomeGoals": "",
      "HomeLogo": "",
      "AwayTeam": "Guadalajara ESPN Deportes ,  ESPN Deportes+ ,  fubo…",
      "AwayGoals": "",
      "AwayLogo": "",
      "TVChannels": "6:30pm   Toluca vs Guadalajara ESPN Deportes ,  ESPN Deportes+ ,  fubo…"
    },
    {
      "LeagueName": "French Ligue 1",
      "LeagueLogo": "https://a.espncdn.com/i/leaguelogos/soccer/500/9.png",
      "GameTime": "8:30pm",
      "GameState": "",
      "HomeTeam": "Atlético San Luis",
      "HomeGoals": "",
      "HomeLogo": "",
      "AwayTeam": "Cruz Azul fuboTV ,  TUDN USA ,  TUDN.com ,  …",
      "AwayGoals": "",
      "AwayLogo": "",
      "TVChannels": "8:30pm   Atlético San Luis vs Cruz Azul fuboTV ,  TUDN USA ,  TUDN.com ,  …"
    },
    {
      "LeagueName": "French Ligue 1",
      "LeagueLogo": "https://a.espncdn.com/i/leaguelogos/soccer/500/9.png",
      "GameTime": "10:06pm",
      "GameState": "",
      "HomeTeam": "Tijuana",
      "HomeGoals": "",
      "HomeLogo": "",
      "AwayTeam": "Puebla fuboTV ,  FOX Deportes ,  Foxsports…",
      "AwayGoals": "",
      "AwayLogo": "",
      "TVChannels": "10:06pm   Tijuana vs Puebla fuboTV ,  FOX Deportes ,  Foxsports…"
    },
    {
      "LeagueName": "French Ligue 1",
      "LeagueLogo": "https://a.espncdn.com/i/leaguelogos/soccer/500/9.png",
      "GameTime": "10:00pm",
      "GameState": "",
      "HomeTeam": "Portland Timbers",
      "HomeGoals": "",
      "HomeLogo": "",
      "AwayTeam": "Seattle Sounders FC Fox Sports 1 ,  fuboTV ,  MLSsoccer…",
      "AwayGoals": "",
      "AwayLogo": "",
      "TVChannels": "10:00pm   Portland Timbers vs Seattle Sounders FC Fox Sports 1 ,  fuboTV ,  MLSsoccer…"
    },
    {
      "LeagueName": "French Ligue 1",
      "LeagueLogo": "https://a.espncdn.com/i/leaguelogos/soccer/500/9.png",
      "GameTime": "10:00am",
      "GameState": "",
      "HomeTeam": "Flamengo",
      "HomeGoals": "",
      "HomeLogo": "",
      "AwayTeam": "Botafogo PFC Internacional ,  Fanatiz Brasileirão ,  …",
      "AwayGoals": "",
      "AwayLogo": "",
      "TVChannels": "10:00am   Flamengo vs Botafogo PFC Internacional ,  Fanatiz Brasileirão ,  …"
    },
    {
      "LeagueName": "French Ligue 1",
      "LeagueLogo": "https://a.espncdn.com/i/leaguelogos/soccer/500/9.png",
      "GameTime": "3:00pm",
      "GameState": "",
      "HomeTeam": "Vasco da Gama",
      "HomeGoals": "",
      "HomeLogo": "",
      "AwayTeam": "Grêmio PFC Internacional ,  Fanatiz Brasileirão ,  S…",
      "AwayGoals": "",
      "AwayLogo": "",
      "TVChannels": "3:00pm   Vasco da Gama vs Grêmio PFC Internacional ,  Fanatiz Brasileirão ,  S…"
    },
    {
      "LeagueName": "French Ligue 1",
      "LeagueLogo": "https://a.espncdn.com/i/leaguelogos/soccer/500/9.png",
      "GameTime": "3:00pm",
      "GameState": "",
      "HomeTeam": "Palmeiras",
      "HomeGoals": "",
      "HomeLogo": "",
      "AwayTeam": "Santos Fanatiz Brasileirão ,  Globo ,  GloboEsporte.co…",
      "AwayGoals": "",
      "AwayLogo": "",
      "TVChannels": "3:00pm   Palmeiras vs Santos Fanatiz Brasileirão ,  Globo ,  GloboEsporte.co…"
    },
    {
      "LeagueName": "French Ligue 1",
      "LeagueLogo": "https://a.espncdn.com/i/leaguelogos/soccer/500/9.png",
      "GameTime": "3:00pm",
      "GameState": "",
      "HomeTeam": "RB Bragantino",
      "HomeGoals": "",
      "HomeLogo": "",
      "AwayTeam": "Coritiba Fanatiz Brasileirão ,  Premiere FC Brasil",
      "AwayGoals": "",
      "AwayLogo": "",
      "TVChannels": "3:00pm   RB Bragantino vs Coritiba Fanatiz Brasileirão ,  Premiere FC Brasil"
    },
    {
      "LeagueName": "French Ligue 1",
      "LeagueLogo": "https://a.espncdn.com/i/leaguelogos/soccer/500/9.png",
      "GameTime": "5:00pm",
      "GameState": "",
      "HomeTeam": "Ceará",
      "HomeGoals": "",
      "HomeLogo": "",
      "AwayTeam": "Bahia Fanatiz Brasileirão ,  Premiere FC Brasil",
      "AwayGoals": "",
      "AwayLogo": "",
      "TVChannels": "5:00pm   Ceará vs Bahia Fanatiz Brasileirão ,  Premiere FC Brasil"
    },
    {
      "LeagueName": "French Ligue 1",
      "LeagueLogo": "https://a.espncdn.com/i/leaguelogos/soccer/500/9.png",
      "GameTime": "6:00pm",
      "GameState": "",
      "HomeTeam": "Sport Recife",
      "HomeGoals": "",
      "HomeLogo": "",
      "AwayTeam": "São Paulo PFC Internacional ,  Fanatiz Brasileirão ,  …",
      "AwayGoals": "",
      "AwayLogo": "",
      "TVChannels": "6:00pm   Sport Recife vs São Paulo PFC Internacional ,  Fanatiz Brasileirão ,  …"
    },
    {
      "LeagueName": "French Ligue 1",
      "LeagueLogo": "https://a.espncdn.com/i/leaguelogos/soccer/500/9.png",
      "GameTime": "12:00pm",
      "GameState": "",
      "HomeTeam": "Atlético Ottawa",
      "HomeGoals": "",
      "HomeLogo": "",
      "AwayTeam": "Edmonton Fox Sports 2 ,  fuboTV ,  Foxspo…",
      "AwayGoals": "",
      "AwayLogo": "",
      "TVChannels": "12:00pm   Atlético Ottawa vs Edmonton Fox Sports 2 ,  fuboTV ,  Foxspo…"
    },
    {
      "LeagueName": "French Ligue 1",
      "LeagueLogo": "https://a.espncdn.com/i/leaguelogos/soccer/500/9.png",
      "GameTime": "3:00pm",
      "GameState": "",
      "HomeTeam": "Cavalry",
      "HomeGoals": "",
      "HomeLogo": "",
      "AwayTeam": "HFX Wanderers Fox Sports 2 ,  fuboTV ,  Foxspo…",
      "AwayGoals": "",
      "AwayLogo": "",
      "TVChannels": "3:00pm   Cavalry vs HFX Wanderers Fox Sports 2 ,  fuboTV ,  Foxspo…"
    },
    {
      "LeagueName": "French Ligue 1",
      "LeagueLogo": "https://a.espncdn.com/i/leaguelogos/soccer/500/9.png",
      "GameTime": "5:00am",
      "GameState": "",
      "HomeTeam": "Jeonbuk Motors",
      "HomeGoals": "",
      "HomeLogo": "",
      "AwayTeam": "Sangju Sangmu Canal 11 ,  PPTV Sport China ,  JTBC Golf…",
      "AwayGoals": "",
      "AwayLogo": "",
      "TVChannels": "5:00am   Jeonbuk Motors vs Sangju Sangmu Canal 11 ,  PPTV Sport China ,  JTBC Golf…"
    },
    {
      "LeagueName": "French Ligue 1",
      "LeagueLogo": "https://a.espncdn.com/i/leaguelogos/soccer/500/9.png",
      "GameTime": "7:00am",
      "GameState": "",
      "HomeTeam": "Seongnam FC",
      "HomeGoals": "",
      "HomeLogo": "",
      "AwayTeam": "Ulsan fuboTV ,  Eleven Sports Network USA ,  …",
      "AwayGoals": "",
      "AwayLogo": "",
      "TVChannels": "7:00am   Seongnam FC vs Ulsan fuboTV ,  Eleven Sports Network USA ,  …"
    },
    {
      "LeagueName": "French Ligue 1",
      "LeagueLogo": "https://a.espncdn.com/i/leaguelogos/soccer/500/9.png",
      "GameTime": "4:00pm",
      "GameState": "",
      "HomeTeam": "Girona",
      "HomeGoals": "",
      "HomeLogo": "",
      "AwayTeam": "Elche *Promotion Play-Off beIN SPORTS ,  fuboTV ,  Fanatiz…",
      "AwayGoals": "",
      "AwayLogo": "",
      "TVChannels": "4:00pm   Girona vs Elche *Promotion Play-Off beIN SPORTS ,  fuboTV ,  Fanatiz…"
    },
    {
      "LeagueName": "French Ligue 1",
      "LeagueLogo": "https://a.espncdn.com/i/leaguelogos/soccer/500/9.png",
      "GameTime": "8:30am",
      "GameState": "",
      "HomeTeam": "Elfsborg",
      "HomeGoals": "",
      "HomeLogo": "",
      "AwayTeam": "Östersunds FK Dplay Sweden ,  Eurosport Player Spain ,  Euro…",
      "AwayGoals": "",
      "AwayLogo": "",
      "TVChannels": "8:30am   Elfsborg vs Östersunds FK Dplay Sweden ,  Eurosport Player Spain ,  Euro…"
    },
    {
      "LeagueName": "French Ligue 1",
      "LeagueLogo": "https://a.espncdn.com/i/leaguelogos/soccer/500/9.png",
      "GameTime": "8:30am",
      "GameState": "",
      "HomeTeam": "Malmö FF",
      "HomeGoals": "",
      "HomeLogo": "",
      "AwayTeam": "Falkenberg ESPN+ ,  ESPN App ,  Kanal 5 Sweden ,  Dpl…",
      "AwayGoals": "",
      "AwayLogo": "",
      "TVChannels": "8:30am   Malmö FF vs Falkenberg ESPN+ ,  ESPN App ,  Kanal 5 Sweden ,  Dpl…"
    },
    {
      "LeagueName": "French Ligue 1",
      "LeagueLogo": "https://a.espncdn.com/i/leaguelogos/soccer/500/9.png",
      "GameTime": "11:30am",
      "GameState": "",
      "HomeTeam": "AIK",
      "HomeGoals": "",
      "HomeLogo": "",
      "AwayTeam": "Helsingborg Dplay Sweden ,  Eurosport Player Spain ,  Euro…",
      "AwayGoals": "",
      "AwayLogo": "",
      "TVChannels": "11:30am   AIK vs Helsingborg Dplay Sweden ,  Eurosport Player Spain ,  Euro…"
    },
    {
      "LeagueName": "French Ligue 1",
      "LeagueLogo": "https://a.espncdn.com/i/leaguelogos/soccer/500/9.png",
      "GameTime": "11:30am",
      "GameState": "",
      "HomeTeam": "Varberg",
      "HomeGoals": "",
      "HomeLogo": "",
      "AwayTeam": "Örebro Dplay Sweden ,  Eurosport Player Spain ,  Euro…",
      "AwayGoals": "",
      "AwayLogo": "",
      "TVChannels": "11:30am   Varberg vs Örebro Dplay Sweden ,  Eurosport Player Spain ,  Euro…"
    },
    {
      "LeagueName": "French Ligue 1",
      "LeagueLogo": "https://a.espncdn.com/i/leaguelogos/soccer/500/9.png",
      "GameTime": "5:00pm",
      "GameState": "",
      "HomeTeam": "New York RB II",
      "HomeGoals": "",
      "HomeLogo": "",
      "AwayTeam": "Philadelphia Union II ESPN+ ,  ESPN App",
      "AwayGoals": "",
      "AwayLogo": "",
      "TVChannels": "5:00pm   New York RB II vs Philadelphia Union II ESPN+ ,  ESPN App"
    },
    {
      "LeagueName": "French Ligue 1",
      "LeagueLogo": "https://a.espncdn.com/i/leaguelogos/soccer/500/9.png",
      "GameTime": "7:00pm",
      "GameState": "",
      "HomeTeam": "Hartford Athletic",
      "HomeGoals": "",
      "HomeLogo": "",
      "AwayTeam": "Loudoun United ESPN+ ,  ESPN App ,  SiriusXM FC",
      "AwayGoals": "",
      "AwayLogo": "",
      "TVChannels": "7:00pm   Hartford Athletic vs Loudoun United ESPN+ ,  ESPN App ,  SiriusXM FC"
    },
    {
      "LeagueName": "French Ligue 1",
      "LeagueLogo": "https://a.espncdn.com/i/leaguelogos/soccer/500/9.png",
      "GameTime": "7:30pm",
      "GameState": "",
      "HomeTeam": "Miami FC",
      "HomeGoals": "",
      "HomeLogo": "",
      "AwayTeam": "Charlotte Independence ESPN+ ,  ESPN App",
      "AwayGoals": "",
      "AwayLogo": "",
      "TVChannels": "7:30pm   Miami FC vs Charlotte Independence ESPN+ ,  ESPN App"
    },
    {
      "LeagueName": "French Ligue 1",
      "LeagueLogo": "https://a.espncdn.com/i/leaguelogos/soccer/500/9.png",
      "GameTime": "5:00pm",
      "GameState": "",
      "HomeTeam": "Forward Madison",
      "HomeGoals": "",
      "HomeLogo": "",
      "AwayTeam": "Orlando City II ESPN+ ,  ESPN App",
      "AwayGoals": "",
      "AwayLogo": "",
      "TVChannels": "5:00pm   Forward Madison vs Orlando City II ESPN+ ,  ESPN App"
    },
    {
      "LeagueName": "French Ligue 1",
      "LeagueLogo": "https://a.espncdn.com/i/leaguelogos/soccer/500/9.png",
      "GameTime": "9:00pm",
      "GameState": "",
      "HomeTeam": "North Texas",
      "HomeGoals": "",
      "HomeLogo": "",
      "AwayTeam": "Roma",
      "AwayGoals": "",
      "AwayLogo": "cdn.livesoccertv.com/images/teams/italy/logos/as-roma.png",
      "TVChannels": "a   Belarus - Premier League   Belgium - First Division A   Belgium - Belgian Cup   Belgium - First Division B   Bosnia and Herzegovina - Premijer Liga   Brazil - Serie B   Brazil - Serie C   Brazil - Serie D   Bulgaria - Parva Liga   Bulgaria - B Group   Colombia - Primera A   Costa Rica - Primera Division   Croatia - 1. HNL   Croatia - Druga HNL   Cyprus - First Division   Czech Republic - Czech First League   Czech Republic - 2. Liga   Czech Republic - 3. Liga   Denmark - Elitedivisionen   Ecuador - Primera A   Egypt - Premier League   Estonia - Meistriliiga   Faroe Islands - Premier League   Finland - Veikkausliiga   Finland - Ykkönen   Finland - Kakkonen   Germany - Regionalliga   Germany - Oberliga   Hungary - NB1   Hungary - Nemzeti Bajnokság II   Indonesia - Liga 1   Ireland Republic - Premier Division   Japan - J1 League   Japan - J2 League   Japan - J3 League   Kazakhstan - Kazakhstan Premier League   Korea Republic - K League 2   Latvia - Virsliga   Luxembourg - National Division   Mexico - Liga de Expansión MX   Mexico - Liga MX Femenil   Moldova - Divizia Nationala   Montenegro - Prva Crnogorska Liga   Morocco - Botola Pro   Nicaragua - Primera División   North Macedonia - Prva Liga   Norway - 2. Divisjon   Paraguay - Primera Division   Paraguay - Segunda División   Peru - Primera Division   Poland - Ekstraklasa   Poland - Puchar Polski   Romania - Liga I   Russia - Premier League   Scotland - Scottish Premiership   Serbia - Super Liga   Slovakia - 2. Futbalová Liga   Slovakia - 3. Futbalová Liga   Slovenia - Druga Liga   South Africa - ABSA Premiership   Sweden - Superettan   Sweden - Division 1   Switzerland - 1. Liga Classic   Switzerland - 1. Liga Promotion   Tajikistan - Tajik League   Thailand - Thai League 1   Thailand - Thai League 2   Tunisia - Ligue Professionnelle 1   Ukraine - Premier League   Uruguay - Primera Division   Venezuela - Primera División   World - Club Friendly   Zambia - Zambian Super League"
    }
  ],
  "day6": [
    {
      "LeagueName": "Major League Soccer",
      "LeagueLogo": "https://a.espncdn.com/i/leaguelogos/soccer/500/19.png",
      "GameTime": "",
      "GameState": "",
      "HomeTeam": "",
      "HomeGoals": "",
      "HomeLogo": "",
      "AwayTeam": "",
      "AwayGoals": "",
      "AwayLogo": "",
      "TVChannels": "LeagueHeader"
    },
    {
      "LeagueName": "Major League Soccer",
      "LeagueLogo": "https://a.espncdn.com/i/leaguelogos/soccer/500/19.png",
      "GameTime": "7:00pm",
      "GameState": "",
      "HomeTeam": "New York City",
      "HomeGoals": "",
      "HomeLogo": "",
      "AwayTeam": "Columbus Crew ESPN+ ,  fuboTV ,  ESPN App ,  …",
      "AwayGoals": "",
      "AwayLogo": "",
      "TVChannels": "7:00pm   New York City vs Columbus Crew ESPN+ ,  fuboTV ,  ESPN App ,  …"
    },
    {
      "LeagueName": "Major League Soccer",
      "LeagueLogo": "https://a.espncdn.com/i/leaguelogos/soccer/500/19.png",
      "GameTime": "7:00pm",
      "GameState": "",
      "HomeTeam": "Chapecoense",
      "HomeGoals": "",
      "HomeLogo": "",
      "AwayTeam": "Guarani PFC Internacional ,  Fanatiz Brasileirão ,  S…",
      "AwayGoals": "",
      "AwayLogo": "",
      "TVChannels": "7:00pm   Chapecoense vs Guarani PFC Internacional ,  Fanatiz Brasileirão ,  S…"
    },
    {
      "LeagueName": "Major League Soccer",
      "LeagueLogo": "https://a.espncdn.com/i/leaguelogos/soccer/500/19.png",
      "GameTime": "6:00am",
      "GameState": "",
      "HomeTeam": "Henan Jianye",
      "HomeGoals": "",
      "HomeLogo": "",
      "AwayTeam": "Shanghai Shenhua ESPN+ ,  ESPN App ,  DAZN ,  sportdigital ,  …",
      "AwayGoals": "",
      "AwayLogo": "",
      "TVChannels": "6:00am   Henan Jianye vs Shanghai Shenhua ESPN+ ,  ESPN App ,  DAZN ,  sportdigital ,  …"
    },
    {
      "LeagueName": "Major League Soccer",
      "LeagueLogo": "https://a.espncdn.com/i/leaguelogos/soccer/500/19.png",
      "GameTime": "8:00am",
      "GameState": "",
      "HomeTeam": "Jiangsu Suning",
      "HomeGoals": "",
      "HomeLogo": "",
      "AwayTeam": "Shenzhen Ruby OVO Play",
      "AwayGoals": "",
      "AwayLogo": "",
      "TVChannels": "8:00am   Jiangsu Suning vs Shenzhen Ruby OVO Play"
    },
    {
      "LeagueName": "Major League Soccer",
      "LeagueLogo": "https://a.espncdn.com/i/leaguelogos/soccer/500/19.png",
      "GameTime": "7:00am",
      "GameState": "",
      "HomeTeam": "Werder Bremen",
      "HomeGoals": "",
      "HomeLogo": "cdn.livesoccertv.com/images/teams/germany/logos/werder-bremen.png",
      "AwayTeam": "Austria Lustenau",
      "AwayGoals": "",
      "AwayLogo": "",
      "TVChannels": ""
    },
    {
      "LeagueName": "Major League Soccer",
      "LeagueLogo": "https://a.espncdn.com/i/leaguelogos/soccer/500/19.png",
      "GameTime": "12:00pm",
      "GameState": "",
      "HomeTeam": "Schalke 04",
      "HomeGoals": "",
      "HomeLogo": "cdn.livesoccertv.com/images/teams/germany/logos/schalke-04.png",
      "AwayTeam": "Würzburger Kickers ESPN Deportes ,  ESPN Deportes+ ,  ESP…",
      "AwayGoals": "",
      "AwayLogo": "",
      "TVChannels": ""
    },
    {
      "LeagueName": "Major League Soccer",
      "LeagueLogo": "https://a.espncdn.com/i/leaguelogos/soccer/500/19.png",
      "GameTime": "2:30pm",
      "GameState": "",
      "HomeTeam": "Birkirkara",
      "HomeGoals": "",
      "HomeLogo": "",
      "AwayTeam": "Roma",
      "AwayGoals": "",
      "AwayLogo": "cdn.livesoccertv.com/images/teams/italy/logos/as-roma.png",
      "TVChannels": "MX Femenil   Norway - Eliteserien   Norway - OBOS-ligaen   Norway - 2. Divisjon   Poland - Ekstraklasa   Romania - Liga I   Saudi Arabia - Pro League   South Africa - ABSA Premiership   Sweden - Allsvenskan   Sweden - Superettan   Sweden - Division 1   Tajikistan - Tajik League   Uzbekistan - Uzbekistan Super League"
    }
  ],
  "day7": [
    {
      "LeagueName": "UEFA Champions League",
      "LeagueLogo": "https://a.espncdn.com/i/leaguelogos/soccer/500/2.png",
      "GameTime": "",
      "GameState": "",
      "HomeTeam": "",
      "HomeGoals": "",
      "HomeLogo": "",
      "AwayTeam": "",
      "AwayGoals": "",
      "AwayLogo": "",
      "TVChannels": "LeagueHeader"
    },
    {
      "LeagueName": "UEFA Champions League",
      "LeagueLogo": "https://a.espncdn.com/i/leaguelogos/soccer/500/2.png",
      "GameTime": "3:00pm",
      "GameState": "",
      "HomeTeam": "PAOK",
      "HomeGoals": "",
      "HomeLogo": "",
      "AwayTeam": "Beşiktaş *2nd Qualifying Round 2020/2021 D-Smart GO ,  Spor Smart",
      "AwayGoals": "",
      "AwayLogo": "",
      "TVChannels": "3:00pm   PAOK vs Beşiktaş *2nd Qualifying Round 2020/2021 D-Smart GO ,  Spor Smart"
    },
    {
      "LeagueName": "UEFA Champions League",
      "LeagueLogo": "https://a.espncdn.com/i/leaguelogos/soccer/500/2.png",
      "GameTime": "7:00pm",
      "GameState": "",
      "HomeTeam": "DC United",
      "HomeGoals": "",
      "HomeLogo": "",
      "AwayTeam": "New England ESPN+ ,  fuboTV ,  NBCSports…",
      "AwayGoals": "",
      "AwayLogo": "",
      "TVChannels": "7:00pm   DC United vs New England ESPN+ ,  fuboTV ,  NBCSports…"
    },
    {
      "LeagueName": "UEFA Champions League",
      "LeagueLogo": "https://a.espncdn.com/i/leaguelogos/soccer/500/2.png",
      "GameTime": "7:30pm",
      "GameState": "",
      "HomeTeam": "Chicago Fire",
      "HomeGoals": "",
      "HomeLogo": "",
      "AwayTeam": "Cincinnati ESPN+ ,  ESPN App ,  MLSsoccer.com ,  …",
      "AwayGoals": "",
      "AwayLogo": "",
      "TVChannels": "7:30pm   Chicago Fire vs Cincinnati ESPN+ ,  ESPN App ,  MLSsoccer.com ,  …"
    },
    {
      "LeagueName": "UEFA Champions League",
      "LeagueLogo": "https://a.espncdn.com/i/leaguelogos/soccer/500/2.png",
      "GameTime": "7:30pm",
      "GameState": "",
      "HomeTeam": "Philadelphia Union",
      "HomeGoals": "",
      "HomeLogo": "",
      "AwayTeam": "New York RB ESPN+ ,  ESPN App ,  MLSsoccer.com ,  …",
      "AwayGoals": "",
      "AwayLogo": "",
      "TVChannels": "7:30pm   Philadelphia Union vs New York RB ESPN+ ,  ESPN App ,  MLSsoccer.com ,  …"
    },
    {
      "LeagueName": "UEFA Champions League",
      "LeagueLogo": "https://a.espncdn.com/i/leaguelogos/soccer/500/2.png",
      "GameTime": "8:00pm",
      "GameState": "",
      "HomeTeam": "Montreal Impact",
      "HomeGoals": "",
      "HomeLogo": "",
      "AwayTeam": "Vancouver Whitecaps ESPN+ ,  MLSsoccer.com ,  MLS App ,  …",
      "AwayGoals": "",
      "AwayLogo": "",
      "TVChannels": "8:00pm   Montreal Impact vs Vancouver Whitecaps ESPN+ ,  MLSsoccer.com ,  MLS App ,  …"
    },
    {
      "LeagueName": "UEFA Champions League",
      "LeagueLogo": "https://a.espncdn.com/i/leaguelogos/soccer/500/2.png",
      "GameTime": "8:30pm",
      "GameState": "",
      "HomeTeam": "Sporting KC",
      "HomeGoals": "",
      "HomeLogo": "",
      "AwayTeam": "Houston Dynamo ESPN+ ,  fuboTV ,  ESPN App ,  …",
      "AwayGoals": "",
      "AwayLogo": "",
      "TVChannels": "8:30pm   Sporting KC vs Houston Dynamo ESPN+ ,  fuboTV ,  ESPN App ,  …"
    },
    {
      "LeagueName": "UEFA Champions League",
      "LeagueLogo": "https://a.espncdn.com/i/leaguelogos/soccer/500/2.png",
      "GameTime": "3:00pm",
      "GameState": "",
      "HomeTeam": "Afogados",
      "HomeGoals": "",
      "HomeLogo": "",
      "AwayTeam": "Ponte Preta PFC Internacional ,  SporTV ,  SporTV Play",
      "AwayGoals": "",
      "AwayLogo": "",
      "TVChannels": "3:00pm   Afogados vs Ponte Preta PFC Internacional ,  SporTV ,  SporTV Play"
    },
    {
      "LeagueName": "UEFA Champions League",
      "LeagueLogo": "https://a.espncdn.com/i/leaguelogos/soccer/500/2.png",
      "GameTime": "6:00pm",
      "GameState": "",
      "HomeTeam": "América Mineiro",
      "HomeGoals": "",
      "HomeLogo": "",
      "AwayTeam": "Ferroviária PFC Internacional ,  SporTV ,  SporTV Play",
      "AwayGoals": "",
      "AwayLogo": "",
      "TVChannels": "6:00pm   América Mineiro vs Ferroviária PFC Internacional ,  SporTV ,  SporTV Play"
    },
    {
      "LeagueName": "UEFA Champions League",
      "LeagueLogo": "https://a.espncdn.com/i/leaguelogos/soccer/500/2.png",
      "GameTime": "8:30pm",
      "GameState": "",
      "HomeTeam": "Fluminense",
      "HomeGoals": "",
      "HomeLogo": "",
      "AwayTeam": "Figueirense PFC Internacional ,  SporTV ,  SporTV Play",
      "AwayGoals": "",
      "AwayLogo": "",
      "TVChannels": "8:30pm   Fluminense vs Figueirense PFC Internacional ,  SporTV ,  SporTV Play"
    },
    {
      "LeagueName": "UEFA Champions League",
      "LeagueLogo": "https://a.espncdn.com/i/leaguelogos/soccer/500/2.png",
      "GameTime": "8:00pm",
      "GameState": "",
      "HomeTeam": "Pacific",
      "HomeGoals": "",
      "HomeLogo": "",
      "AwayTeam": "Valour Fox Sports 2 ,  fuboTV ,  Foxspo…",
      "AwayGoals": "",
      "AwayLogo": "",
      "TVChannels": "8:00pm   Pacific vs Valour Fox Sports 2 ,  fuboTV ,  Foxspo…"
    },
    {
      "LeagueName": "UEFA Champions League",
      "LeagueLogo": "https://a.espncdn.com/i/leaguelogos/soccer/500/2.png",
      "GameTime": "8:00am",
      "GameState": "",
      "HomeTeam": "Plymouth Argyle",
      "HomeGoals": "",
      "HomeLogo": "",
      "AwayTeam": "Middlesbrough",
      "AwayGoals": "",
      "AwayLogo": "",
      "TVChannels": "8:00am   Plymouth Argyle vs Middlesbrough"
    },
    {
      "LeagueName": "UEFA Champions League",
      "LeagueLogo": "https://a.espncdn.com/i/leaguelogos/soccer/500/2.png",
      "GameTime": "10:00am",
      "GameState": "",
      "HomeTeam": "Feyenoord",
      "HomeGoals": "",
      "HomeLogo": "",
      "AwayTeam": "Arminia Bielefeld",
      "AwayGoals": "",
      "AwayLogo": "cdn.livesoccertv.com/images/teams/germany/logos/arminia-bielefeld.png",
      "TVChannels": ""
    },
    {
      "LeagueName": "UEFA Champions League",
      "LeagueLogo": "https://a.espncdn.com/i/leaguelogos/soccer/500/2.png",
      "GameTime": "12:30pm",
      "GameState": "",
      "HomeTeam": "Sheffield United",
      "HomeGoals": "",
      "HomeLogo": "cdn.livesoccertv.com/images/teams/england/logos/sheffield-united.png",
      "AwayTeam": "Lausanne-Sport C More Fotball ,  C More Play",
      "AwayGoals": "",
      "AwayLogo": "",
      "TVChannels": ""
    },
    {
      "LeagueName": "UEFA Champions League",
      "LeagueLogo": "https://a.espncdn.com/i/leaguelogos/soccer/500/2.png",
      "GameTime": "12:30pm",
      "GameState": "",
      "HomeTeam": "Viktoria Aschaffenburg",
      "HomeGoals": "",
      "HomeLogo": "",
      "AwayTeam": "Kickers Offenbach",
      "AwayGoals": "",
      "AwayLogo": "",
      "TVChannels": "12:30pm   Viktoria Aschaffenburg vs Kickers Offenbach"
    },
    {
      "LeagueName": "UEFA Champions League",
      "LeagueLogo": "https://a.espncdn.com/i/leaguelogos/soccer/500/2.png",
      "GameTime": "1:00pm",
      "GameState": "",
      "HomeTeam": "Blau-Weiß Linz",
      "HomeGoals": "",
      "HomeLogo": "",
      "AwayTeam": "Austria Wien II",
      "AwayGoals": "",
      "AwayLogo": "",
      "TVChannels": "1:00pm   Blau-Weiß Linz vs Austria Wien II"
    },
    {
      "LeagueName": "UEFA Champions League",
      "LeagueLogo": "https://a.espncdn.com/i/leaguelogos/soccer/500/2.png",
      "GameTime": "1:00pm",
      "GameState": "",
      "HomeTeam": "Heracles",
      "HomeGoals": "",
      "HomeLogo": "",
      "AwayTeam": "Telstar",
      "AwayGoals": "",
      "AwayLogo": "",
      "TVChannels": "1:00pm   Heracles vs Telstar"
    },
    {
      "LeagueName": "UEFA Champions League",
      "LeagueLogo": "https://a.espncdn.com/i/leaguelogos/soccer/500/2.png",
      "GameTime": "1:00pm",
      "GameState": "",
      "HomeTeam": "SDC Putten",
      "HomeGoals": "",
      "HomeLogo": "",
      "AwayTeam": "RKC Waalwijk",
      "AwayGoals": "",
      "AwayLogo": "",
      "TVChannels": "1:00pm   SDC Putten vs RKC Waalwijk"
    },
    {
      "LeagueName": "UEFA Champions League",
      "LeagueLogo": "https://a.espncdn.com/i/leaguelogos/soccer/500/2.png",
      "GameTime": "2:00pm",
      "GameState": "",
      "HomeTeam": "Blackpool",
      "HomeGoals": "",
      "HomeLogo": "",
      "AwayTeam": "Blackburn Rovers",
      "AwayGoals": "",
      "AwayLogo": "",
      "TVChannels": "2:00pm   Blackpool vs Blackburn Rovers"
    },
    {
      "LeagueName": "UEFA Champions League",
      "LeagueLogo": "https://a.espncdn.com/i/leaguelogos/soccer/500/2.png",
      "GameTime": "2:00pm",
      "GameState": "",
      "HomeTeam": "Villarreal",
      "HomeGoals": "",
      "HomeLogo": "cdn.livesoccertv.com/images/teams/spain/logos/villarreal.png",
      "AwayTeam": "Tenerife ESPN Deportes ,  ESPN Deportes+ ,  ESP…",
      "AwayGoals": "",
      "AwayLogo": "",
      "TVChannels": ""
    },
    {
      "LeagueName": "UEFA Champions League",
      "LeagueLogo": "https://a.espncdn.com/i/leaguelogos/soccer/500/2.png",
      "GameTime": "10:00pm",
      "GameState": "",
      "HomeTeam": "Las Vegas Lights",
      "HomeGoals": "",
      "HomeLogo": "",
      "AwayTeam": "Orange County SC ESPN Deportes ,  ESPN Deportes+ ,  ESP…   Australia - NPL NorZone   Australia - NPL Queensland   Austria - Regionalliga   Bahrain - Premier League   Brazil - Campeonato Paulista A2   Bulgaria - B Group   China - Super League   Czech Republic - Czech Cup   Ecuador - Primera A   Egypt - Premier League   Europe - UEFA Womens Champions League   Europe - UEFA Youth League   Finland - Kakkonen   Germany - Regionalliga   Indonesia - Liga 1   Jordan - Jordan League   Lithuania - A Lyga   Mexico - Liga de Expansión MX   Morocco - Botola Pro   Paraguay - Primera Division   Russia - Premier League   Saudi Arabia - Pro League   Singapore - Singapore Premier League   South Africa - ABSA Premiership   Switzerland - Schweitzer Pokal   Tunisia - Ligue Professionnelle 1   Turkmenistan - Ýokary Liga   Uzbekistan - Uzbekistan Super League",
      "AwayGoals": "",
      "AwayLogo": "",
      "TVChannels": "10:00pm   Las Vegas Lights vs Orange County SC ESPN Deportes ,  ESPN Deportes+ ,  ESP…   Australia - NPL NorZone   Australia - NPL Queensland   Austria - Regionalliga   Bahrain - Premier League   Brazil - Campeonato Paulista A2   Bulgaria - B Group   China - Super League   Czech Republic - Czech Cup   Ecuador - Primera A   Egypt - Premier League   Europe - UEFA Womens Champions League   Europe - UEFA Youth League   Finland - Kakkonen   Germany - Regionalliga   Indonesia - Liga 1   Jordan - Jordan League   Lithuania - A Lyga   Mexico - Liga de Expansión MX   Morocco - Botola Pro   Paraguay - Primera Division   Russia - Premier League   Saudi Arabia - Pro League   Singapore - Singapore Premier League   South Africa - ABSA Premiership   Switzerland - Schweitzer Pokal   Tunisia - Ligue Professionnelle 1   Turkmenistan - Ýokary Liga   Uzbekistan - Uzbekistan Super League"
    }
  ]
}
