{
  "premier-league": [
    {
        "teamrank": 1,
        "teamname": "Manchester City",
        "teamlogo": "https://a.espncdn.com/i/teamlogos/soccer/500/382.png",
        "played": 36,
        "wins": 26,
        "draws": 5,
        "lossess": 5,
        "goalsfor": 76,
        "goalsagainst": 29,
        "goalsdiff": "+47",
        "points": 83,
        "form": "'WLWWL'"
    },
    {
        "teamrank": 2,
        "teamname": "Manchester United",
        "teamlogo": "https://a.espncdn.com/i/teamlogos/soccer/500/360.png",
        "played": 36,
        "wins": 20,
        "draws": 10,
        "lossess": 6,
        "goalsfor": 70,
        "goalsagainst": 42,
        "goalsdiff": "+28",
        "points": 70,
        "form": "'LLWDW'"
    },
    {
        "teamrank": 3,
        "teamname": "Leicester City",
        "teamlogo": "https://a.espncdn.com/i/teamlogos/soccer/500/375.png",
        "played": 36,
        "wins": 20,
        "draws": 6,
        "lossess": 10,
        "goalsfor": 65,
        "goalsagainst": 44,
        "goalsdiff": "+21",
        "points": 66,
        "form": "'WLDWW'"
    },
    {
        "teamrank": 4,
        "teamname": "Chelsea",
        "teamlogo": "https://a.espncdn.com/i/teamlogos/soccer/500/363.png",
        "played": 36,
        "wins": 18,
        "draws": 10,
        "lossess": 8,
        "goalsfor": 55,
        "goalsagainst": 33,
        "goalsdiff": "+22",
        "points": 64,
        "form": "'LWWWD'"
    },
    {
        "teamrank": 5,
        "teamname": "Liverpool",
        "teamlogo": "https://a.espncdn.com/i/teamlogos/soccer/500/364.png",
        "played": 36,
        "wins": 18,
        "draws": 9,
        "lossess": 9,
        "goalsfor": 63,
        "goalsagainst": 42,
        "goalsdiff": "+21",
        "points": 63,
        "form": "'WWWDD'"
    },
    {
        "teamrank": 6,
        "teamname": "Tottenham Hotspur",
        "teamlogo": "https://a.espncdn.com/i/teamlogos/soccer/500/367.png",
        "played": 36,
        "wins": 17,
        "draws": 8,
        "lossess": 11,
        "goalsfor": 63,
        "goalsagainst": 41,
        "goalsdiff": "+22",
        "points": 59,
        "form": "'WLWWD'"
    },
    {
        "teamrank": 7,
        "teamname": "West Ham United",
        "teamlogo": "https://a.espncdn.com/i/teamlogos/soccer/500/371.png",
        "played": 36,
        "wins": 17,
        "draws": 8,
        "lossess": 11,
        "goalsfor": 56,
        "goalsagainst": 46,
        "goalsdiff": "+10",
        "points": 59,
        "form": "'DLWLL'"
    },
    {
        "teamrank": 8,
        "teamname": "Everton",
        "teamlogo": "https://a.espncdn.com/i/teamlogos/soccer/500/368.png",
        "played": 36,
        "wins": 16,
        "draws": 8,
        "lossess": 12,
        "goalsfor": 46,
        "goalsagainst": 43,
        "goalsdiff": "+3",
        "points": 56,
        "form": "'LDWLW'"
    },
    {
        "teamrank": 9,
        "teamname": "Arsenal",
        "teamlogo": "https://a.espncdn.com/i/teamlogos/soccer/500/359.png",
        "played": 36,
        "wins": 16,
        "draws": 7,
        "lossess": 13,
        "goalsfor": 50,
        "goalsagainst": 38,
        "goalsdiff": "+12",
        "points": 55,
        "form": "'WWWLD'"
    },
    {
        "teamrank": 10,
        "teamname": "Leeds United",
        "teamlogo": "https://a.espncdn.com/i/teamlogos/soccer/500/357.png",
        "played": 36,
        "wins": 16,
        "draws": 5,
        "lossess": 15,
        "goalsfor": 57,
        "goalsagainst": 53,
        "goalsdiff": "+4",
        "points": 53,
        "form": "'WWLDD'"
    },
    {
        "teamrank": 11,
        "teamname": "Aston Villa",
        "teamlogo": "https://a.espncdn.com/i/teamlogos/soccer/500/362.png",
        "played": 36,
        "wins": 14,
        "draws": 7,
        "lossess": 15,
        "goalsfor": 51,
        "goalsagainst": 44,
        "goalsdiff": "+7",
        "points": 49,
        "form": "'LDLWD'"
    },
    {
        "teamrank": 12,
        "teamname": "Wolverhampton Wanderers",
        "teamlogo": "https://a.espncdn.com/i/teamlogos/soccer/500/380.png",
        "played": 36,
        "wins": 12,
        "draws": 9,
        "lossess": 15,
        "goalsfor": 35,
        "goalsagainst": 49,
        "goalsdiff": "-14",
        "points": 45,
        "form": "'LWDLW'"
    },
    {
        "teamrank": 13,
        "teamname": "Crystal Palace",
        "teamlogo": "https://a.espncdn.com/i/teamlogos/soccer/500/384.png",
        "played": 36,
        "wins": 12,
        "draws": 8,
        "lossess": 16,
        "goalsfor": 40,
        "goalsagainst": 61,
        "goalsdiff": "-21",
        "points": 44,
        "form": "'WLWLL'"
    },
    {
        "teamrank": 14,
        "teamname": "Southampton",
        "teamlogo": "https://a.espncdn.com/i/teamlogos/soccer/500/376.png",
        "played": 36,
        "wins": 12,
        "draws": 7,
        "lossess": 17,
        "goalsfor": 47,
        "goalsagainst": 63,
        "goalsdiff": "-16",
        "points": 43,
        "form": "'WWLDL'"
    },
    {
        "teamrank": 15,
        "teamname": "Burnley",
        "teamlogo": "https://a.espncdn.com/i/teamlogos/soccer/500/379.png",
        "played": 36,
        "wins": 10,
        "draws": 9,
        "lossess": 17,
        "goalsfor": 33,
        "goalsagainst": 51,
        "goalsdiff": "-18",
        "points": 39,
        "form": "'LWLWL'"
    },
    {
        "teamrank": 16,
        "teamname": "Newcastle United",
        "teamlogo": "https://a.espncdn.com/i/teamlogos/soccer/500/361.png",
        "played": 36,
        "wins": 10,
        "draws": 9,
        "lossess": 17,
        "goalsfor": 43,
        "goalsagainst": 62,
        "goalsdiff": "-19",
        "points": 39,
        "form": "'LWLDW'"
    },
    {
        "teamrank": 17,
        "teamname": "Brighton & Hove Albion",
        "teamlogo": "https://a.espncdn.com/i/teamlogos/soccer/500/331.png",
        "played": 36,
        "wins": 8,
        "draws": 14,
        "lossess": 14,
        "goalsfor": 37,
        "goalsagainst": 42,
        "goalsdiff": "-5",
        "points": 38,
        "form": "'DLWLD'"
    },
    {
        "teamrank": 18,
        "teamname": "Fulham",
        "teamlogo": "https://a.espncdn.com/i/teamlogos/soccer/500/370.png",
        "played": 36,
        "wins": 5,
        "draws": 12,
        "lossess": 19,
        "goalsfor": 26,
        "goalsagainst": 50,
        "goalsdiff": "-24",
        "points": 27,
        "form": "'LLLDL'"
    },
    {
        "teamrank": 19,
        "teamname": "West Bromwich Albion",
        "teamlogo": "https://a.espncdn.com/i/teamlogos/soccer/500/383.png",
        "played": 36,
        "wins": 5,
        "draws": 11,
        "lossess": 20,
        "goalsfor": 33,
        "goalsagainst": 70,
        "goalsdiff": "-37",
        "points": 26,
        "form": "'LLDDL'"
    },
    {
        "teamrank": 20,
        "teamname": "Sheffield United",
        "teamlogo": "https://a.espncdn.com/i/teamlogos/soccer/500/398.png",
        "played": 36,
        "wins": 6,
        "draws": 2,
        "lossess": 28,
        "goalsfor": 19,
        "goalsagainst": 62,
        "goalsdiff": "-43",
        "points": 20,
        "form": "'WLLWL'"
    }
  ],
  "primera-division": [
    {
        "teamrank": 1,
        "teamname": "Atlético Madrid",
        "teamlogo": "https://a.espncdn.com/i/teamlogos/soccer/500/1068.png",
        "played": 37,
        "wins": 25,
        "draws": 8,
        "lossess": 4,
        "goalsfor": 65,
        "goalsagainst": 24,
        "goalsdiff": "+41",
        "points": 83,
        "form": "'WWDWL'"
    },
    {
        "teamrank": 2,
        "teamname": "Real Madrid",
        "teamlogo": "https://a.espncdn.com/i/teamlogos/soccer/500/86.png",
        "played": 37,
        "wins": 24,
        "draws": 9,
        "lossess": 4,
        "goalsfor": 65,
        "goalsagainst": 27,
        "goalsdiff": "+38",
        "points": 81,
        "form": "'WWDWD'"
    },
    {
        "teamrank": 3,
        "teamname": "Barcelona",
        "teamlogo": "https://a.espncdn.com/i/teamlogos/soccer/500/83.png",
        "played": 37,
        "wins": 23,
        "draws": 7,
        "lossess": 7,
        "goalsfor": 84,
        "goalsagainst": 38,
        "goalsdiff": "+46",
        "points": 76,
        "form": "'LDDWL'"
    },
    {
        "teamrank": 4,
        "teamname": "Sevilla",
        "teamlogo": "https://a.espncdn.com/i/teamlogos/soccer/500/243.png",
        "played": 37,
        "wins": 23,
        "draws": 5,
        "lossess": 9,
        "goalsfor": 52,
        "goalsagainst": 33,
        "goalsdiff": "+19",
        "points": 74,
        "form": "'LWDLW'"
    },
    {
        "teamrank": 5,
        "teamname": "Real Sociedad",
        "teamlogo": "https://a.espncdn.com/i/teamlogos/soccer/500/89.png",
        "played": 37,
        "wins": 16,
        "draws": 11,
        "lossess": 10,
        "goalsfor": 58,
        "goalsagainst": 38,
        "goalsdiff": "+20",
        "points": 59,
        "form": "'WLWLW'"
    },
    {
        "teamrank": 6,
        "teamname": "Real Betis",
        "teamlogo": "https://a.espncdn.com/i/teamlogos/soccer/500/244.png",
        "played": 37,
        "wins": 16,
        "draws": 10,
        "lossess": 11,
        "goalsfor": 47,
        "goalsagainst": 48,
        "goalsdiff": "-1",
        "points": 58,
        "form": "'WDWDD'"
    },
    {
        "teamrank": 7,
        "teamname": "Villarreal",
        "teamlogo": "https://a.espncdn.com/i/teamlogos/soccer/500/102.png",
        "played": 37,
        "wins": 15,
        "draws": 13,
        "lossess": 9,
        "goalsfor": 59,
        "goalsagainst": 42,
        "goalsdiff": "+17",
        "points": 58,
        "form": "'WWLWL'"
    },
    {
        "teamrank": 8,
        "teamname": "Celta de Vigo",
        "teamlogo": "https://a.espncdn.com/i/teamlogos/soccer/500/85.png",
        "played": 37,
        "wins": 14,
        "draws": 11,
        "lossess": 12,
        "goalsfor": 53,
        "goalsagainst": 54,
        "goalsdiff": "-1",
        "points": 53,
        "form": "'WWWWW'"
    },
    {
        "teamrank": 9,
        "teamname": "Athletic Club",
        "teamlogo": "https://a.espncdn.com/i/teamlogos/soccer/500/93.png",
        "played": 37,
        "wins": 11,
        "draws": 13,
        "lossess": 13,
        "goalsfor": 46,
        "goalsagainst": 40,
        "goalsdiff": "+6",
        "points": 46,
        "form": "'LLDWD'"
    },
    {
        "teamrank": 10,
        "teamname": "Granada",
        "teamlogo": "https://a.espncdn.com/i/teamlogos/soccer/500/3747.png",
        "played": 37,
        "wins": 13,
        "draws": 6,
        "lossess": 18,
        "goalsfor": 47,
        "goalsagainst": 65,
        "goalsdiff": "-18",
        "points": 45,
        "form": "'LLLLW'"
    },
    {
        "teamrank": 11,
        "teamname": "Osasuna",
        "teamlogo": "https://a.espncdn.com/i/teamlogos/soccer/500/97.png",
        "played": 37,
        "wins": 11,
        "draws": 11,
        "lossess": 15,
        "goalsfor": 37,
        "goalsagainst": 47,
        "goalsdiff": "-10",
        "points": 44,
        "form": "'LWDLL'"
    },
    {
        "teamrank": 12,
        "teamname": "Cádiz",
        "teamlogo": "https://a.espncdn.com/i/teamlogos/soccer/500/3842.png",
        "played": 37,
        "wins": 11,
        "draws": 10,
        "lossess": 16,
        "goalsfor": 34,
        "goalsagainst": 56,
        "goalsdiff": "-22",
        "points": 43,
        "form": "'LLWWD'"
    },
    {
        "teamrank": 13,
        "teamname": "Valencia",
        "teamlogo": "https://a.espncdn.com/i/teamlogos/soccer/500/94.png",
        "played": 37,
        "wins": 10,
        "draws": 12,
        "lossess": 15,
        "goalsfor": 50,
        "goalsagainst": 53,
        "goalsdiff": "-3",
        "points": 42,
        "form": "'WLWLD'"
    },
    {
        "teamrank": 14,
        "teamname": "Levante",
        "teamlogo": "https://a.espncdn.com/i/teamlogos/soccer/500/1538.png",
        "played": 37,
        "wins": 9,
        "draws": 13,
        "lossess": 15,
        "goalsfor": 44,
        "goalsagainst": 55,
        "goalsdiff": "-11",
        "points": 40,
        "form": "'LDDLL'"
    },
    {
        "teamrank": 15,
        "teamname": "Deportivo Alavés",
        "teamlogo": "https://a.espncdn.com/i/teamlogos/soccer/500/96.png",
        "played": 37,
        "wins": 9,
        "draws": 11,
        "lossess": 17,
        "goalsfor": 36,
        "goalsagainst": 56,
        "goalsdiff": "-20",
        "points": 38,
        "form": "'WWDLD'"
    },
    {
        "teamrank": 16,
        "teamname": "Getafe",
        "teamlogo": "https://a.espncdn.com/i/teamlogos/soccer/500/2922.png",
        "played": 37,
        "wins": 9,
        "draws": 10,
        "lossess": 18,
        "goalsfor": 28,
        "goalsagainst": 43,
        "goalsdiff": "-15",
        "points": 37,
        "form": "'WLLLW'"
    },
    {
        "teamrank": 17,
        "teamname": "Huesca",
        "teamlogo": "https://a.espncdn.com/i/teamlogos/soccer/500/5413.png",
        "played": 37,
        "wins": 7,
        "draws": 12,
        "lossess": 18,
        "goalsfor": 34,
        "goalsagainst": 53,
        "goalsdiff": "-19",
        "points": 33,
        "form": "'LWLWL'"
    },
    {
        "teamrank": 18,
        "teamname": "Elche",
        "teamlogo": "https://a.espncdn.com/i/teamlogos/soccer/500/3751.png",
        "played": 37,
        "wins": 7,
        "draws": 12,
        "lossess": 18,
        "goalsfor": 32,
        "goalsagainst": 55,
        "goalsdiff": "-23",
        "points": 33,
        "form": "'WLLLW'"
    },
    {
        "teamrank": 19,
        "teamname": "Real Valladolid",
        "teamlogo": "https://a.espncdn.com/i/teamlogos/soccer/500/95.png",
        "played": 37,
        "wins": 5,
        "draws": 16,
        "lossess": 16,
        "goalsfor": 33,
        "goalsagainst": 55,
        "goalsdiff": "-22",
        "points": 31,
        "form": "'LLLDD'"
    },
    {
        "teamrank": 20,
        "teamname": "Eibar",
        "teamlogo": "https://a.espncdn.com/i/teamlogos/soccer/500/3752.png",
        "played": 37,
        "wins": 6,
        "draws": 12,
        "lossess": 19,
        "goalsfor": 29,
        "goalsagainst": 51,
        "goalsdiff": "-22",
        "points": 30,
        "form": "'LDWWL'"
    }
  ],
  "serie-a": [
    {
        "teamrank": 1,
        "teamname": "Internazionale",
        "teamlogo": "https://a.espncdn.com/i/teamlogos/soccer/500/110.png",
        "played": 37,
        "wins": 27,
        "draws": 7,
        "lossess": 3,
        "goalsfor": 84,
        "goalsagainst": 34,
        "goalsdiff": "+50",
        "points": 88,
        "form": "'LWWWW'"
    },
    {
        "teamrank": 2,
        "teamname": "Atalanta",
        "teamlogo": "https://a.espncdn.com/i/teamlogos/soccer/500/105.png",
        "played": 37,
        "wins": 23,
        "draws": 9,
        "lossess": 5,
        "goalsfor": 90,
        "goalsagainst": 45,
        "goalsdiff": "+45",
        "points": 78,
        "form": "'WWWDW'"
    },
    {
        "teamrank": 3,
        "teamname": "Milan",
        "teamlogo": "https://a.espncdn.com/i/teamlogos/soccer/500/103.png",
        "played": 37,
        "wins": 23,
        "draws": 7,
        "lossess": 7,
        "goalsfor": 72,
        "goalsagainst": 41,
        "goalsdiff": "+31",
        "points": 76,
        "form": "'DWWWL'"
    },
    {
        "teamrank": 4,
        "teamname": "Napoli",
        "teamlogo": "https://a.espncdn.com/i/teamlogos/soccer/500/114.png",
        "played": 37,
        "wins": 24,
        "draws": 4,
        "lossess": 9,
        "goalsfor": 85,
        "goalsagainst": 40,
        "goalsdiff": "+45",
        "points": 76,
        "form": "'WWWDW'"
    },
    {
        "teamrank": 5,
        "teamname": "Juventus",
        "teamlogo": "https://a.espncdn.com/i/teamlogos/soccer/500/111.png",
        "played": 37,
        "wins": 22,
        "draws": 9,
        "lossess": 6,
        "goalsfor": 73,
        "goalsagainst": 37,
        "goalsdiff": "+36",
        "points": 75,
        "form": "'WWLWD'"
    },
    {
        "teamrank": 6,
        "teamname": "Lazio",
        "teamlogo": "https://a.espncdn.com/i/teamlogos/soccer/500/112.png",
        "played": 36,
        "wins": 21,
        "draws": 4,
        "lossess": 11,
        "goalsfor": 61,
        "goalsagainst": 53,
        "goalsdiff": "+8",
        "points": 67,
        "form": "'LWLWW'"
    },
    {
        "teamrank": 7,
        "teamname": "Roma",
        "teamlogo": "https://a.espncdn.com/i/teamlogos/soccer/500/104.png",
        "played": 37,
        "wins": 18,
        "draws": 7,
        "lossess": 12,
        "goalsfor": 66,
        "goalsagainst": 56,
        "goalsdiff": "+10",
        "points": 61,
        "form": "'WLWLL'"
    },
    {
        "teamrank": 8,
        "teamname": "Sassuolo",
        "teamlogo": "https://a.espncdn.com/i/teamlogos/soccer/500/3997.png",
        "played": 37,
        "wins": 16,
        "draws": 11,
        "lossess": 10,
        "goalsfor": 62,
        "goalsagainst": 56,
        "goalsdiff": "+6",
        "points": 59,
        "form": "'WLWDW'"
    },
    {
        "teamrank": 9,
        "teamname": "Sampdoria",
        "teamlogo": "https://a.espncdn.com/i/teamlogos/soccer/500/2734.png",
        "played": 37,
        "wins": 14,
        "draws": 7,
        "lossess": 16,
        "goalsfor": 49,
        "goalsagainst": 54,
        "goalsdiff": "-5",
        "points": 49,
        "form": "'WDLWL'"
    },
    {
        "teamrank": 10,
        "teamname": "Hellas Verona",
        "teamlogo": "https://a.espncdn.com/i/teamlogos/soccer/500/119.png",
        "played": 36,
        "wins": 11,
        "draws": 10,
        "lossess": 15,
        "goalsfor": 43,
        "goalsagainst": 45,
        "goalsdiff": "-2",
        "points": 43,
        "form": "'LDDLL'"
    },
    {
        "teamrank": 11,
        "teamname": "Bologna",
        "teamlogo": "https://a.espncdn.com/i/teamlogos/soccer/500/107.png",
        "played": 36,
        "wins": 10,
        "draws": 10,
        "lossess": 16,
        "goalsfor": 48,
        "goalsagainst": 59,
        "goalsdiff": "-11",
        "points": 40,
        "form": "'LDDLD'"
    },
    {
        "teamrank": 12,
        "teamname": "Udinese",
        "teamlogo": "https://a.espncdn.com/i/teamlogos/soccer/500/118.png",
        "played": 37,
        "wins": 10,
        "draws": 10,
        "lossess": 17,
        "goalsfor": 41,
        "goalsagainst": 53,
        "goalsdiff": "-12",
        "points": 40,
        "form": "'LLDLW'"
    },
    {
        "teamrank": 13,
        "teamname": "Fiorentina",
        "teamlogo": "https://a.espncdn.com/i/teamlogos/soccer/500/109.png",
        "played": 37,
        "wins": 9,
        "draws": 12,
        "lossess": 16,
        "goalsfor": 47,
        "goalsagainst": 59,
        "goalsdiff": "-12",
        "points": 39,
        "form": "'LDWDD'"
    },
    {
        "teamrank": 14,
        "teamname": "Genoa",
        "teamlogo": "https://a.espncdn.com/i/teamlogos/soccer/500/3263.png",
        "played": 37,
        "wins": 9,
        "draws": 12,
        "lossess": 16,
        "goalsfor": 46,
        "goalsagainst": 58,
        "goalsdiff": "-12",
        "points": 39,
        "form": "'LWLLW'"
    },
    {
        "teamrank": 15,
        "teamname": "Spezia",
        "teamlogo": "https://a.espncdn.com/i/teamlogos/soccer/500/4056.png",
        "played": 37,
        "wins": 9,
        "draws": 11,
        "lossess": 17,
        "goalsfor": 50,
        "goalsagainst": 70,
        "goalsdiff": "-20",
        "points": 38,
        "form": "'WDLDL'"
    },
    {
        "teamrank": 16,
        "teamname": "Cagliari",
        "teamlogo": "https://a.espncdn.com/i/teamlogos/soccer/500/2925.png",
        "played": 37,
        "wins": 9,
        "draws": 10,
        "lossess": 18,
        "goalsfor": 43,
        "goalsagainst": 58,
        "goalsdiff": "-15",
        "points": 37,
        "form": "'DDWDW'"
    },
    {
        "teamrank": 17,
        "teamname": "Torino",
        "teamlogo": "https://a.espncdn.com/i/teamlogos/soccer/500/239.png",
        "played": 36,
        "wins": 7,
        "draws": 14,
        "lossess": 15,
        "goalsfor": 49,
        "goalsagainst": 68,
        "goalsdiff": "-19",
        "points": 35,
        "form": "'LLDWL'"
    },
    {
        "teamrank": 18,
        "teamname": "Benevento",
        "teamlogo": "https://a.espncdn.com/i/teamlogos/soccer/500/4059.png",
        "played": 37,
        "wins": 7,
        "draws": 11,
        "lossess": 19,
        "goalsfor": 39,
        "goalsagainst": 74,
        "goalsdiff": "-35",
        "points": 32,
        "form": "'DLLLL'"
    },
    {
        "teamrank": 19,
        "teamname": "Crotone",
        "teamlogo": "https://a.espncdn.com/i/teamlogos/soccer/500/3173.png",
        "played": 37,
        "wins": 6,
        "draws": 4,
        "lossess": 27,
        "goalsfor": 45,
        "goalsagainst": 92,
        "goalsdiff": "-47",
        "points": 22,
        "form": "'DWLLW'"
    },
    {
        "teamrank": 20,
        "teamname": "Parma",
        "teamlogo": "https://a.espncdn.com/i/teamlogos/soccer/500/115.png",
        "played": 37,
        "wins": 3,
        "draws": 11,
        "lossess": 23,
        "goalsfor": 39,
        "goalsagainst": 80,
        "goalsdiff": "-41",
        "points": 20,
        "form": "'LLLLL'"
    }
  ],
  "ligue-1": [
    {
        "teamrank": 1,
        "teamname": "Lille",
        "teamlogo": "https://a.espncdn.com/i/teamlogos/soccer/500/166.png",
        "played": 37,
        "wins": 23,
        "draws": 11,
        "lossess": 3,
        "goalsfor": 62,
        "goalsagainst": 22,
        "goalsdiff": "+40",
        "points": 80,
        "form": "'DWWWD'"
    },
    {
        "teamrank": 2,
        "teamname": "PSG",
        "teamlogo": "https://a.espncdn.com/i/teamlogos/soccer/500/160.png",
        "played": 37,
        "wins": 25,
        "draws": 4,
        "lossess": 8,
        "goalsfor": 84,
        "goalsagainst": 28,
        "goalsdiff": "+56",
        "points": 79,
        "form": "'WDWWW'"
    },
    {
        "teamrank": 3,
        "teamname": "Monaco",
        "teamlogo": "https://a.espncdn.com/i/teamlogos/soccer/500/174.png",
        "played": 37,
        "wins": 24,
        "draws": 5,
        "lossess": 8,
        "goalsfor": 76,
        "goalsagainst": 42,
        "goalsdiff": "+34",
        "points": 77,
        "form": "'WWLWW'"
    },
    {
        "teamrank": 4,
        "teamname": "Olympique Lyonnais",
        "teamlogo": "https://a.espncdn.com/i/teamlogos/soccer/500/167.png",
        "played": 37,
        "wins": 22,
        "draws": 10,
        "lossess": 5,
        "goalsfor": 79,
        "goalsagainst": 40,
        "goalsdiff": "+39",
        "points": 76,
        "form": "'WWWLW'"
    },
    {
        "teamrank": 5,
        "teamname": "Olympique Marseille",
        "teamlogo": "https://a.espncdn.com/i/teamlogos/soccer/500/176.png",
        "played": 37,
        "wins": 16,
        "draws": 11,
        "lossess": 10,
        "goalsfor": 53,
        "goalsagainst": 46,
        "goalsdiff": "+7",
        "points": 59,
        "form": "'WLDWW'"
    },
    {
        "teamrank": 6,
        "teamname": "Lens",
        "teamlogo": "https://a.espncdn.com/i/teamlogos/soccer/500/175.png",
        "played": 37,
        "wins": 15,
        "draws": 11,
        "lossess": 11,
        "goalsfor": 55,
        "goalsagainst": 54,
        "goalsdiff": "+1",
        "points": 56,
        "form": "'LLLWD'"
    },
    {
        "teamrank": 7,
        "teamname": "Rennes",
        "teamlogo": "https://a.espncdn.com/i/teamlogos/soccer/500/169.png",
        "played": 37,
        "wins": 15,
        "draws": 10,
        "lossess": 12,
        "goalsfor": 50,
        "goalsagainst": 40,
        "goalsdiff": "+10",
        "points": 55,
        "form": "'LDLWW'"
    },
    {
        "teamrank": 8,
        "teamname": "Montpellier",
        "teamlogo": "https://a.espncdn.com/i/teamlogos/soccer/500/274.png",
        "played": 37,
        "wins": 13,
        "draws": 12,
        "lossess": 12,
        "goalsfor": 58,
        "goalsagainst": 61,
        "goalsdiff": "-3",
        "points": 51,
        "form": "'DWLLD'"
    },
    {
        "teamrank": 9,
        "teamname": "Nice",
        "teamlogo": "https://a.espncdn.com/i/teamlogos/soccer/500/2502.png",
        "played": 37,
        "wins": 14,
        "draws": 7,
        "lossess": 16,
        "goalsfor": 47,
        "goalsagainst": 51,
        "goalsdiff": "-4",
        "points": 49,
        "form": "'LWLWL'"
    },
    {
        "teamrank": 10,
        "teamname": "Metz",
        "teamlogo": "https://a.espncdn.com/i/teamlogos/soccer/500/177.png",
        "played": 37,
        "wins": 12,
        "draws": 10,
        "lossess": 15,
        "goalsfor": 43,
        "goalsagainst": 47,
        "goalsdiff": "-4",
        "points": 46,
        "form": "'LLWLD'"
    },
    {
        "teamrank": 11,
        "teamname": "Saint-Étienne",
        "teamlogo": "https://a.espncdn.com/i/teamlogos/soccer/500/178.png",
        "played": 37,
        "wins": 12,
        "draws": 10,
        "lossess": 15,
        "goalsfor": 42,
        "goalsagainst": 53,
        "goalsdiff": "-11",
        "points": 46,
        "form": "'DWWLL'"
    },
    {
        "teamrank": 12,
        "teamname": "Angers SCO",
        "teamlogo": "https://a.espncdn.com/i/teamlogos/soccer/500/7868.png",
        "played": 37,
        "wins": 12,
        "draws": 8,
        "lossess": 17,
        "goalsfor": 39,
        "goalsagainst": 56,
        "goalsdiff": "-17",
        "points": 44,
        "form": "'LWLLL'"
    },
    {
        "teamrank": 13,
        "teamname": "Reims",
        "teamlogo": "https://a.espncdn.com/i/teamlogos/soccer/500/3243.png",
        "played": 37,
        "wins": 9,
        "draws": 15,
        "lossess": 13,
        "goalsfor": 41,
        "goalsagainst": 48,
        "goalsdiff": "-7",
        "points": 42,
        "form": "'LLDLD'"
    },
    {
        "teamrank": 14,
        "teamname": "Bordeaux",
        "teamlogo": "https://a.espncdn.com/i/teamlogos/soccer/500/159.png",
        "played": 37,
        "wins": 12,
        "draws": 6,
        "lossess": 19,
        "goalsfor": 40,
        "goalsagainst": 55,
        "goalsdiff": "-15",
        "points": 42,
        "form": "'WLWLL'"
    },
    {
        "teamrank": 15,
        "teamname": "Strasbourg",
        "teamlogo": "https://a.espncdn.com/i/teamlogos/soccer/500/180.png",
        "played": 37,
        "wins": 11,
        "draws": 8,
        "lossess": 18,
        "goalsfor": 48,
        "goalsagainst": 57,
        "goalsdiff": "-9",
        "points": 41,
        "form": "'WLDLD'"
    },
    {
        "teamrank": 16,
        "teamname": "Brest",
        "teamlogo": "https://a.espncdn.com/i/teamlogos/soccer/500/6997.png",
        "played": 37,
        "wins": 11,
        "draws": 8,
        "lossess": 18,
        "goalsfor": 50,
        "goalsagainst": 64,
        "goalsdiff": "-14",
        "points": 41,
        "form": "'DLLWD'"
    },
    {
        "teamrank": 17,
        "teamname": "Lorient",
        "teamlogo": "https://a.espncdn.com/i/teamlogos/soccer/500/273.png",
        "played": 37,
        "wins": 11,
        "draws": 8,
        "lossess": 18,
        "goalsfor": 49,
        "goalsagainst": 67,
        "goalsdiff": "-18",
        "points": 41,
        "form": "'WLWWL'"
    },
    {
        "teamrank": 18,
        "teamname": "Nantes",
        "teamlogo": "https://a.espncdn.com/i/teamlogos/soccer/500/165.png",
        "played": 37,
        "wins": 9,
        "draws": 13,
        "lossess": 15,
        "goalsfor": 46,
        "goalsagainst": 53,
        "goalsdiff": "-7",
        "points": 40,
        "form": "'WWWWL'"
    },
    {
        "teamrank": 19,
        "teamname": "Nîmes",
        "teamlogo": "https://a.espncdn.com/i/teamlogos/soccer/500/7730.png",
        "played": 37,
        "wins": 9,
        "draws": 8,
        "lossess": 20,
        "goalsfor": 40,
        "goalsagainst": 69,
        "goalsdiff": "-29",
        "points": 35,
        "form": "'LWDLD'"
    },
    {
        "teamrank": 20,
        "teamname": "Dijon",
        "teamlogo": "https://a.espncdn.com/i/teamlogos/soccer/500/3170.png",
        "played": 37,
        "wins": 3,
        "draws": 9,
        "lossess": 25,
        "goalsfor": 24,
        "goalsagainst": 73,
        "goalsdiff": "-49",
        "points": 18,
        "form": "'LLLLW'"
    }
  ],
  "bundesliga": [
    {
        "teamrank": 1,
        "teamname": "Bayern München",
        "teamlogo": "https://a.espncdn.com/i/teamlogos/soccer/500/132.png",
        "played": 33,
        "wins": 23,
        "draws": 6,
        "lossess": 4,
        "goalsfor": 94,
        "goalsagainst": 42,
        "goalsdiff": "+52",
        "points": 75,
        "form": "'DWLWW'"
    },
    {
        "teamrank": 2,
        "teamname": "RB Leipzig",
        "teamlogo": "https://a.espncdn.com/i/teamlogos/soccer/500/11420.png",
        "played": 33,
        "wins": 19,
        "draws": 8,
        "lossess": 6,
        "goalsfor": 59,
        "goalsagainst": 30,
        "goalsdiff": "+29",
        "points": 65,
        "form": "'DLWLD'"
    },
    {
        "teamrank": 3,
        "teamname": "Borussia Dortmund",
        "teamlogo": "https://a.espncdn.com/i/teamlogos/soccer/500/124.png",
        "played": 33,
        "wins": 19,
        "draws": 4,
        "lossess": 10,
        "goalsfor": 72,
        "goalsagainst": 45,
        "goalsdiff": "+27",
        "points": 61,
        "form": "'WWWWW'"
    },
    {
        "teamrank": 4,
        "teamname": "Wolfsburg",
        "teamlogo": "https://a.espncdn.com/i/teamlogos/soccer/500/138.png",
        "played": 33,
        "wins": 17,
        "draws": 10,
        "lossess": 6,
        "goalsfor": 59,
        "goalsagainst": 34,
        "goalsdiff": "+25",
        "points": 61,
        "form": "'DWLWL'"
    },
    {
        "teamrank": 5,
        "teamname": "Eintracht Frankfurt",
        "teamlogo": "https://a.espncdn.com/i/teamlogos/soccer/500/125.png",
        "played": 33,
        "wins": 15,
        "draws": 12,
        "lossess": 6,
        "goalsfor": 66,
        "goalsagainst": 52,
        "goalsdiff": "+14",
        "points": 57,
        "form": "'LDLWL'"
    },
    {
        "teamrank": 6,
        "teamname": "Bayer Leverkusen",
        "teamlogo": "https://a.espncdn.com/i/teamlogos/soccer/500/131.png",
        "played": 33,
        "wins": 14,
        "draws": 10,
        "lossess": 9,
        "goalsfor": 52,
        "goalsagainst": 36,
        "goalsdiff": "+16",
        "points": 52,
        "form": "'DDWLW'"
    },
    {
        "teamrank": 7,
        "teamname": "Union Berlin",
        "teamlogo": "https://a.espncdn.com/i/teamlogos/soccer/500/598.png",
        "played": 33,
        "wins": 11,
        "draws": 14,
        "lossess": 8,
        "goalsfor": 48,
        "goalsagainst": 42,
        "goalsdiff": "+6",
        "points": 47,
        "form": "'DLWLW'"
    }
  ]
}
